raiz/comparador.v
module comparador #(
    parameter ITERS = 8,   // = N/2
    parameter WIDTH = 4
)(
    input  wire [WIDTH-1:0] count,
    output wire             Z
);

    assign Z = (count == ITERS[WIDTH-1:0]) ? 1'b1 : 1'b0;

endmodule

raiz/contador_i.v
module contador_i #(
    parameter WIDTH = 4   // alcanza para contar 0..8 (N/2 con N=16)
)(
    input  wire              clk,
    input  wire              rst,   // = LD
    input  wire              inc,   // = SH
    output reg [WIDTH-1:0]   count
);

    always @(negedge clk) begin
        if (rst)
            count <= {WIDTH{1'b0}};
        else if (inc)
            count <= count + 1'b1;
    end

endmodule

raiz/Ultimo/sumador.v
module sumador #(
    parameter PW      = 8,
    parameter RE_WIDTH = 10
)(
    input  wire [RE_WIDTH-1:0] Re,
    input  wire [PW-1:0]       Co,
    output wire [RE_WIDTH-1:0] sub_result,
    output wire                Sumf
);

    wire [RE_WIDTH-1:0] trial;
    wire [RE_WIDTH:0]   diff;

    assign trial      = {{(RE_WIDTH-PW-1){1'b0}}, Co, 1'b1};
    assign diff        = {1'b0, Re} - {1'b0, trial};
    assign sub_result  = diff[RE_WIDTH-1:0];
    assign Sumf        = ~diff[RE_WIDTH];   // 1 = Re>=trial (sin prestamo)

endmodule

raiz/Ultimo/reg_co.v
module reg_co #(
    parameter PW = 8
)(
    input  wire            clk,
    input  wire            LDC,
    input  wire [PW-1:0]   p_in,
    output reg  [PW-1:0]   Co
);

    always @(negedge clk) begin
        if (LDC)
            Co <= p_in;
    end

endmodule

raiz/Ultimo/reg_p.v
module reg_p #(
    parameter PW = 8    // ancho de P = N/2
)(
    input  wire            clk,
    input  wire            LD,
    input  wire            SH,
    input  wire            LDR,
    input  wire            Ne,     // valor del nuevo bit (1 o 0)
    output reg  [PW-1:0]   P
);

    always @(negedge clk) begin
        if (LD)
            P <= {PW{1'b0}};
        else if (SH)
            P <= P << 1;
        else if (LDR)
            P[0] <= Ne;
    end

endmodule

raiz/Ultimo/reg_re_a.v
module reg_re_a #(
    parameter N        = 16,
    parameter RE_WIDTH = 10
)(
    input  wire                   clk,
    input  wire                   LD,
    input  wire                   SH,
    input  wire                   Ne,
    input  wire [N-1:0]           a_in,
    input  wire [RE_WIDTH-1:0]    sub_result,
    output reg  [RE_WIDTH-1:0]    Re,
    output reg  [N-1:0]           A
);

    always @(negedge clk) begin
        if (LD) begin
            A  <= a_in;
            Re <= {RE_WIDTH{1'b0}};
        end else if (SH) begin
            {Re, A} <= {Re, A} << 2;
        end else if (Ne) begin
            Re <= sub_result;
        end
    end

endmodule

raiz/Ultimo/datapath.v
module datapath #(
    parameter N         = 16,
    parameter PW        = 8,          // N/2
    parameter RE_WIDTH  = 10,         // N/2 + 2
    parameter CNT_WIDTH = 4
)(
    input  wire             clk,
    input  wire [N-1:0]     a,
    input  wire             LD,
    input  wire             SH,
    input  wire             LDC,
    input  wire             LDR,
    input  wire             Ne,
    output wire              Sumf,   
    output wire              Z,      
    output wire [PW-1:0]     P,      // raiz
    output wire [RE_WIDTH-1:0] Rem   // residuo 
);

    wire [N-1:0]         A_reg;
    wire [PW-1:0]        Co;
    wire [RE_WIDTH-1:0]  sub_result;
    wire [CNT_WIDTH-1:0] count;

    reg_re_a #(.N(N), .RE_WIDTH(RE_WIDTH)) u_reg_re_a (
        .clk        (clk),
        .LD         (LD),
        .SH         (SH),
        .Ne         (Ne),
        .a_in       (a),
        .sub_result (sub_result),
        .Re         (Rem),
        .A          (A_reg)
    );

    reg_p #(.PW(PW)) u_reg_p (
        .clk (clk),
        .LD  (LD),
        .SH  (SH),
        .LDR (LDR),
        .Ne  (Ne),
        .P   (P)
    );

    reg_co #(.PW(PW)) u_reg_co (
        .clk  (clk),
        .LDC  (LDC),
        .p_in (P),
        .Co   (Co)
    );

    sumador #(.PW(PW), .RE_WIDTH(RE_WIDTH)) u_sumador (
        .Re         (Rem),
        .Co         (Co),
        .sub_result (sub_result),
        .Sumf       (Sumf)
    );

    contador_i #(.WIDTH(CNT_WIDTH)) u_contador_i (
        .clk   (clk),
        .rst   (LD),
        .inc   (SH),
        .count (count)
    );

    comparador #(.ITERS(PW), .WIDTH(CNT_WIDTH)) u_comparador (
        .count (count),
        .Z     (Z)
    );

endmodule

raiz/Ultimo/control.v
module control (
    input  wire clk,
    input  wire rst,     // reset 
    input  wire start,
    input  wire Sumf,
    input  wire Z,
    output reg  LD,
    output reg  SH,
    output reg  LDC,
    output reg  LDR,
    output reg  Ne,
    output reg  DONE
);

    localparam [2:0]
        START  = 3'b000,
        STAD1  = 3'b001,
        STAD2  = 3'b010,
        CHECK1 = 3'b011,
        CHECK2 = 3'b100,
        ENDST  = 3'b101;

    reg [2:0] state, next_state;

    
    always @(posedge clk or posedge rst) begin
        if (rst)
            state <= START;
        else
            state <= next_state;
    end

    always @(*) begin
        case (state)
            START:  next_state = start ? STAD1 : START;
            STAD1:  next_state = STAD2;
            STAD2:  next_state = Sumf ? CHECK1 : CHECK2;
            CHECK1: next_state = Z ? ENDST : STAD1;
            CHECK2: next_state = Z ? ENDST : STAD1;
            ENDST:  next_state = start ? START : ENDST;
            default: next_state = START;
        endcase
    end

    always @(*) begin
        LD   = 1'b0;
        SH   = 1'b0;
        LDC  = 1'b0;
        LDR  = 1'b0;
        Ne   = 1'b0;
        DONE = 1'b0;
        case (state)
            START:  LD  = 1'b1;
            STAD1:  SH  = 1'b1;
            STAD2:  LDC = 1'b1;
            CHECK1: begin LDR = 1'b1; Ne = 1'b1; end
            CHECK2: begin LDR = 1'b1; Ne = 1'b0; end
            ENDST:  DONE = 1'b1;
            default: ;
        endcase
    end

endmodule

raiz/raiz_top.v
module raiz_top #(
    parameter N         = 16,
    parameter PW        = 8,     // N/2
    parameter RE_WIDTH  = 10,    // N/2 + 2
    parameter CNT_WIDTH = 4
)(
    input  wire                 clk,
    input  wire                 rst,
    input  wire                 start,
    input  wire [N-1:0]         a,
    output wire [PW-1:0]        P,      // raiz
    output wire [RE_WIDTH-1:0]  Rem,    // residuo
    output wire                 DONE
);

    wire LD, SH, LDC, LDR, Ne;
    wire Sumf, Z;

    control u_control (
        .clk   (clk),
        .rst   (rst),
        .start (start),
        .Sumf  (Sumf),
        .Z     (Z),
        .LD    (LD),
        .SH    (SH),
        .LDC   (LDC),
        .LDR   (LDR),
        .Ne    (Ne),
        .DONE  (DONE)
    );

    datapath #(.N(N), .PW(PW), .RE_WIDTH(RE_WIDTH), .CNT_WIDTH(CNT_WIDTH)) u_datapath (
        .clk  (clk),
        .a    (a),
        .LD   (LD),
        .SH   (SH),
        .LDC  (LDC),
        .LDR  (LDR),
        .Ne   (Ne),
        .Sumf (Sumf),
        .Z    (Z),
        .P    (P),
        .Rem  (Rem)
    );

endmodule

raiz/Ultimo/raiz_top_TB.v
module tb_raiz;

    parameter N         = 16;
    parameter PW        = 8;
    parameter RE_WIDTH  = 10;
    parameter CNT_WIDTH = 4;

    reg              clk;
    reg              rst;
    reg              start;
    reg  [N-1:0]     a;
    wire [PW-1:0]        P;
    wire [RE_WIDTH-1:0]  Rem;
    wire                 DONE;

    integer errors = 0;
    integer tests  = 0;

    raiz_top #(.N(N), .PW(PW), .RE_WIDTH(RE_WIDTH), .CNT_WIDTH(CNT_WIDTH)) uut (
        .clk   (clk),
        .rst   (rst),
        .start (start),
        .a     (a),
        .P     (P),
        .Rem   (Rem),
        .DONE  (DONE)
    );

    initial clk = 1'b0;
    always #5 clk = ~clk;

    function integer isqrt(input integer val);
        integer p;
        begin
            p = 0;
            while ((p+1)*(p+1) <= val)
                p = p + 1;
            isqrt = p;
        end
    endfunction

    task run_test(input [N-1:0] ta);
        integer expected_p, expected_rem;
        begin
            tests        = tests + 1;
            expected_p   = isqrt(ta);
            expected_rem = ta - expected_p*expected_p;

            a = ta;
            start = 1'b0;
            @(posedge clk);

            // Pulso de start de 2 ciclos: cubre ENDST->START->STAD1
            start = 1'b1;
            @(posedge clk);
            @(posedge clk);
            start = 1'b0;

            // Espera a que la FSM llegue al estado END
            wait (DONE == 1'b1);
            @(posedge clk);

            if (P !== expected_p[PW-1:0] || Rem !== expected_rem[RE_WIDTH-1:0]) begin
                $display("FALLO: a=%0d -> P=%0d Rem=%0d (esperado P=%0d Rem=%0d)",
                          ta, P, Rem, expected_p, expected_rem);
                errors = errors + 1;
            end else begin
                $display("OK   : a=%0d -> P=%0d Rem=%0d", ta, P, Rem);
            end

            // Deja pasar un ciclo en ENDST y vuelve a START
            @(posedge clk);
        end
    endtask

    initial begin
        $dumpfile("raiz_top_TB.vcd");
        $dumpvars(0, tb_raiz);

        rst   = 1'b1;
        start = 1'b0;
        a = 0;
        repeat (2) @(posedge clk);
        rst = 1'b0;
        @(posedge clk);

        run_test(16'd0);      // 0    -> P=0   Rem=0
        run_test(16'd1);      // 1    -> P=1   Rem=0
        run_test(16'd144);    // 144  -> P=12  Rem=0  (cuadrado perfecto)
        run_test(16'd150);    // 150  -> P=12  Rem=6  (no perfecto)
        run_test(16'd65535);  // max  -> P=255 Rem=254
        run_test(16'd255);    // 255  -> P=15  Rem=30
        run_test(16'd65025);  // 255^2 = 65025 -> P=255 Rem=0
        run_test(16'd2);      // 2    -> P=1   Rem=1
        run_test(16'd10000);  // 100^2 = 10000 -> P=100 Rem=0

        $display("--------------------------------------------------");
        if (errors == 0)
            $display("TODAS LAS PRUEBAS PASARON (%0d/%0d)", tests, tests);
        else
            $display("%0d DE %0d PRUEBAS FALLARON", errors, tests);

        $finish;
    end

endmodule

raiz/Ultimo/raiz_top_TB.vcd
$date
	Thu Jul 16 13:49:32 2026
$end
$version
	Icarus Verilog
$end
$timescale
	1ps
$end
$scope module tb_raiz $end
$var wire 10 ! Rem [9:0] $end
$var wire 8 " P [7:0] $end
$var wire 1 # DONE $end
$var parameter 32 $ CNT_WIDTH $end
$var parameter 32 % N $end
$var parameter 32 & PW $end
$var parameter 32 ' RE_WIDTH $end
$var reg 16 ( a [15:0] $end
$var reg 1 ) clk $end
$var reg 1 * rst $end
$var reg 1 + start $end
$var integer 32 , errors [31:0] $end
$var integer 32 - tests [31:0] $end
$scope function isqrt $end
$var integer 32 . p [31:0] $end
$var integer 32 / val [31:0] $end
$upscope $end
$scope module uut $end
$var wire 16 0 a [15:0] $end
$var wire 1 ) clk $end
$var wire 1 * rst $end
$var wire 1 + start $end
$var wire 1 1 Z $end
$var wire 1 2 Sumf $end
$var wire 1 3 SH $end
$var wire 10 4 Rem [9:0] $end
$var wire 8 5 P [7:0] $end
$var wire 1 6 Ne $end
$var wire 1 7 LDR $end
$var wire 1 8 LDC $end
$var wire 1 9 LD $end
$var wire 1 # DONE $end
$var parameter 32 : CNT_WIDTH $end
$var parameter 32 ; N $end
$var parameter 32 < PW $end
$var parameter 32 = RE_WIDTH $end
$scope module u_control $end
$var wire 1 ) clk $end
$var wire 1 * rst $end
$var wire 1 + start $end
$var wire 1 1 Z $end
$var wire 1 2 Sumf $end
$var parameter 3 > CHECK1 $end
$var parameter 3 ? CHECK2 $end
$var parameter 3 @ ENDST $end
$var parameter 3 A STAD1 $end
$var parameter 3 B STAD2 $end
$var parameter 3 C START $end
$var reg 1 # DONE $end
$var reg 1 9 LD $end
$var reg 1 8 LDC $end
$var reg 1 7 LDR $end
$var reg 1 6 Ne $end
$var reg 1 3 SH $end
$var reg 3 D next_state [2:0] $end
$var reg 3 E state [2:0] $end
$upscope $end
$scope module u_datapath $end
$var wire 1 9 LD $end
$var wire 1 8 LDC $end
$var wire 1 7 LDR $end
$var wire 1 6 Ne $end
$var wire 1 3 SH $end
$var wire 16 F a [15:0] $end
$var wire 1 ) clk $end
$var wire 10 G sub_result [9:0] $end
$var wire 4 H count [3:0] $end
$var wire 1 1 Z $end
$var wire 1 2 Sumf $end
$var wire 10 I Rem [9:0] $end
$var wire 8 J P [7:0] $end
$var wire 8 K Co [7:0] $end
$var wire 16 L A_reg [15:0] $end
$var parameter 32 M CNT_WIDTH $end
$var parameter 32 N N $end
$var parameter 32 O PW $end
$var parameter 32 P RE_WIDTH $end
$scope module u_comparador $end
$var wire 4 Q count [3:0] $end
$var wire 1 1 Z $end
$var parameter 32 R ITERS $end
$var parameter 32 S WIDTH $end
$upscope $end
$scope module u_contador_i $end
$var wire 1 ) clk $end
$var wire 1 3 inc $end
$var wire 1 9 rst $end
$var parameter 32 T WIDTH $end
$var reg 4 U count [3:0] $end
$upscope $end
$scope module u_reg_co $end
$var wire 1 8 LDC $end
$var wire 1 ) clk $end
$var wire 8 V p_in [7:0] $end
$var parameter 32 W PW $end
$var reg 8 X Co [7:0] $end
$upscope $end
$scope module u_reg_p $end
$var wire 1 9 LD $end
$var wire 1 7 LDR $end
$var wire 1 6 Ne $end
$var wire 1 3 SH $end
$var wire 1 ) clk $end
$var parameter 32 Y PW $end
$var reg 8 Z P [7:0] $end
$upscope $end
$scope module u_reg_re_a $end
$var wire 1 9 LD $end
$var wire 1 6 Ne $end
$var wire 1 3 SH $end
$var wire 16 [ a_in [15:0] $end
$var wire 1 ) clk $end
$var wire 10 \ sub_result [9:0] $end
$var parameter 32 ] N $end
$var parameter 32 ^ RE_WIDTH $end
$var reg 16 _ A [15:0] $end
$var reg 10 ` Re [9:0] $end
$upscope $end
$scope module u_sumador $end
$var wire 8 a Co [7:0] $end
$var wire 10 b Re [9:0] $end
$var wire 1 2 Sumf $end
$var wire 10 c trial [9:0] $end
$var wire 10 d sub_result [9:0] $end
$var wire 11 e diff [10:0] $end
$var parameter 32 f PW $end
$var parameter 32 g RE_WIDTH $end
$upscope $end
$upscope $end
$upscope $end
$scope task run_test $end
$var reg 16 h ta [15:0] $end
$var integer 32 i expected_p [31:0] $end
$var integer 32 j expected_rem [31:0] $end
$upscope $end
$upscope $end
$enddefinitions $end
$comment Show the parameter values. $end
$dumpall
b1010 g
b1000 f
b1010 ^
b10000 ]
b1000 Y
b1000 W
b100 T
b100 S
b1000 R
b1010 P
b1000 O
b10000 N
b100 M
b0 C
b10 B
b1 A
b101 @
b100 ?
b11 >
b1010 =
b1000 <
b10000 ;
b100 :
b1010 '
b1000 &
b10000 %
b100 $
$end
#0
$dumpvars
bx j
bx i
bx h
bx e
bx d
b0xxxxxxxx1 c
bx b
bx a
bx `
bx _
bx \
b0 [
bx Z
bx X
bx V
bx U
bx Q
bx L
bx K
bx J
bx I
bx H
bx G
b0 F
b0 E
b0 D
19
08
07
06
bx 5
bx 4
03
x2
x1
b0 0
bx /
bx .
b0 -
b0 ,
0+
1*
0)
b0 (
0#
bx "
bx !
$end
#5000
1)
#10000
01
b0 H
b0 Q
b0 U
b0 "
b0 5
b0 J
b0 V
b0 Z
b0 !
b0 4
b0 I
b0 `
b0 b
b0 L
b0 _
0)
#15000
0*
1)
#20000
0)
#25000
b0 j
b0 i
b0 .
b0 /
b1 -
b0 h
1)
#30000
0)
#35000
b1 D
1+
1)
#40000
0)
#45000
13
09
b10 D
b1 E
1)
#50000
b1 H
b1 Q
b1 U
0)
#55000
18
03
bx D
b10 E
0+
1)
#60000
b100 D
02
b1111111111 G
b1111111111 \
b1111111111 d
b11111111111 e
b1 c
b0 K
b0 X
b0 a
0)
#65000
17
08
b1 D
b100 E
1)
#70000
0)
#75000
13
07
b10 D
b1 E
1)
#80000
b10 H
b10 Q
b10 U
0)
#85000
18
03
b100 D
b10 E
1)
#90000
0)
#95000
17
08
b1 D
b100 E
1)
#100000
0)
#105000
13
07
b10 D
b1 E
1)
#110000
b11 H
b11 Q
b11 U
0)
#115000
18
03
b100 D
b10 E
1)
#120000
0)
#125000
17
08
b1 D
b100 E
1)
#130000
0)
#135000
13
07
b10 D
b1 E
1)
#140000
b100 H
b100 Q
b100 U
0)
#145000
18
03
b100 D
b10 E
1)
#150000
0)
#155000
17
08
b1 D
b100 E
1)
#160000
0)
#165000
13
07
b10 D
b1 E
1)
#170000
b101 H
b101 Q
b101 U
0)
#175000
18
03
b100 D
b10 E
1)
#180000
0)
#185000
17
08
b1 D
b100 E
1)
#190000
0)
#195000
13
07
b10 D
b1 E
1)
#200000
b110 H
b110 Q
b110 U
0)
#205000
18
03
b100 D
b10 E
1)
#210000
0)
#215000
17
08
b1 D
b100 E
1)
#220000
0)
#225000
13
07
b10 D
b1 E
1)
#230000
b111 H
b111 Q
b111 U
0)
#235000
18
03
b100 D
b10 E
1)
#240000
0)
#245000
17
08
b1 D
b100 E
1)
#250000
0)
#255000
13
07
b10 D
b1 E
1)
#260000
11
b1000 H
b1000 Q
b1000 U
0)
#265000
18
03
b100 D
b10 E
1)
#270000
0)
#275000
17
08
b101 D
b100 E
1)
#280000
0)
#285000
1#
07
b101 E
1)
#290000
0)
#295000
1)
#300000
0)
#305000
b1 (
b1 0
b1 F
b1 [
b1 i
b1 .
b1 /
b10 -
b1 h
1)
#310000
0)
#315000
b0 D
1+
1)
#320000
0)
#325000
19
0#
b1 D
b0 E
1)
#330000
01
b0 H
b0 Q
b0 U
b1 L
b1 _
0)
#335000
13
09
b1 E
b10 D
0+
1)
#340000
b100 L
b100 _
b1 H
b1 Q
b1 U
0)
#345000
18
03
b100 D
b10 E
1)
#350000
0)
#355000
17
08
b1 D
b100 E
1)
#360000
0)
#365000
13
07
b10 D
b1 E
1)
#370000
b10 H
b10 Q
b10 U
b10000 L
b10000 _
0)
#375000
18
03
b100 D
b10 E
1)
#380000
0)
#385000
17
08
b1 D
b100 E
1)
#390000
0)
#395000
13
07
b10 D
b1 E
1)
#400000
b1000000 L
b1000000 _
b11 H
b11 Q
b11 U
0)
#405000
18
03
b100 D
b10 E
1)
#410000
0)
#415000
17
08
b1 D
b100 E
1)
#420000
0)
#425000
13
07
b10 D
b1 E
1)
#430000
b100 H
b100 Q
b100 U
b100000000 L
b100000000 _
0)
#435000
18
03
b100 D
b10 E
1)
#440000
0)
#445000
17
08
b1 D
b100 E
1)
#450000
0)
#455000
13
07
b10 D
b1 E
1)
#460000
b10000000000 L
b10000000000 _
b101 H
b101 Q
b101 U
0)
#465000
18
03
b100 D
b10 E
1)
#470000
0)
#475000
17
08
b1 D
b100 E
1)
#480000
0)
#485000
13
07
b10 D
b1 E
1)
#490000
b110 H
b110 Q
b110 U
b1000000000000 L
b1000000000000 _
0)
#495000
18
03
b100 D
b10 E
1)
#500000
0)
#505000
17
08
b1 D
b100 E
1)
#510000
0)
#515000
13
07
b10 D
b1 E
1)
#520000
b100000000000000 L
b100000000000000 _
b111 H
b111 Q
b111 U
0)
#525000
18
03
b100 D
b10 E
1)
#530000
0)
#535000
17
08
b1 D
b100 E
1)
#540000
0)
#545000
13
07
b10 D
b1 E
1)
#550000
12
11
b0 G
b0 \
b0 d
b1000 H
b1000 Q
b1000 U
b0 e
b1 !
b1 4
b1 I
b1 `
b1 b
b0 L
b0 _
0)
#555000
18
03
b11 D
b10 E
1)
#560000
0)
#565000
16
17
08
b101 D
b11 E
1)
#570000
02
b1111111111 G
b1111111111 \
b1111111111 d
b1 "
b1 5
b1 J
b1 V
b1 Z
b11111111111 e
b0 !
b0 4
b0 I
b0 `
b0 b
0)
#575000
1#
06
07
b101 E
1)
#580000
0)
#585000
1)
#590000
0)
#595000
b10010000 (
b10010000 0
b10010000 F
b10010000 [
b1100 i
b1100 .
b10010000 /
b11 -
b10010000 h
1)
#600000
0)
#605000
b0 D
1+
1)
#610000
0)
#615000
19
0#
b1 D
b0 E
1)
#620000
01
b10010000 L
b10010000 _
b0 "
b0 5
b0 J
b0 V
b0 Z
b0 H
b0 Q
b0 U
0)
#625000
13
09
b1 E
b10 D
0+
1)
#630000
b1 H
b1 Q
b1 U
b1001000000 L
b1001000000 _
0)
#635000
18
03
b100 D
b10 E
1)
#640000
0)
#645000
17
08
b1 D
b100 E
1)
#650000
0)
#655000
13
07
b10 D
b1 E
1)
#660000
b100100000000 L
b100100000000 _
b10 H
b10 Q
b10 U
0)
#665000
18
03
b100 D
b10 E
1)
#670000
0)
#675000
17
08
b1 D
b100 E
1)
#680000
0)
#685000
13
07
b10 D
b1 E
1)
#690000
b11 H
b11 Q
b11 U
b10010000000000 L
b10010000000000 _
0)
#695000
18
03
b100 D
b10 E
1)
#700000
0)
#705000
17
08
b1 D
b100 E
1)
#710000
0)
#715000
13
07
b10 D
b1 E
1)
#720000
b1001000000000000 L
b1001000000000000 _
b100 H
b100 Q
b100 U
0)
#725000
18
03
b100 D
b10 E
1)
#730000
0)
#735000
17
08
b1 D
b100 E
1)
#740000
0)
#745000
13
07
b10 D
b1 E
1)
#750000
12
b1 G
b1 \
b1 d
b101 H
b101 Q
b101 U
b1 e
b10 !
b10 4
b10 I
b10 `
b10 b
b100000000000000 L
b100000000000000 _
0)
#755000
18
03
b11 D
b10 E
1)
#760000
0)
#765000
16
17
08
b1 D
b11 E
1)
#770000
b0 G
b0 \
b0 d
b1 "
b1 5
b1 J
b1 V
b1 Z
b0 e
b1 !
b1 4
b1 I
b1 `
b1 b
0)
#775000
13
06
07
b10 D
b1 E
1)
#780000
b100 G
b100 \
b100 d
b100 e
b101 !
b101 4
b101 I
b101 `
b101 b
b0 L
b0 _
b10 "
b10 5
b10 J
b10 V
b10 Z
b110 H
b110 Q
b110 U
0)
#785000
18
03
b11 D
b10 E
1)
#790000
b0 G
b0 \
b0 d
b0 e
b101 c
b10 K
b10 X
b10 a
0)
#795000
16
17
08
b1 D
b11 E
1)
#800000
02
b1111111011 G
b1111111011 \
b1111111011 d
b11111111011 e
b0 !
b0 4
b0 I
b0 `
b0 b
b11 "
b11 5
b11 J
b11 V
b11 Z
0)
#805000
13
06
07
b10 D
b1 E
1)
#810000
b111 H
b111 Q
b111 U
b110 "
b110 5
b110 J
b110 V
b110 Z
0)
#815000
18
03
b100 D
b10 E
1)
#820000
b1111110011 G
b1111110011 \
b1111110011 d
b11111110011 e
b1101 c
b110 K
b110 X
b110 a
0)
#825000
17
08
b1 D
b100 E
1)
#830000
0)
#835000
13
07
b10 D
b1 E
1)
#840000
11
b1100 "
b1100 5
b1100 J
b1100 V
b1100 Z
b1000 H
b1000 Q
b1000 U
0)
#845000
18
03
b100 D
b10 E
1)
#850000
b1111100111 G
b1111100111 \
b1111100111 d
b11111100111 e
b11001 c
b1100 K
b1100 X
b1100 a
0)
#855000
17
08
b101 D
b100 E
1)
#860000
0)
#865000
1#
07
b101 E
1)
#870000
0)
#875000
1)
#880000
0)
#885000
b10010110 (
b10010110 0
b10010110 F
b10010110 [
b110 j
b1100 .
b10010110 /
b100 -
b10010110 h
1)
#890000
0)
#895000
b0 D
1+
1)
#900000
0)
#905000
19
0#
b1 D
b0 E
1)
#910000
01
b0 H
b0 Q
b0 U
b0 "
b0 5
b0 J
b0 V
b0 Z
b10010110 L
b10010110 _
0)
#915000
13
09
b1 E
b10 D
0+
1)
#920000
b1001011000 L
b1001011000 _
b1 H
b1 Q
b1 U
0)
#925000
18
03
b100 D
b10 E
1)
#930000
b1111111111 G
b1111111111 \
b1111111111 d
b11111111111 e
b1 c
b0 K
b0 X
b0 a
0)
#935000
17
08
b1 D
b100 E
1)
#940000
0)
#945000
13
07
b10 D
b1 E
1)
#950000
b10 H
b10 Q
b10 U
b100101100000 L
b100101100000 _
0)
#955000
18
03
b100 D
b10 E
1)
#960000
0)
#965000
17
08
b1 D
b100 E
1)
#970000
0)
#975000
13
07
b10 D
b1 E
1)
#980000
b10010110000000 L
b10010110000000 _
b11 H
b11 Q
b11 U
0)
#985000
18
03
b100 D
b10 E
1)
#990000
0)
#995000
17
08
b1 D
b100 E
1)
#1000000
0)
#1005000
13
07
b10 D
b1 E
1)
#1010000
b100 H
b100 Q
b100 U
b1001011000000000 L
b1001011000000000 _
0)
#1015000
18
03
b100 D
b10 E
1)
#1020000
0)
#1025000
17
08
b1 D
b100 E
1)
#1030000
0)
#1035000
13
07
b10 D
b1 E
1)
#1040000
12
b1 G
b1 \
b1 d
b1 e
b10 !
b10 4
b10 I
b10 `
b10 b
b101100000000000 L
b101100000000000 _
b101 H
b101 Q
b101 U
0)
#1045000
18
03
b11 D
b10 E
1)
#1050000
0)
#1055000
16
17
08
b1 D
b11 E
1)
#1060000
b0 G
b0 \
b0 d
b0 e
b1 !
b1 4
b1 I
b1 `
b1 b
b1 "
b1 5
b1 J
b1 V
b1 Z
0)
#1065000
13
06
07
b10 D
b1 E
1)
#1070000
b100 G
b100 \
b100 d
b110 H
b110 Q
b110 U
b10 "
b10 5
b10 J
b10 V
b10 Z
b100 e
b101 !
b101 4
b101 I
b101 `
b101 b
b110000000000000 L
b110000000000000 _
0)
#1075000
18
03
b11 D
b10 E
1)
#1080000
b0 G
b0 \
b0 d
b0 e
b101 c
b10 K
b10 X
b10 a
0)
#1085000
16
17
08
b1 D
b11 E
1)
#1090000
02
b1111111011 G
b1111111011 \
b1111111011 d
b11 "
b11 5
b11 J
b11 V
b11 Z
b11111111011 e
b0 !
b0 4
b0 I
b0 `
b0 b
0)
#1095000
13
06
07
b10 D
b1 E
1)
#1100000
b1111111100 G
b1111111100 \
b1111111100 d
b11111111100 e
b1 !
b1 4
b1 I
b1 `
b1 b
b1000000000000000 L
b1000000000000000 _
b110 "
b110 5
b110 J
b110 V
b110 Z
b111 H
b111 Q
b111 U
0)
#1105000
18
03
b100 D
b10 E
1)
#1110000
b1111110100 G
b1111110100 \
b1111110100 d
b11111110100 e
b1101 c
b110 K
b110 X
b110 a
0)
#1115000
17
08
b1 D
b100 E
1)
#1120000
0)
#1125000
13
07
b10 D
b1 E
1)
#1130000
11
b1111111001 G
b1111111001 \
b1111111001 d
b1000 H
b1000 Q
b1000 U
b1100 "
b1100 5
b1100 J
b1100 V
b1100 Z
b11111111001 e
b110 !
b110 4
b110 I
b110 `
b110 b
b0 L
b0 _
0)
#1135000
18
03
b100 D
b10 E
1)
#1140000
b1111101101 G
b1111101101 \
b1111101101 d
b11111101101 e
b11001 c
b1100 K
b1100 X
b1100 a
0)
#1145000
17
08
b101 D
b100 E
1)
#1150000
0)
#1155000
1#
07
b101 E
1)
#1160000
0)
#1165000
1)
#1170000
0)
#1175000
b1111111111111111 (
b1111111111111111 0
b1111111111111111 F
b1111111111111111 [
b111111110 j
b11111111 i
b11111111 .
b1111111111111111 /
b101 -
b1111111111111111 h
1)
#1180000
0)
#1185000
b0 D
1+
1)
#1190000
0)
#1195000
19
0#
b1 D
b0 E
1)
#1200000
b1111100111 G
b1111100111 \
b1111100111 d
01
b11111100111 e
b0 !
b0 4
b0 I
b0 `
b0 b
b1111111111111111 L
b1111111111111111 _
b0 "
b0 5
b0 J
b0 V
b0 Z
b0 H
b0 Q
b0 U
0)
#1205000
13
09
b1 E
b10 D
0+
1)
#1210000
b1111101010 G
b1111101010 \
b1111101010 d
b1 H
b1 Q
b1 U
b11111101010 e
b11 !
b11 4
b11 I
b11 `
b11 b
b1111111111111100 L
b1111111111111100 _
0)
#1215000
18
03
b100 D
b10 E
1)
#1220000
b11 D
12
b10 G
b10 \
b10 d
b10 e
b1 c
b0 K
b0 X
b0 a
0)
#1225000
16
17
08
b1 D
b11 E
1)
#1230000
b1 G
b1 \
b1 d
b1 "
b1 5
b1 J
b1 V
b1 Z
b1 e
b10 !
b10 4
b10 I
b10 `
b10 b
0)
#1235000
13
06
07
b10 D
b1 E
1)
#1240000
b1010 G
b1010 \
b1010 d
b1010 e
b1011 !
b1011 4
b1011 I
b1011 `
b1011 b
b1111111111110000 L
b1111111111110000 _
b10 "
b10 5
b10 J
b10 V
b10 Z
b10 H
b10 Q
b10 U
0)
#1245000
18
03
b11 D
b10 E
1)
#1250000
b110 G
b110 \
b110 d
b110 e
b101 c
b10 K
b10 X
b10 a
0)
#1255000
16
17
08
b1 D
b11 E
1)
#1260000
b1 G
b1 \
b1 d
b1 e
b110 !
b110 4
b110 I
b110 `
b110 b
b11 "
b11 5
b11 J
b11 V
b11 Z
0)
#1265000
13
06
07
b10 D
b1 E
1)
#1270000
b10110 G
b10110 \
b10110 d
b11 H
b11 Q
b11 U
b110 "
b110 5
b110 J
b110 V
b110 Z
b10110 e
b11011 !
b11011 4
b11011 I
b11011 `
b11011 b
b1111111111000000 L
b1111111111000000 _
0)
#1275000
18
03
b11 D
b10 E
1)
#1280000
b1110 G
b1110 \
b1110 d
b1110 e
b1101 c
b110 K
b110 X
b110 a
0)
#1285000
16
17
08
b1 D
b11 E
1)
#1290000
b1 G
b1 \
b1 d
b111 "
b111 5
b111 J
b111 V
b111 Z
b1 e
b1110 !
b1110 4
b1110 I
b1110 `
b1110 b
0)
#1295000
13
06
07
b10 D
b1 E
1)
#1300000
b101110 G
b101110 \
b101110 d
b101110 e
b111011 !
b111011 4
b111011 I
b111011 `
b111011 b
b1111111100000000 L
b1111111100000000 _
b1110 "
b1110 5
b1110 J
b1110 V
b1110 Z
b100 H
b100 Q
b100 U
0)
#1305000
18
03
b11 D
b10 E
1)
#1310000
b11110 G
b11110 \
b11110 d
b11110 e
b11101 c
b1110 K
b1110 X
b1110 a
0)
#1315000
16
17
08
b1 D
b11 E
1)
#1320000
b1 G
b1 \
b1 d
b1 e
b11110 !
b11110 4
b11110 I
b11110 `
b11110 b
b1111 "
b1111 5
b1111 J
b1111 V
b1111 Z
0)
#1325000
13
06
07
b10 D
b1 E
1)
#1330000
b1011110 G
b1011110 \
b1011110 d
b101 H
b101 Q
b101 U
b11110 "
b11110 5
b11110 J
b11110 V
b11110 Z
b1011110 e
b1111011 !
b1111011 4
b1111011 I
b1111011 `
b1111011 b
b1111110000000000 L
b1111110000000000 _
0)
#1335000
18
03
b11 D
b10 E
1)
#1340000
b111110 G
b111110 \
b111110 d
b111110 e
b111101 c
b11110 K
b11110 X
b11110 a
0)
#1345000
16
17
08
b1 D
b11 E
1)
