divisor/comparador.v
// ============================================================
// comparador.v
// Compara el contador i contra N (16 = cantidad de bits de A).
// Z=1 cuando i llega a 16 -> ya se hicieron las 16 iteraciones.
// ============================================================
module comparador #(
    parameter N     = 16,
    parameter WIDTH = 5
)(
    input  wire [WIDTH-1:0] count,
    output wire             Z
);

    assign Z = (count == N[WIDTH-1:0]) ? 1'b1 : 1'b0;

endmodule

divisor/contador_i.v
module contador_i #(
    parameter WIDTH = 5 
)(
    input  wire              clk,
    input  wire              rst,   // = LDA
    input  wire              inc,   // = INC
    output reg [WIDTH-1:0]   count
);

    always @(negedge clk) begin
        if (rst)
            count <= {WIDTH{1'b0}};
        else if (inc)
            count <= count + 1'b1;
    end

endmodule

divisor/reg_ra.v
module reg_ra #(
    parameter N = 16
)(
    input  wire             clk,
    input  wire             LDA,
    input  wire             CO,
    input  wire             AO,
    input  wire             LDR,
    input  wire [N-1:0]     a_in,
    input  wire [N-1:0]     sub_result,
    output reg  [N-1:0]     R,
    output reg  [N-1:0]     A
);

    always @(negedge clk) begin
        if (LDA) begin
            A <= a_in;
            R <= {N{1'b0}};
        end else if (CO) begin
            {R, A} <= {R, A} << 1;
        end else begin
            if (LDR)
                R <= sub_result;
            if (AO)
                A[0] <= 1'b1;
        end
    end

endmodule

divisor/restador.v
// ============================================================
// restador.v
// Restador en complemento a 2: calcula R - B.
// MSB = 1 si R < B (hubo "prestamo", resultado negativo)
// MSB = 0 si R >= B (resta valida, se puede usar result)
// Puramente combinacional (no tiene reloj).
// ============================================================
module restador #(
    parameter N = 16
)(
    input  wire [N-1:0] R,
    input  wire [N-1:0] B,
    output wire [N-1:0] result,
    output wire         MSB
);

    wire [N:0] diff;

    assign diff   = {1'b0, R} - {1'b0, B};
    assign result = diff[N-1:0];
    assign MSB    = diff[N];   // 1 = negativo (R<B), 0 = R>=B

endmodule

divisor/ultimo/reg_divisor.v
module reg_divisor #(
    parameter N = 16
)(
    input  wire         clk,
    input  wire         LDA,
    input  wire [N-1:0] b_in,
    output reg  [N-1:0] B
);

    always @(negedge clk) begin
        if (LDA)
            B <= b_in;
    end

endmodule

divisor/datapath.v
// ============================================================
// datapath.v
// Camino de datos del divisor restaurador.
// Conecta: reg_ra ({R,A}), reg_divisor (B), restador (R-B),
// contador_i y comparador (Z).
// ============================================================
module datapath #(
    parameter N          = 16,
    parameter CNT_WIDTH  = 5
)(
    input  wire             clk,
    input  wire [N-1:0]     a,      // dividendo
    input  wire [N-1:0]     b,      // divisor
    input  wire             LDA,
    input  wire             CO,
    input  wire             AO,
    input  wire             INC,
    input  wire             LDR,
    output wire             MSB,    // hacia Control (signo de R-B)
    output wire             Z,      // hacia Control (fin de las N iteraciones)
    output wire [N-1:0]     Q,      // cociente (registro A al terminar)
    output wire [N-1:0]     Rem     // residuo (registro R al terminar)
);

    wire [N-1:0]        B_reg;
    wire [N-1:0]         sub_result;
    wire [CNT_WIDTH-1:0] count;

    reg_divisor #(.N(N)) u_reg_divisor (
        .clk  (clk),
        .LDA  (LDA),
        .b_in (b),
        .B    (B_reg)
    );

    restador #(.N(N)) u_restador (
        .R      (Rem),
        .B      (B_reg),
        .result (sub_result),
        .MSB    (MSB)
    );

    reg_ra #(.N(N)) u_reg_ra (
        .clk        (clk),
        .LDA        (LDA),
        .CO         (CO),
        .AO         (AO),
        .LDR        (LDR),
        .a_in       (a),
        .sub_result (sub_result),
        .R          (Rem),
        .A          (Q)
    );

    contador_i #(.WIDTH(CNT_WIDTH)) u_contador_i (
        .clk   (clk),
        .rst   (LDA),
        .inc   (INC),
        .count (count)
    );

    comparador #(.N(N), .WIDTH(CNT_WIDTH)) u_comparador (
        .count (count),
        .Z     (Z)
    );

endmodule

divisor/ultimo/control.v
module control (
    input  wire clk,
    input  wire rst,     
    input  wire start,
    input  wire MSB,     
    input  wire Z,       
    output reg  LDA,
    output reg  CO,
    output reg  AO,
    output reg  INC,
    output reg  LDR,
    output reg  DONE
);

    localparam [2:0]
        START = 3'b000,
        SHIFT = 3'b001,
        CHECK = 3'b010,
        ADDST = 3'b011,
        ENDST = 3'b100;

    reg [2:0] state, next_state;

   
    always @(posedge clk or posedge rst) begin
        if (rst)
            state <= START;
        else
            state <= next_state;
    end

 
    always @(*) begin
        case (state)
            START: next_state = start ? SHIFT : START;
            SHIFT: next_state = CHECK;
            CHECK: next_state = MSB ? (Z ? ENDST : SHIFT) : ADDST;
            ADDST: next_state = Z ? ENDST : SHIFT;
            ENDST: next_state = start ? START : ENDST;
            default: next_state = START;
        endcase
    end

 
    always @(*) begin
        LDA  = 1'b0;
        CO   = 1'b0;
        AO   = 1'b0;
        INC  = 1'b0;
        LDR  = 1'b0;
        DONE = 1'b0;
        case (state)
            START: LDA  = 1'b1;
            SHIFT: begin CO = 1'b1; INC = 1'b1; end
            CHECK: ; // sin senales activas
            ADDST: begin AO = 1'b1; LDR = 1'b1; end
            ENDST: DONE = 1'b1;
            default: ;
        endcase
    end

endmodule

divisor/ultimo/divisor_top.v
module divisor_top #(
    parameter N         = 16,
    parameter CNT_WIDTH = 5
)(
    input  wire             clk,
    input  wire             rst,
    input  wire             start,
    input  wire [N-1:0]     a,      // dividendo
    input  wire [N-1:0]     b,      // divisor
    output wire [N-1:0]     Q,      // cociente
    output wire [N-1:0]     Rem,    // residuo
    output wire             DONE
);

    wire LDA, CO, AO, INC, LDR;
    wire MSB, Z;

    control u_control (
        .clk   (clk),
        .rst   (rst),
        .start (start),
        .MSB   (MSB),
        .Z     (Z),
        .LDA   (LDA),
        .CO    (CO),
        .AO    (AO),
        .INC   (INC),
        .LDR   (LDR),
        .DONE  (DONE)
    );

    datapath #(.N(N), .CNT_WIDTH(CNT_WIDTH)) u_datapath (
        .clk (clk),
        .a   (a),
        .b   (b),
        .LDA (LDA),
        .CO  (CO),
        .AO  (AO),
        .INC (INC),
        .LDR (LDR),
        .MSB (MSB),
        .Z   (Z),
        .Q   (Q),
        .Rem (Rem)
    );

endmodule

divisor/ultimo/divisor_top_TB.v
module tb_divisor;

    parameter N         = 16;
    parameter CNT_WIDTH = 5;

    reg              clk;
    reg              rst;
    reg              start;
    reg  [N-1:0]     a, b;
    wire [N-1:0]     Q, Rem;
    wire             DONE;

    integer errors = 0;
    integer tests  = 0;

    divisor_top #(.N(N), .CNT_WIDTH(CNT_WIDTH)) uut (
        .clk   (clk),
        .rst   (rst),
        .start (start),
        .a     (a),
        .b     (b),
        .Q     (Q),
        .Rem   (Rem),
        .DONE  (DONE)
    );

    initial clk = 1'b0;
    always #5 clk = ~clk;

    task run_test(input [N-1:0] ta, input [N-1:0] tb);
        reg [N-1:0] expected_q, expected_r;
        begin
            tests      = tests + 1;
            expected_q = ta / tb;
            expected_r = ta % tb;

            a = ta;
            b = tb;
            start = 1'b0;
            @(posedge clk);

            start = 1'b1;
            @(posedge clk);
            @(posedge clk);
            start = 1'b0;

            wait (DONE == 1'b1);
            @(posedge clk);

            if (Q !== expected_q || Rem !== expected_r) begin
                $display("FALLO: a=%0d b=%0d -> Q=%0d Rem=%0d (esperado Q=%0d Rem=%0d)",
                          ta, tb, Q, Rem, expected_q, expected_r);
                errors = errors + 1;
            end else begin
                $display("OK   : a=%0d b=%0d -> Q=%0d Rem=%0d", ta, tb, Q, Rem);
            end

            @(posedge clk);
        end
    endtask

    initial begin
        $dumpfile("divisor_top_TB.vcd");
        $dumpvars(0, tb_divisor);

        rst   = 1'b1;
        start = 1'b0;
        a = 0; b = 0;
        repeat (2) @(posedge clk);
        rst = 1'b0;
        @(posedge clk);

        run_test(16'd20,    16'd4);
        run_test(16'd100,   16'd7);
        run_test(16'd65535, 16'd1);
        run_test(16'd65535, 16'd65535);
        run_test(16'd1,     16'd1);
        run_test(16'd0,     16'd5);
        run_test(16'd12345, 16'd100);

        $display("--------------------------------------------------");
        if (errors == 0)
            $display("TODAS LAS PRUEBAS PASARON (%0d/%0d)", tests, tests);
        else
            $display("%0d DE %0d PRUEBAS FALLARON", errors, tests);

        $finish;
    end

endmodule

divisor/ultimo/divisor_top_TB.vcd
$date
	Thu Jul 16 14:24:02 2026
$end
$version
	Icarus Verilog
$end
$timescale
	1s
$end
$scope module tb_divisor $end
$var wire 16 ! Rem [15:0] $end
$var wire 16 " Q [15:0] $end
$var wire 1 # DONE $end
$var parameter 32 $ CNT_WIDTH $end
$var parameter 32 % N $end
$var reg 16 & a [15:0] $end
$var reg 16 ' b [15:0] $end
$var reg 1 ( clk $end
$var reg 1 ) rst $end
$var reg 1 * start $end
$var integer 32 + errors [31:0] $end
$var integer 32 , tests [31:0] $end
$scope module uut $end
$var wire 16 - a [15:0] $end
$var wire 16 . b [15:0] $end
$var wire 1 ( clk $end
$var wire 1 ) rst $end
$var wire 1 * start $end
$var wire 1 / Z $end
$var wire 16 0 Rem [15:0] $end
$var wire 16 1 Q [15:0] $end
$var wire 1 2 MSB $end
$var wire 1 3 LDR $end
$var wire 1 4 LDA $end
$var wire 1 5 INC $end
$var wire 1 # DONE $end
$var wire 1 6 CO $end
$var wire 1 7 AO $end
$var parameter 32 8 CNT_WIDTH $end
$var parameter 32 9 N $end
$scope module u_control $end
$var wire 1 ( clk $end
$var wire 1 ) rst $end
$var wire 1 * start $end
$var wire 1 / Z $end
$var wire 1 2 MSB $end
$var parameter 3 : ADDST $end
$var parameter 3 ; CHECK $end
$var parameter 3 < ENDST $end
$var parameter 3 = SHIFT $end
$var parameter 3 > START $end
$var reg 1 7 AO $end
$var reg 1 6 CO $end
$var reg 1 # DONE $end
$var reg 1 5 INC $end
$var reg 1 4 LDA $end
$var reg 1 3 LDR $end
$var reg 3 ? next_state [2:0] $end
$var reg 3 @ state [2:0] $end
$upscope $end
$scope module u_datapath $end
$var wire 1 7 AO $end
$var wire 1 6 CO $end
$var wire 1 5 INC $end
$var wire 1 4 LDA $end
$var wire 1 3 LDR $end
$var wire 16 A a [15:0] $end
$var wire 16 B b [15:0] $end
$var wire 1 ( clk $end
$var wire 16 C sub_result [15:0] $end
$var wire 5 D count [4:0] $end
$var wire 1 / Z $end
$var wire 16 E Rem [15:0] $end
$var wire 16 F Q [15:0] $end
$var wire 1 2 MSB $end
$var wire 16 G B_reg [15:0] $end
$var parameter 32 H CNT_WIDTH $end
$var parameter 32 I N $end
$scope module u_comparador $end
$var wire 5 J count [4:0] $end
$var wire 1 / Z $end
$var parameter 32 K N $end
$var parameter 32 L WIDTH $end
$upscope $end
$scope module u_contador_i $end
$var wire 1 ( clk $end
$var wire 1 5 inc $end
$var wire 1 4 rst $end
$var parameter 32 M WIDTH $end
$var reg 5 N count [4:0] $end
$upscope $end
$scope module u_reg_divisor $end
$var wire 1 4 LDA $end
$var wire 16 O b_in [15:0] $end
$var wire 1 ( clk $end
$var parameter 32 P N $end
$var reg 16 Q B [15:0] $end
$upscope $end
$scope module u_reg_ra $end
$var wire 1 7 AO $end
$var wire 1 6 CO $end
$var wire 1 4 LDA $end
$var wire 1 3 LDR $end
$var wire 16 R a_in [15:0] $end
$var wire 1 ( clk $end
$var wire 16 S sub_result [15:0] $end
$var parameter 32 T N $end
$var reg 16 U A [15:0] $end
$var reg 16 V R [15:0] $end
$upscope $end
$scope module u_restador $end
$var wire 16 W B [15:0] $end
$var wire 16 X R [15:0] $end
$var wire 16 Y result [15:0] $end
$var wire 17 Z diff [16:0] $end
$var wire 1 2 MSB $end
$var parameter 32 [ N $end
$upscope $end
$upscope $end
$upscope $end
$scope task run_test $end
$var reg 16 \ expected_q [15:0] $end
$var reg 16 ] expected_r [15:0] $end
$var reg 16 ^ ta [15:0] $end
$var reg 16 _ tb [15:0] $end
$upscope $end
$upscope $end
$enddefinitions $end
$comment Show the parameter values. $end
$dumpall
b10000 [
b10000 T
b10000 P
b101 M
b101 L
b10000 K
b10000 I
b101 H
b0 >
b1 =
b100 <
b10 ;
b11 :
b10000 9
b101 8
b10000 %
b101 $
$end
#0
$dumpvars
bx _
bx ^
bx ]
bx \
bx Z
bx Y
bx X
bx W
bx V
bx U
bx S
b0 R
bx Q
b0 O
bx N
bx J
bx G
bx F
bx E
bx D
bx C
b0 B
b0 A
b0 @
b0 ?
07
06
05
14
03
x2
bx 1
bx 0
x/
b0 .
b0 -
b0 ,
b0 +
0*
1)
0(
b0 '
b0 &
0#
bx "
bx !
$end
#5
1(
#10
0/
b0 C
b0 S
b0 Y
02
b0 D
b0 J
b0 N
b0 Z
b0 !
b0 0
b0 E
b0 V
b0 X
b0 "
b0 1
b0 F
b0 U
b0 G
b0 Q
b0 W
0(
#15
0)
1(
#20
0(
#25
b100 '
b100 .
b100 B
b100 O
b10100 &
b10100 -
b10100 A
b10100 R
b0 ]
b101 \
b1 ,
b100 _
b10100 ^
1(
#30
b1111111111111100 C
b1111111111111100 S
b1111111111111100 Y
12
b10100 "
b10100 1
b10100 F
b10100 U
b11111111111111100 Z
b100 G
b100 Q
b100 W
0(
#35
b1 ?
1*
1(
#40
0(
#45
15
16
04
b10 ?
b1 @
1(
#50
b1 D
b1 J
b1 N
b101000 "
b101000 1
b101000 F
b101000 U
0(
#55
05
06
b1 ?
b10 @
0*
1(
#60
0(
#65
15
16
b10 ?
b1 @
1(
#70
b10 D
b10 J
b10 N
b1010000 "
b1010000 1
b1010000 F
b1010000 U
0(
#75
05
06
b1 ?
b10 @
1(
#80
0(
#85
15
16
b10 ?
b1 @
1(
#90
b11 D
b11 J
b11 N
b10100000 "
b10100000 1
b10100000 F
b10100000 U
0(
#95
05
06
b1 ?
b10 @
1(
#100
0(
#105
15
16
b10 ?
b1 @
1(
#110
b100 D
b100 J
b100 N
b101000000 "
b101000000 1
b101000000 F
b101000000 U
0(
#115
05
06
b1 ?
b10 @
1(
#120
0(
#125
15
16
b10 ?
b1 @
1(
#130
b101 D
b101 J
b101 N
b1010000000 "
b1010000000 1
b1010000000 F
b1010000000 U
0(
#135
05
06
b1 ?
b10 @
1(
#140
0(
#145
15
16
b10 ?
b1 @
1(
#150
b110 D
b110 J
b110 N
b10100000000 "
b10100000000 1
b10100000000 F
b10100000000 U
0(
#155
05
06
b1 ?
b10 @
1(
#160
0(
#165
15
16
b10 ?
b1 @
1(
#170
b111 D
b111 J
b111 N
b101000000000 "
b101000000000 1
b101000000000 F
b101000000000 U
0(
#175
05
06
b1 ?
b10 @
1(
#180
0(
#185
15
16
b10 ?
b1 @
1(
#190
b1000 D
b1000 J
b1000 N
b1010000000000 "
b1010000000000 1
b1010000000000 F
b1010000000000 U
0(
#195
05
06
b1 ?
b10 @
1(
#200
0(
#205
15
16
b10 ?
b1 @
1(
#210
b1001 D
b1001 J
b1001 N
b10100000000000 "
b10100000000000 1
b10100000000000 F
b10100000000000 U
0(
#215
05
06
b1 ?
b10 @
1(
#220
0(
#225
15
16
b10 ?
b1 @
1(
#230
b1010 D
b1010 J
b1010 N
b101000000000000 "
b101000000000000 1
b101000000000000 F
b101000000000000 U
0(
#235
05
06
b1 ?
b10 @
1(
#240
0(
#245
15
16
b10 ?
b1 @
1(
#250
b1011 D
b1011 J
b1011 N
b1010000000000000 "
b1010000000000000 1
b1010000000000000 F
b1010000000000000 U
0(
#255
05
06
b1 ?
b10 @
1(
#260
0(
#265
15
16
b10 ?
b1 @
1(
#270
b1111111111111101 C
b1111111111111101 S
b1111111111111101 Y
b1100 D
b1100 J
b1100 N
b11111111111111101 Z
b1 !
b1 0
b1 E
b1 V
b1 X
b100000000000000 "
b100000000000000 1
b100000000000000 F
b100000000000000 U
0(
#275
05
06
b1 ?
b10 @
1(
#280
0(
#285
15
16
b10 ?
b1 @
1(
#290
b1111111111111110 C
b1111111111111110 S
b1111111111111110 Y
b1101 D
b1101 J
b1101 N
b11111111111111110 Z
b10 !
b10 0
b10 E
b10 V
b10 X
b1000000000000000 "
b1000000000000000 1
b1000000000000000 F
b1000000000000000 U
0(
#295
05
06
b1 ?
b10 @
1(
#300
0(
#305
15
16
b10 ?
b1 @
1(
#310
b1 C
b1 S
b1 Y
02
b1110 D
b1110 J
b1110 N
b1 Z
b101 !
b101 0
b101 E
b101 V
b101 X
b0 "
b0 1
b0 F
b0 U
0(
#315
05
06
b11 ?
b10 @
1(
#320
0(
#325
13
17
b1 ?
b11 @
1(
#330
b1111111111111101 C
b1111111111111101 S
b1111111111111101 Y
12
b1 "
b1 1
b1 F
b1 U
b11111111111111101 Z
b1 !
b1 0
b1 E
b1 V
b1 X
0(
#335
15
16
03
07
b10 ?
b1 @
1(
#340
b1111111111111110 C
b1111111111111110 S
b1111111111111110 Y
b11111111111111110 Z
b10 !
b10 0
b10 E
b10 V
b10 X
b10 "
b10 1
b10 F
b10 U
b1111 D
b1111 J
b1111 N
0(
#345
05
06
b1 ?
b10 @
1(
#350
0(
#355
15
16
b10 ?
b1 @
1(
#360
b0 C
b0 S
b0 Y
02
1/
b0 Z
b100 !
b100 0
b100 E
b100 V
b100 X
b100 "
b100 1
b100 F
b100 U
b10000 D
b10000 J
b10000 N
0(
#365
05
06
b11 ?
b10 @
1(
#370
0(
#375
13
17
b100 ?
b11 @
1(
#380
b1111111111111100 C
b1111111111111100 S
b1111111111111100 Y
12
b101 "
b101 1
b101 F
b101 U
b11111111111111100 Z
b0 !
b0 0
b0 E
b0 V
b0 X
0(
#385
1#
03
07
b100 @
1(
#390
0(
#395
1(
#400
0(
#405
b111 '
b111 .
b111 B
b111 O
b1100100 &
b1100100 -
b1100100 A
b1100100 R
b10 ]
b1110 \
b10 ,
b111 _
b1100100 ^
1(
#410
0(
#415
b0 ?
1*
1(
#420
0(
#425
14
0#
b1 ?
b0 @
1(
#430
0/
b1111111111111001 C
b1111111111111001 S
b1111111111111001 Y
b0 D
b0 J
b0 N
b1100100 "
b1100100 1
b1100100 F
b1100100 U
b11111111111111001 Z
b111 G
b111 Q
b111 W
0(
#435
15
16
04
b1 @
b10 ?
0*
1(
#440
b11001000 "
b11001000 1
b11001000 F
b11001000 U
b1 D
b1 J
b1 N
0(
#445
05
06
b1 ?
b10 @
1(
#450
0(
#455
15
16
b10 ?
b1 @
1(
#460
b110010000 "
b110010000 1
b110010000 F
b110010000 U
b10 D
b10 J
b10 N
0(
#465
05
06
b1 ?
b10 @
1(
#470
0(
#475
15
16
b10 ?
b1 @
1(
#480
b1100100000 "
b1100100000 1
b1100100000 F
b1100100000 U
b11 D
b11 J
b11 N
0(
#485
05
06
b1 ?
b10 @
1(
#490
0(
#495
15
16
b10 ?
b1 @
1(
#500
b11001000000 "
b11001000000 1
b11001000000 F
b11001000000 U
b100 D
b100 J
b100 N
0(
#505
05
06
b1 ?
b10 @
1(
#510
0(
#515
15
16
b10 ?
b1 @
1(
#520
b110010000000 "
b110010000000 1
b110010000000 F
b110010000000 U
b101 D
b101 J
b101 N
0(
#525
05
06
b1 ?
b10 @
1(
#530
0(
#535
15
16
b10 ?
b1 @
1(
#540
b1100100000000 "
b1100100000000 1
b1100100000000 F
b1100100000000 U
b110 D
b110 J
b110 N
0(
#545
05
06
b1 ?
b10 @
1(
#550
0(
#555
15
16
b10 ?
b1 @
1(
#560
b11001000000000 "
b11001000000000 1
b11001000000000 F
b11001000000000 U
b111 D
b111 J
b111 N
0(
#565
05
06
b1 ?
b10 @
1(
#570
0(
#575
15
16
b10 ?
b1 @
1(
#580
b110010000000000 "
b110010000000000 1
b110010000000000 F
b110010000000000 U
b1000 D
b1000 J
b1000 N
0(
#585
05
06
b1 ?
b10 @
1(
#590
0(
#595
15
16
b10 ?
b1 @
1(
#600
b1100100000000000 "
b1100100000000000 1
b1100100000000000 F
b1100100000000000 U
b1001 D
b1001 J
b1001 N
0(
#605
05
06
b1 ?
b10 @
1(
#610
0(
#615
15
16
b10 ?
b1 @
1(
#620
b1111111111111010 C
b1111111111111010 S
b1111111111111010 Y
b11111111111111010 Z
b1 !
b1 0
b1 E
b1 V
b1 X
b1001000000000000 "
b1001000000000000 1
b1001000000000000 F
b1001000000000000 U
b1010 D
b1010 J
b1010 N
0(
#625
05
06
b1 ?
b10 @
1(
#630
0(
#635
15
16
b10 ?
b1 @
1(
#640
b1111111111111100 C
b1111111111111100 S
b1111111111111100 Y
b11111111111111100 Z
b11 !
b11 0
b11 E
b11 V
b11 X
b10000000000000 "
b10000000000000 1
b10000000000000 F
b10000000000000 U
b1011 D
b1011 J
b1011 N
0(
#645
05
06
b1 ?
b10 @
1(
#650
0(
#655
15
16
b10 ?
b1 @
1(
#660
b1111111111111111 C
b1111111111111111 S
b1111111111111111 Y
b11111111111111111 Z
b110 !
b110 0
b110 E
b110 V
b110 X
b100000000000000 "
b100000000000000 1
b100000000000000 F
b100000000000000 U
b1100 D
b1100 J
b1100 N
0(
#665
05
06
b1 ?
b10 @
1(
#670
0(
#675
15
16
b10 ?
b1 @
1(
#680
b101 C
b101 S
b101 Y
02
b101 Z
b1100 !
b1100 0
b1100 E
b1100 V
b1100 X
b1000000000000000 "
b1000000000000000 1
b1000000000000000 F
b1000000000000000 U
b1101 D
b1101 J
b1101 N
0(
#685
05
06
b11 ?
b10 @
1(
#690
0(
#695
13
17
b1 ?
b11 @
1(
#700
b1111111111111110 C
b1111111111111110 S
b1111111111111110 Y
12
b1000000000000001 "
b1000000000000001 1
b1000000000000001 F
b1000000000000001 U
b11111111111111110 Z
b101 !
b101 0
b101 E
b101 V
b101 X
0(
#705
15
16
03
07
b10 ?
b1 @
1(
#710
b100 C
b100 S
b100 Y
02
b1110 D
b1110 J
b1110 N
b100 Z
b1011 !
b1011 0
b1011 E
b1011 V
b1011 X
b10 "
b10 1
b10 F
b10 U
0(
#715
05
06
b11 ?
b10 @
1(
#720
0(
#725
13
17
b1 ?
b11 @
1(
#730
b1111111111111101 C
b1111111111111101 S
b1111111111111101 Y
12
b11 "
b11 1
b11 F
b11 U
b11111111111111101 Z
b100 !
b100 0
b100 E
b100 V
b100 X
0(
#735
15
16
03
07
b10 ?
b1 @
1(
#740
b1 C
b1 S
b1 Y
02
b1 Z
b1000 !
b1000 0
b1000 E
b1000 V
b1000 X
b110 "
b110 1
b110 F
b110 U
b1111 D
b1111 J
b1111 N
0(
#745
05
06
b11 ?
b10 @
1(
#750
0(
#755
13
17
b1 ?
b11 @
1(
#760
b1111111111111010 C
b1111111111111010 S
b1111111111111010 Y
12
b111 "
b111 1
b111 F
b111 U
b11111111111111010 Z
b1 !
b1 0
b1 E
b1 V
b1 X
0(
#765
15
16
03
07
b10 ?
b1 @
1(
#770
1/
b1111111111111011 C
b1111111111111011 S
b1111111111111011 Y
b10000 D
b10000 J
b10000 N
b11111111111111011 Z
b10 !
b10 0
b10 E
b10 V
b10 X
b1110 "
b1110 1
b1110 F
b1110 U
0(
#775
05
06
b100 ?
b10 @
1(
#780
0(
#785
1#
b100 @
1(
#790
0(
#795
1(
#800
0(
#805
b1 '
b1 .
b1 B
b1 O
b1111111111111111 &
b1111111111111111 -
b1111111111111111 A
b1111111111111111 R
b0 ]
b1111111111111111 \
b11 ,
b1 _
b1111111111111111 ^
1(
#810
0(
#815
b0 ?
1*
1(
#820
0(
#825
14
0#
b1 ?
b0 @
1(
#830
0/
b1111111111111111 C
b1111111111111111 S
b1111111111111111 Y
b0 D
b0 J
b0 N
b0 !
b0 0
b0 E
b0 V
b0 X
b1111111111111111 "
b1111111111111111 1
b1111111111111111 F
b1111111111111111 U
b11111111111111111 Z
b1 G
b1 Q
b1 W
0(
#835
15
16
04
b1 @
b10 ?
0*
1(
#840
b0 C
b0 S
b0 Y
02
b0 Z
b1 !
b1 0
b1 E
b1 V
b1 X
b1111111111111110 "
b1111111111111110 1
b1111111111111110 F
b1111111111111110 U
b1 D
b1 J
b1 N
0(
#845
05
06
b11 ?
b10 @
1(
#850
0(
#855
13
17
b1 ?
b11 @
1(
#860
b1111111111111111 C
b1111111111111111 S
b1111111111111111 Y
12
b1111111111111111 "
b1111111111111111 1
b1111111111111111 F
b1111111111111111 U
b11111111111111111 Z
b0 !
b0 0
b0 E
b0 V
b0 X
0(
#865
15
16
03
07
b10 ?
b1 @
1(
#870
b0 C
b0 S
b0 Y
02
b10 D
b10 J
b10 N
b0 Z
b1 !
b1 0
b1 E
b1 V
b1 X
b1111111111111110 "
b1111111111111110 1
b1111111111111110 F
b1111111111111110 U
0(
#875
05
06
b11 ?
b10 @
1(
#880
0(
#885
13
17
b1 ?
b11 @
1(
#890
b1111111111111111 C
b1111111111111111 S
b1111111111111111 Y
12
b1111111111111111 "
b1111111111111111 1
b1111111111111111 F
b1111111111111111 U
b11111111111111111 Z
b0 !
b0 0
b0 E
b0 V
b0 X
0(
#895
15
16
03
07
b10 ?
b1 @
1(
#900
b0 C
b0 S
b0 Y
02
b0 Z
b1 !
b1 0
b1 E
b1 V
b1 X
b1111111111111110 "
b1111111111111110 1
b1111111111111110 F
b1111111111111110 U
b11 D
b11 J
b11 N
0(
#905
05
06
b11 ?
b10 @
1(
#910
0(
#915
13
17
b1 ?
b11 @
1(
#920
b1111111111111111 C
b1111111111111111 S
b1111111111111111 Y
12
b1111111111111111 "
b1111111111111111 1
b1111111111111111 F
b1111111111111111 U
b11111111111111111 Z
b0 !
b0 0
b0 E
b0 V
b0 X
0(
#925
15
16
03
07
b10 ?
b1 @
1(
#930
b0 C
b0 S
b0 Y
02
b100 D
b100 J
b100 N
b0 Z
b1 !
b1 0
b1 E
b1 V
b1 X
b1111111111111110 "
b1111111111111110 1
b1111111111111110 F
b1111111111111110 U
0(
#935
05
06
b11 ?
b10 @
1(
#940
0(
#945
13
17
b1 ?
b11 @
1(
#950
b1111111111111111 C
b1111111111111111 S
b1111111111111111 Y
12
b1111111111111111 "
b1111111111111111 1
b1111111111111111 F
b1111111111111111 U
b11111111111111111 Z
b0 !
b0 0
b0 E
b0 V
b0 X
0(
#955
15
16
03
07
b10 ?
b1 @
1(
#960
b0 C
b0 S
b0 Y
02
b0 Z
b1 !
b1 0
b1 E
b1 V
b1 X
b1111111111111110 "
b1111111111111110 1
b1111111111111110 F
b1111111111111110 U
b101 D
b101 J
b101 N
0(
#965
05
06
b11 ?
b10 @
1(
#970
0(
#975
13
17
b1 ?
b11 @
1(
#980
b1111111111111111 C
b1111111111111111 S
b1111111111111111 Y
12
b1111111111111111 "
b1111111111111111 1
b1111111111111111 F
b1111111111111111 U
b11111111111111111 Z
b0 !
b0 0
b0 E
b0 V
b0 X
0(
#985
15
16
03
07
b10 ?
b1 @
1(
#990
b0 C
b0 S
b0 Y
02
b110 D
b110 J
b110 N
b0 Z
b1 !
b1 0
b1 E
b1 V
b1 X
b1111111111111110 "
b1111111111111110 1
b1111111111111110 F
b1111111111111110 U
0(
#995
05
06
b11 ?
b10 @
1(
#1000
0(
#1005
13
17
b1 ?
b11 @
1(
#1010
b1111111111111111 C
b1111111111111111 S
b1111111111111111 Y
12
b1111111111111111 "
b1111111111111111 1
b1111111111111111 F
b1111111111111111 U
b11111111111111111 Z
b0 !
b0 0
b0 E
b0 V
b0 X
0(
#1015
15
16
03
07
b10 ?
b1 @
1(
#1020
b0 C
b0 S
b0 Y
02
b0 Z
b1 !
b1 0
b1 E
b1 V
b1 X
b1111111111111110 "
b1111111111111110 1
b1111111111111110 F
b1111111111111110 U
b111 D
b111 J
b111 N
0(
#1025
05
06
b11 ?
b10 @
1(
#1030
0(
#1035
13
17
b1 ?
b11 @
1(
#1040
b1111111111111111 C
b1111111111111111 S
b1111111111111111 Y
12
b1111111111111111 "
b1111111111111111 1
b1111111111111111 F
b1111111111111111 U
b11111111111111111 Z
b0 !
b0 0
b0 E
b0 V
b0 X
0(
#1045
15
16
03
07
b10 ?
b1 @
1(
#1050
b0 C
b0 S
b0 Y
02
b1000 D
b1000 J
b1000 N
b0 Z
b1 !
b1 0
b1 E
b1 V
b1 X
b1111111111111110 "
b1111111111111110 1
b1111111111111110 F
b1111111111111110 U
0(
#1055
05
06
b11 ?
b10 @
1(
#1060
0(
#1065
13
17
b1 ?
b11 @
1(
#1070
b1111111111111111 C
b1111111111111111 S
b1111111111111111 Y
12
b1111111111111111 "
b1111111111111111 1
b1111111111111111 F
b1111111111111111 U
b11111111111111111 Z
b0 !
b0 0
b0 E
b0 V
b0 X
0(
#1075
15
16
03
07
b10 ?
b1 @
1(
#1080
b0 C
b0 S
b0 Y
02
b0 Z
b1 !
b1 0
b1 E
b1 V
b1 X
b1111111111111110 "
b1111111111111110 1
b1111111111111110 F
b1111111111111110 U
b1001 D
b1001 J
b1001 N
0(
#1085
05
06
b11 ?
b10 @
1(
#1090
0(
#1095
13
17
b1 ?
b11 @
1(
#1100
b1111111111111111 C
b1111111111111111 S
b1111111111111111 Y
12
b1111111111111111 "
b1111111111111111 1
b1111111111111111 F
b1111111111111111 U
b11111111111111111 Z
b0 !
b0 0
b0 E
b0 V
b0 X
0(
#1105
15
16
03
07
b10 ?
b1 @
1(
#1110
b0 C
b0 S
b0 Y
02
b1010 D
b1010 J
b1010 N
b0 Z
b1 !
b1 0
b1 E
b1 V
b1 X
b1111111111111110 "
b1111111111111110 1
b1111111111111110 F
b1111111111111110 U
0(
#1115
05
06
b11 ?
b10 @
1(
#1120
0(
#1125
13
17
b1 ?
b11 @
1(
#1130
b1111111111111111 C
b1111111111111111 S
b1111111111111111 Y
12
b1111111111111111 "
b1111111111111111 1
b1111111111111111 F
b1111111111111111 U
b11111111111111111 Z
b0 !
b0 0
b0 E
b0 V
b0 X
0(
#1135
15
16
03
07
b10 ?
b1 @
1(
#1140
b0 C
b0 S
b0 Y
02
b0 Z
b1 !
b1 0
b1 E
b1 V
b1 X
b1111111111111110 "
b1111111111111110 1
b1111111111111110 F
b1111111111111110 U
b1011 D
b1011 J
b1011 N
0(
#1145
05
06
b11 ?
b10 @
1(
#1150
0(
#1155
13
17
b1 ?
b11 @
1(
