multiplicador/Ultimo/acc.v
module acc #(
    parameter N = 16
)(
    input  wire                clk,
    input  wire                LD,      
    input  wire                AD,      
    input  wire [2*N-1:0]      add_val, 
    output reg  [2*N-1:0]      R
);

    always @(negedge clk) begin
        if (LD)
            R <= {2*N{1'b0}};
        else if (AD)
            R <= R + add_val;
    end

endmodule

multiplicador/Ultimo/lsr.v
module lsr #(
    parameter N = 16
)(
    input  wire                clk,
    input  wire                LD,    
    input  wire                SH,    
    input  wire [N-1:0]        a_in,
    output reg  [2*N-1:0]      a_out
);

    always @(negedge clk) begin
        if (LD)
            a_out <= {{N{1'b0}}, a_in};  
        else if (SH)
            a_out <= a_out << 1;       
    end

endmodule

multiplicador/ultimo/comparador.v
// ============================================================
// comparador.v
// Compara el contador contra t = N (cantidad de bits de b).
// Z=1 cuando ya se procesaron los N bits -> fin del ciclo.
// ============================================================
module comparador #(
    parameter N         = 16,
    parameter CNT_WIDTH = $clog2(N+1)
)(
    input  wire [CNT_WIDTH-1:0] count,
    output wire                 Z
);

    assign Z = (count == N[CNT_WIDTH-1:0]) ? 1'b1 : 1'b0;

endmodule

multiplicador/Ultimo/contador.v
module contador #(
    parameter N         = 16,
    parameter CNT_WIDTH = $clog2(N+1)
)(
    input  wire                    clk,
    input  wire                    rst,   // = LD
    input  wire                    inc,   // = SH
    output reg  [CNT_WIDTH-1:0]    count
);

    always @(negedge clk) begin
        if (rst)
            count <= {CNT_WIDTH{1'b0}};
        else if (inc)
            count <= count + 1'b1;
    end

endmodule

multiplicador/ultimo/reg_b.v
// ============================================================
// reg_b.v
// Registro/Multiplexor de B
// Guarda el multiplicador 'b' cuando LD=1, y expone el bit
// actual b(i) seleccionado por el indice del contador (idx).
// ============================================================
module reg_b #(
    parameter N         = 16,
    parameter CNT_WIDTH = $clog2(N+1)
)(
    input  wire                  clk,
    input  wire                  LD,     // carga b (viene de Control)
    input  wire [N-1:0]          b_in,   // entrada b del top
    input  wire [CNT_WIDTH-1:0]  idx,    // indice i (del contador)
    output wire                  b_i     // bit b(i) actual
);

    reg [N-1:0] b_reg;

    always @(negedge clk) begin
        if (LD)
            b_reg <= b_in;
    end

    // Multiplexor: selecciona el bit "idx" del registro guardado
    assign b_i = (idx < N) ? b_reg[idx] : 1'b0;

endmodule

multiplicador/Ultimo/datapath.v
module datapath #(
    parameter N         = 16,
    parameter CNT_WIDTH = $clog2(N+1)
)(
    input  wire             clk,
    input  wire [N-1:0]     a,
    input  wire [N-1:0]     b,
    input  wire             LD,
    input  wire             SH,
    input  wire             AD,
    output wire             b_i,   
    output wire             Z,     
    output wire [2*N-1:0]   R      
);

    wire [CNT_WIDTH-1:0] count;
    wire [2*N-1:0]       a_shifted;

    reg_b #(.N(N)) u_reg_b (
        .clk   (clk),
        .LD    (LD),
        .b_in  (b),
        .idx   (count),
        .b_i   (b_i)
    );

    contador #(.N(N)) u_contador (
        .clk   (clk),
        .rst   (LD),
        .inc   (SH),
        .count (count)
    );

    comparador #(.N(N)) u_comparador (
        .count (count),
        .Z     (Z)
    );

    lsr #(.N(N)) u_lsr (
        .clk   (clk),
        .LD    (LD),
        .SH    (SH),
        .a_in  (a),
        .a_out (a_shifted)
    );

    acc #(.N(N)) u_acc (
        .clk     (clk),
        .LD      (LD),
        .AD      (AD),
        .add_val (a_shifted),
        .R       (R)
    );

endmodule

multiplicador/Ultimo/control.v
module control (
    input  wire clk,
    input  wire rst,     
    input  wire start,
    input  wire b_i,
    input  wire Z,
    output reg  LD,
    output reg  SH,
    output reg  AD,
    output reg  DONE
);

    localparam [2:0]
        IDLE    = 3'b000,   // Inicio
        CHECK   = 3'b001,
        ADDST   = 3'b010,   // ADD
        SHIFTST = 3'b011,   // Shift
        DONEST  = 3'b100;   // End

    reg [2:0] state, next_state;

    // Registro de estado
    always @(posedge clk or posedge rst) begin
        if (rst)
            state <= IDLE;
        else
            state <= next_state;
    end

    // Logica de siguiente estado
    always @(*) begin
        case (state)
            IDLE:    next_state = start ? CHECK   : IDLE;
            CHECK:   next_state = b_i   ? ADDST   : SHIFTST;
            ADDST:   next_state = SHIFTST;
            SHIFTST: next_state = Z     ? DONEST  : CHECK;
            DONEST:  next_state = start ? IDLE : DONEST;
            default: next_state = IDLE;
        endcase
    end

    // Salidas (Moore, dependen solo del estado)
    always @(*) begin
        LD   = 1'b0;
        SH   = 1'b0;
        AD   = 1'b0;
        DONE = 1'b0;
        case (state)
            IDLE:    LD   = 1'b1;
            CHECK:   ; // sin senales activas
            ADDST:   AD   = 1'b1;
            SHIFTST: SH   = 1'b1;
            DONEST:  DONE = 1'b1;
            default: ;
        endcase
    end

endmodule

multiplicador/Ultimo/multiplier_top.v
// ============================================================
// multiplier_top.v
// Modulo TOP: une Control (FSM) y Datapath (camino de datos)
// ============================================================
module multiplier_top #(
    parameter N = 16
)(
    input  wire             clk,
    input  wire             rst,
    input  wire             start,
    input  wire [N-1:0]     a,
    input  wire [N-1:0]     b,
    output wire [2*N-1:0]   R,
    output wire             DONE
);

    wire LD, SH, AD;
    wire b_i, Z;

    control u_control (
        .clk   (clk),
        .rst   (rst),
        .start (start),
        .b_i   (b_i),
        .Z     (Z),
        .LD    (LD),
        .SH    (SH),
        .AD    (AD),
        .DONE  (DONE)
    );

    datapath #(.N(N)) u_datapath (
        .clk (clk),
        .a   (a),
        .b   (b),
        .LD  (LD),
        .SH  (SH),
        .AD  (AD),
        .b_i (b_i),
        .Z   (Z),
        .R   (R)
    );

endmodule

multiplicador/Ultimo/multiplier_top_TB.v
module tb_multiplier;

    parameter N = 16;

    reg                  clk;
    reg                  rst;
    reg                  start;
    reg  [N-1:0]         a, b;
    wire [2*N-1:0]       R;
    wire                 DONE;

    integer errors = 0;
    integer tests  = 0;

    multiplier_top #(.N(N)) uut (
        .clk   (clk),
        .rst   (rst),
        .start (start),
        .a     (a),
        .b     (b),
        .R     (R),
        .DONE  (DONE)
    );

  
    initial clk = 1'b0;
    always #5 clk = ~clk;

    task run_test(input [N-1:0] ta, input [N-1:0] tb);
        reg [2*N-1:0] expected;
        begin
            tests    = tests + 1;
            expected = ta * tb;

            a = ta;
            b = tb;
            start = 1'b0;
            @(posedge clk);

            
            start = 1'b1;
            @(posedge clk);
            @(posedge clk);
            start = 1'b0;

            
            wait (DONE == 1'b1);
            @(posedge clk);

            if (R !== expected) begin
                $display("FALLO: a=%0d b=%0d -> R=%0d (esperado %0d)", ta, tb, R, expected);
                errors = errors + 1;
            end else begin
                $display("OK   : a=%0d b=%0d -> R=%0d", ta, tb, R);
            end


            @(posedge clk);
        end
    endtask

    initial begin
        $dumpfile("multiplier_top_TB.vcd");
        $dumpvars(0, tb_multiplier);

        rst   = 1'b1;
        start = 1'b0;
        a = 0; b = 0;
        repeat (2) @(posedge clk);
        rst = 1'b0;
        @(posedge clk);

        run_test(16'd5,     16'd3);
        run_test(16'd1000,  16'd1000);
        run_test(16'd65535, 16'd65535);
        run_test(16'd0,     16'd12345);
        run_test(16'd1,     16'd1);
        run_test(16'd30000, 16'd2);
        run_test(16'd43690, 16'd21845);

        $display("--------------------------------------------------");
        if (errors == 0)
            $display("TODAS LAS PRUEBAS PASARON (%0d/%0d)", tests, tests);
        else
            $display("%0d DE %0d PRUEBAS FALLARON", errors, tests);

        $finish;
    end

endmodule

multiplicador/Ultimo/multiplier_top_TB.vcd
$date
	Thu Jul 16 14:00:42 2026
$end
$version
	Icarus Verilog
$end
$timescale
	1s
$end
$scope module tb_multiplier $end
$var wire 32 ! R [31:0] $end
$var wire 1 " DONE $end
$var parameter 32 # N $end
$var reg 16 $ a [15:0] $end
$var reg 16 % b [15:0] $end
$var reg 1 & clk $end
$var reg 1 ' rst $end
$var reg 1 ( start $end
$var integer 32 ) errors [31:0] $end
$var integer 32 * tests [31:0] $end
$scope module uut $end
$var wire 16 + a [15:0] $end
$var wire 16 , b [15:0] $end
$var wire 1 & clk $end
$var wire 1 ' rst $end
$var wire 1 ( start $end
$var wire 1 - b_i $end
$var wire 1 . Z $end
$var wire 1 / SH $end
$var wire 32 0 R [31:0] $end
$var wire 1 1 LD $end
$var wire 1 " DONE $end
$var wire 1 2 AD $end
$var parameter 32 3 N $end
$scope module u_control $end
$var wire 1 & clk $end
$var wire 1 ' rst $end
$var wire 1 ( start $end
$var wire 1 - b_i $end
$var wire 1 . Z $end
$var parameter 3 4 ADDST $end
$var parameter 3 5 CHECK $end
$var parameter 3 6 DONEST $end
$var parameter 3 7 IDLE $end
$var parameter 3 8 SHIFTST $end
$var reg 1 2 AD $end
$var reg 1 " DONE $end
$var reg 1 1 LD $end
$var reg 1 / SH $end
$var reg 3 9 next_state [2:0] $end
$var reg 3 : state [2:0] $end
$upscope $end
$scope module u_datapath $end
$var wire 1 2 AD $end
$var wire 1 1 LD $end
$var wire 1 / SH $end
$var wire 16 ; a [15:0] $end
$var wire 16 < b [15:0] $end
$var wire 1 & clk $end
$var wire 5 = count [4:0] $end
$var wire 1 - b_i $end
$var wire 32 > a_shifted [31:0] $end
$var wire 1 . Z $end
$var wire 32 ? R [31:0] $end
$var parameter 32 @ CNT_WIDTH $end
$var parameter 32 A N $end
$scope module u_acc $end
$var wire 1 2 AD $end
$var wire 1 1 LD $end
$var wire 1 & clk $end
$var wire 32 B add_val [31:0] $end
$var parameter 32 C N $end
$var reg 32 D R [31:0] $end
$upscope $end
$scope module u_comparador $end
$var wire 5 E count [4:0] $end
$var wire 1 . Z $end
$var parameter 32 F CNT_WIDTH $end
$var parameter 32 G N $end
$upscope $end
$scope module u_contador $end
$var wire 1 & clk $end
$var wire 1 / inc $end
$var wire 1 1 rst $end
$var parameter 32 H CNT_WIDTH $end
$var parameter 32 I N $end
$var reg 5 J count [4:0] $end
$upscope $end
$scope module u_lsr $end
$var wire 1 1 LD $end
$var wire 1 / SH $end
$var wire 16 K a_in [15:0] $end
$var wire 1 & clk $end
$var parameter 32 L N $end
$var reg 32 M a_out [31:0] $end
$upscope $end
$scope module u_reg_b $end
$var wire 1 1 LD $end
$var wire 16 N b_in [15:0] $end
$var wire 1 & clk $end
$var wire 5 O idx [4:0] $end
$var wire 1 - b_i $end
$var parameter 32 P CNT_WIDTH $end
$var parameter 32 Q N $end
$var reg 16 R b_reg [15:0] $end
$upscope $end
$upscope $end
$upscope $end
$scope task run_test $end
$var reg 32 S expected [31:0] $end
$var reg 16 T ta [15:0] $end
$var reg 16 U tb [15:0] $end
$upscope $end
$upscope $end
$enddefinitions $end
$comment Show the parameter values. $end
$dumpall
b10000 Q
b101 P
b10000 L
b10000 I
b101 H
b10000 G
b101 F
b10000 C
b10000 A
b101 @
b11 8
b0 7
b100 6
b1 5
b10 4
b10000 3
b10000 #
$end
#0
$dumpvars
bx U
bx T
bx S
bx R
bx O
b0 N
bx M
b0 K
bx J
bx E
bx D
bx B
bx ?
bx >
bx =
b0 <
b0 ;
b0 :
b0 9
02
11
bx 0
0/
x.
x-
b0 ,
b0 +
b0 *
b0 )
0(
1'
0&
b0 %
b0 $
0"
bx !
$end
#5
1&
#10
0-
0.
b0 !
b0 0
b0 ?
b0 D
b0 >
b0 B
b0 M
b0 =
b0 E
b0 J
b0 O
b0 R
0&
#15
0'
1&
#20
0&
#25
b11 %
b11 ,
b11 <
b11 N
b101 $
b101 +
b101 ;
b101 K
b1111 S
b1 *
b11 U
b101 T
1&
#30
1-
b101 >
b101 B
b101 M
b11 R
0&
#35
b1 9
1(
1&
#40
0&
#45
01
b10 9
b1 :
1&
#50
0&
#55
12
b11 9
b10 :
0(
1&
#60
b101 !
b101 0
b101 ?
b101 D
0&
#65
1/
02
b1 9
b11 :
1&
#70
b1010 >
b1010 B
b1010 M
b1 =
b1 E
b1 J
b1 O
0&
#75
0/
b10 9
b1 :
1&
#80
0&
#85
12
b11 9
b10 :
1&
#90
b1111 !
b1111 0
b1111 ?
b1111 D
0&
#95
1/
02
b1 9
b11 :
1&
#100
0-
b10 =
b10 E
b10 J
b10 O
b10100 >
b10100 B
b10100 M
0&
#105
0/
b11 9
b1 :
1&
#110
0&
#115
1/
b1 9
b11 :
1&
#120
b11 =
b11 E
b11 J
b11 O
b101000 >
b101000 B
b101000 M
0&
#125
0/
b11 9
b1 :
1&
#130
0&
#135
1/
b1 9
b11 :
1&
#140
b100 =
b100 E
b100 J
b100 O
b1010000 >
b1010000 B
b1010000 M
0&
#145
0/
b11 9
b1 :
1&
#150
0&
#155
1/
b1 9
b11 :
1&
#160
b101 =
b101 E
b101 J
b101 O
b10100000 >
b10100000 B
b10100000 M
0&
#165
0/
b11 9
b1 :
1&
#170
0&
#175
1/
b1 9
b11 :
1&
#180
b110 =
b110 E
b110 J
b110 O
b101000000 >
b101000000 B
b101000000 M
0&
#185
0/
b11 9
b1 :
1&
#190
0&
#195
1/
b1 9
b11 :
1&
#200
b111 =
b111 E
b111 J
b111 O
b1010000000 >
b1010000000 B
b1010000000 M
0&
#205
0/
b11 9
b1 :
1&
#210
0&
#215
1/
b1 9
b11 :
1&
#220
b1000 =
b1000 E
b1000 J
b1000 O
b10100000000 >
b10100000000 B
b10100000000 M
0&
#225
0/
b11 9
b1 :
1&
#230
0&
#235
1/
b1 9
b11 :
1&
#240
b1001 =
b1001 E
b1001 J
b1001 O
b101000000000 >
b101000000000 B
b101000000000 M
0&
#245
0/
b11 9
b1 :
1&
#250
0&
#255
1/
b1 9
b11 :
1&
#260
b1010 =
b1010 E
b1010 J
b1010 O
b1010000000000 >
b1010000000000 B
b1010000000000 M
0&
#265
0/
b11 9
b1 :
1&
#270
0&
#275
1/
b1 9
b11 :
1&
#280
b1011 =
b1011 E
b1011 J
b1011 O
b10100000000000 >
b10100000000000 B
b10100000000000 M
0&
#285
0/
b11 9
b1 :
1&
#290
0&
#295
1/
b1 9
b11 :
1&
#300
b1100 =
b1100 E
b1100 J
b1100 O
b101000000000000 >
b101000000000000 B
b101000000000000 M
0&
#305
0/
b11 9
b1 :
1&
#310
0&
#315
1/
b1 9
b11 :
1&
#320
b1101 =
b1101 E
b1101 J
b1101 O
b1010000000000000 >
b1010000000000000 B
b1010000000000000 M
0&
#325
0/
b11 9
b1 :
1&
#330
0&
#335
1/
b1 9
b11 :
1&
#340
b1110 =
b1110 E
b1110 J
b1110 O
b10100000000000000 >
b10100000000000000 B
b10100000000000000 M
0&
#345
0/
b11 9
b1 :
1&
#350
0&
#355
1/
b1 9
b11 :
1&
#360
b1111 =
b1111 E
b1111 J
b1111 O
b101000000000000000 >
b101000000000000000 B
b101000000000000000 M
0&
#365
0/
b11 9
b1 :
1&
#370
0&
#375
1/
b1 9
b11 :
1&
#380
b100 9
1.
b10000 =
b10000 E
b10000 J
b10000 O
b1010000000000000000 >
b1010000000000000000 B
b1010000000000000000 M
0&
#385
1"
0/
b100 :
1&
#390
0&
#395
1&
#400
0&
#405
b1111101000 %
b1111101000 ,
b1111101000 <
b1111101000 N
b1111101000 $
b1111101000 +
b1111101000 ;
b1111101000 K
b11110100001001000000 S
b10 *
b1111101000 U
b1111101000 T
1&
#410
0&
#415
b0 9
1(
1&
#420
0&
#425
11
0"
b1 9
b0 :
1&
#430
0.
b0 !
b0 0
b0 ?
b0 D
b1111101000 >
b1111101000 B
b1111101000 M
b0 =
b0 E
b0 J
b0 O
b1111101000 R
0&
#435
01
b1 :
b11 9
0(
1&
#440
0&
#445
1/
b1 9
b11 :
1&
#450
b11111010000 >
b11111010000 B
b11111010000 M
b1 =
b1 E
b1 J
b1 O
0&
#455
0/
b11 9
b1 :
1&
#460
0&
#465
1/
b1 9
b11 :
1&
#470
b111110100000 >
b111110100000 B
b111110100000 M
b10 =
b10 E
b10 J
b10 O
0&
#475
0/
b11 9
b1 :
1&
#480
0&
#485
1/
b1 9
b11 :
1&
#490
1-
b1111101000000 >
b1111101000000 B
b1111101000000 M
b11 =
b11 E
b11 J
b11 O
0&
#495
0/
b10 9
b1 :
1&
#500
0&
#505
12
b11 9
b10 :
1&
#510
b1111101000000 !
b1111101000000 0
b1111101000000 ?
b1111101000000 D
0&
#515
1/
02
b1 9
b11 :
1&
#520
0-
b100 =
b100 E
b100 J
b100 O
b11111010000000 >
b11111010000000 B
b11111010000000 M
0&
#525
0/
b11 9
b1 :
1&
#530
0&
#535
1/
b1 9
b11 :
1&
#540
1-
b101 =
b101 E
b101 J
b101 O
b111110100000000 >
b111110100000000 B
b111110100000000 M
0&
#545
0/
b10 9
b1 :
1&
#550
0&
#555
12
b11 9
b10 :
1&
#560
b1001110001000000 !
b1001110001000000 0
b1001110001000000 ?
b1001110001000000 D
0&
#565
1/
02
b1 9
b11 :
1&
#570
b1111101000000000 >
b1111101000000000 B
b1111101000000000 M
b110 =
b110 E
b110 J
b110 O
0&
#575
0/
b10 9
b1 :
1&
#580
0&
#585
12
b11 9
b10 :
1&
#590
b11001011001000000 !
b11001011001000000 0
b11001011001000000 ?
b11001011001000000 D
0&
#595
1/
02
b1 9
b11 :
1&
#600
b111 =
b111 E
b111 J
b111 O
b11111010000000000 >
b11111010000000000 B
b11111010000000000 M
0&
#605
0/
b10 9
b1 :
1&
#610
0&
#615
12
b11 9
b10 :
1&
#620
b111000101001000000 !
b111000101001000000 0
b111000101001000000 ?
b111000101001000000 D
0&
#625
1/
02
b1 9
b11 :
1&
#630
b111110100000000000 >
b111110100000000000 B
b111110100000000000 M
b1000 =
b1000 E
b1000 J
b1000 O
0&
#635
0/
b10 9
b1 :
1&
#640
0&
#645
12
b11 9
b10 :
1&
#650
b1110111001001000000 !
b1110111001001000000 0
b1110111001001000000 ?
b1110111001001000000 D
0&
#655
1/
02
b1 9
b11 :
1&
#660
b1001 =
b1001 E
b1001 J
b1001 O
b1111101000000000000 >
b1111101000000000000 B
b1111101000000000000 M
0&
#665
0/
b10 9
b1 :
1&
#670
0&
#675
12
b11 9
b10 :
1&
#680
b11110100001001000000 !
b11110100001001000000 0
b11110100001001000000 ?
b11110100001001000000 D
0&
#685
1/
02
b1 9
b11 :
1&
#690
0-
b11111010000000000000 >
b11111010000000000000 B
b11111010000000000000 M
b1010 =
b1010 E
b1010 J
b1010 O
0&
#695
0/
b11 9
b1 :
1&
#700
0&
#705
1/
b1 9
b11 :
1&
#710
b111110100000000000000 >
b111110100000000000000 B
b111110100000000000000 M
b1011 =
b1011 E
b1011 J
b1011 O
0&
#715
0/
b11 9
b1 :
1&
#720
0&
#725
1/
b1 9
b11 :
1&
#730
b1111101000000000000000 >
b1111101000000000000000 B
b1111101000000000000000 M
b1100 =
b1100 E
b1100 J
b1100 O
0&
#735
0/
b11 9
b1 :
1&
#740
0&
#745
1/
b1 9
b11 :
1&
#750
b11111010000000000000000 >
b11111010000000000000000 B
b11111010000000000000000 M
b1101 =
b1101 E
b1101 J
b1101 O
0&
#755
0/
b11 9
b1 :
1&
#760
0&
#765
1/
b1 9
b11 :
1&
#770
b111110100000000000000000 >
b111110100000000000000000 B
b111110100000000000000000 M
b1110 =
b1110 E
b1110 J
b1110 O
0&
#775
0/
b11 9
b1 :
1&
#780
0&
#785
1/
b1 9
b11 :
1&
#790
b1111101000000000000000000 >
b1111101000000000000000000 B
b1111101000000000000000000 M
b1111 =
b1111 E
b1111 J
b1111 O
0&
#795
0/
b11 9
b1 :
1&
#800
0&
#805
1/
b1 9
b11 :
1&
#810
b100 9
1.
b11111010000000000000000000 >
b11111010000000000000000000 B
b11111010000000000000000000 M
b10000 =
b10000 E
b10000 J
b10000 O
0&
#815
1"
0/
b100 :
1&
#820
0&
#825
1&
#830
0&
#835
b1111111111111111 %
b1111111111111111 ,
b1111111111111111 <
b1111111111111111 N
b1111111111111111 $
b1111111111111111 +
b1111111111111111 ;
b1111111111111111 K
b11111111111111100000000000000001 S
b11 *
b1111111111111111 U
b1111111111111111 T
1&
#840
0&
#845
b0 9
1(
1&
#850
0&
#855
11
0"
b1 9
b0 :
1&
#860
1-
0.
b1111111111111111 R
b0 =
b0 E
b0 J
b0 O
b1111111111111111 >
b1111111111111111 B
b1111111111111111 M
b0 !
b0 0
b0 ?
b0 D
0&
#865
01
b1 :
b10 9
0(
1&
#870
0&
#875
12
b11 9
b10 :
1&
#880
b1111111111111111 !
b1111111111111111 0
b1111111111111111 ?
b1111111111111111 D
0&
#885
1/
02
b1 9
b11 :
1&
#890
b11111111111111110 >
b11111111111111110 B
b11111111111111110 M
b1 =
b1 E
b1 J
b1 O
0&
#895
0/
b10 9
b1 :
1&
#900
0&
#905
12
b11 9
b10 :
1&
#910
b101111111111111101 !
b101111111111111101 0
b101111111111111101 ?
b101111111111111101 D
0&
#915
1/
02
b1 9
b11 :
1&
#920
b10 =
b10 E
b10 J
b10 O
b111111111111111100 >
b111111111111111100 B
b111111111111111100 M
0&
#925
0/
b10 9
b1 :
1&
#930
0&
#935
12
b11 9
b10 :
1&
#940
b1101111111111111001 !
b1101111111111111001 0
b1101111111111111001 ?
b1101111111111111001 D
0&
#945
1/
02
b1 9
b11 :
1&
#950
b1111111111111111000 >
b1111111111111111000 B
b1111111111111111000 M
b11 =
b11 E
b11 J
b11 O
0&
#955
0/
b10 9
b1 :
1&
#960
0&
#965
12
b11 9
b10 :
1&
#970
b11101111111111110001 !
b11101111111111110001 0
b11101111111111110001 ?
b11101111111111110001 D
0&
#975
1/
02
b1 9
b11 :
1&
#980
b100 =
b100 E
b100 J
b100 O
b11111111111111110000 >
b11111111111111110000 B
b11111111111111110000 M
0&
#985
0/
b10 9
b1 :
1&
#990
0&
#995
12
b11 9
b10 :
1&
#1000
b111101111111111100001 !
b111101111111111100001 0
b111101111111111100001 ?
b111101111111111100001 D
0&
#1005
1/
02
b1 9
b11 :
1&
#1010
b111111111111111100000 >
b111111111111111100000 B
b111111111111111100000 M
b101 =
b101 E
b101 J
b101 O
0&
#1015
0/
b10 9
b1 :
1&
#1020
0&
#1025
12
b11 9
b10 :
1&
#1030
b1111101111111111000001 !
b1111101111111111000001 0
b1111101111111111000001 ?
b1111101111111111000001 D
0&
#1035
1/
02
b1 9
b11 :
1&
#1040
b110 =
b110 E
b110 J
b110 O
b1111111111111111000000 >
b1111111111111111000000 B
b1111111111111111000000 M
0&
#1045
0/
b10 9
b1 :
1&
#1050
0&
#1055
12
b11 9
b10 :
1&
#1060
b11111101111111110000001 !
b11111101111111110000001 0
b11111101111111110000001 ?
b11111101111111110000001 D
0&
#1065
1/
02
b1 9
b11 :
1&
#1070
b11111111111111110000000 >
b11111111111111110000000 B
b11111111111111110000000 M
b111 =
b111 E
b111 J
b111 O
0&
#1075
0/
b10 9
b1 :
1&
#1080
0&
#1085
12
b11 9
b10 :
1&
#1090
b111111101111111100000001 !
b111111101111111100000001 0
b111111101111111100000001 ?
b111111101111111100000001 D
0&
#1095
1/
02
b1 9
b11 :
1&
#1100
b1000 =
b1000 E
b1000 J
b1000 O
b111111111111111100000000 >
b111111111111111100000000 B
b111111111111111100000000 M
0&
#1105
0/
b10 9
b1 :
1&
#1110
0&
#1115
12
b11 9
b10 :
1&
#1120
b1111111101111111000000001 !
b1111111101111111000000001 0
b1111111101111111000000001 ?
b1111111101111111000000001 D
0&
#1125
1/
02
b1 9
b11 :
1&
#1130
b1111111111111111000000000 >
b1111111111111111000000000 B
b1111111111111111000000000 M
b1001 =
b1001 E
b1001 J
b1001 O
0&
#1135
0/
b10 9
b1 :
1&
#1140
0&
#1145
12
b11 9
b10 :
1&
#1150
b11111111101111110000000001 !
b11111111101111110000000001 0
b11111111101111110000000001 ?
b11111111101111110000000001 D
0&
#1155
1/
02
b1 9
b11 :
1&
#1160
b1010 =
b1010 E
b1010 J
b1010 O
b11111111111111110000000000 >
b11111111111111110000000000 B
b11111111111111110000000000 M
0&
#1165
0/
b10 9
b1 :
1&
#1170
0&
#1175
12
b11 9
b10 :
1&
#1180
b111111111101111100000000001 !
b111111111101111100000000001 0
b111111111101111100000000001 ?
b111111111101111100000000001 D
0&
#1185
1/
02
b1 9
b11 :
1&
#1190
b111111111111111100000000000 >
b111111111111111100000000000 B
b111111111111111100000000000 M
b1011 =
b1011 E
b1011 J
b1011 O
0&
#1195
0/
b10 9
b1 :
1&
#1200
0&
#1205
12
b11 9
b10 :
1&
#1210
b1111111111101111000000000001 !
b1111111111101111000000000001 0
b1111111111101111000000000001 ?
b1111111111101111000000000001 D
0&
#1215
1/
02
b1 9
b11 :
1&
#1220
b1100 =
b1100 E
b1100 J
b1100 O
b1111111111111111000000000000 >
b1111111111111111000000000000 B
b1111111111111111000000000000 M
0&
#1225
0/
b10 9
b1 :
1&
#1230
0&
#1235
12
b11 9
b10 :
1&
#1240
b11111111111101110000000000001 !
b11111111111101110000000000001 0
b11111111111101110000000000001 ?
b11111111111101110000000000001 D
0&
#1245
1/
02
b1 9
b11 :
1&
#1250
b11111111111111110000000000000 >
b11111111111111110000000000000 B
b11111111111111110000000000000 M
b1101 =
b1101 E
b1101 J
b1101 O
0&
#1255
0/
b10 9
b1 :
1&
#1260
0&
#1265
12
b11 9
b10 :
1&
#1270
b111111111111101100000000000001 !
b111111111111101100000000000001 0
b111111111111101100000000000001 ?
b111111111111101100000000000001 D
0&
#1275
1/
02
b1 9
b11 :
1&
#1280
b1110 =
b1110 E
b1110 J
b1110 O
b111111111111111100000000000000 >
b111111111111111100000000000000 B
b111111111111111100000000000000 M
0&
#1285
0/
b10 9
b1 :
1&
#1290
0&
#1295
12
b11 9
b10 :
1&
#1300
b1111111111111101000000000000001 !
b1111111111111101000000000000001 0
b1111111111111101000000000000001 ?
b1111111111111101000000000000001 D
0&
#1305
1/
02
b1 9
b11 :
1&
#1310
b1111111111111111000000000000000 >
b1111111111111111000000000000000 B
b1111111111111111000000000000000 M
b1111 =
b1111 E
b1111 J
b1111 O
0&
#1315
0/
b10 9
b1 :
1&
#1320
0&
#1325
12
b11 9
b10 :
1&
#1330
b11111111111111100000000000000001 !
b11111111111111100000000000000001 0
b11111111111111100000000000000001 ?
b11111111111111100000000000000001 D
0&
#1335
1/
02
b1 9
b11 :
1&
#1340
b100 9
0-
1.
b10000 =
b10000 E
b10000 J
b10000 O
b11111111111111110000000000000000 >
b11111111111111110000000000000000 B
b11111111111111110000000000000000 M
0&
#1345
1"
0/
b100 :
1&
#1350
0&
#1355
1&
#1360
0&
#1365
b11000000111001 %
b11000000111001 ,
b11000000111001 <
b11000000111001 N
b0 $
b0 +
b0 ;
b0 K
b0 S
b100 *
b11000000111001 U
b0 T
1&
#1370
0&
#1375
b0 9
1(
1&
#1380
0&
#1385
11
0"
b1 9
b0 :
1&
#1390
1-
0.
b0 !
b0 0
b0 ?
b0 D
b0 >
b0 B
b0 M
b0 =
b0 E
b0 J
b0 O
b11000000111001 R
0&
#1395
01
b1 :
b10 9
0(
1&
#1400
0&
#1405
12
b11 9
b10 :
1&
#1410
0&
#1415
1/
02
b1 9
b11 :
1&
#1420
0-
b1 =
b1 E
b1 J
b1 O
0&
#1425
0/
b11 9
b1 :
1&
#1430
0&
#1435
1/
b1 9
b11 :
1&
#1440
b10 =
b10 E
b10 J
b10 O
0&
#1445
0/
b11 9
b1 :
1&
#1450
0&
#1455
1/
b1 9
b11 :
1&
#1460
1-
b11 =
b11 E
b11 J
b11 O
0&
#1465
0/
b10 9
b1 :
1&
#1470
0&
#1475
12
b11 9
b10 :
1&
#1480
0&
#1485
1/
02
b1 9
b11 :
1&
#1490
b100 =
b100 E
b100 J
b100 O
0&
#1495
0/
b10 9
b1 :
1&
#1500
0&
#1505
12
b11 9
b10 :
1&
#1510
0&
#1515
1/
02
b1 9
b11 :
1&
#1520
b101 =
b101 E
b101 J
b101 O
0&
#1525
0/
b10 9
b1 :
1&
#1530
0&
#1535
12
b11 9
b10 :
1&
#1540
0&
#1545
1/
02
b1 9
b11 :
1&
#1550
0-
b110 =
b110 E
b110 J
b110 O
0&
#1555
0/
b11 9
b1 :
1&
#1560
0&
#1565
1/
b1 9
b11 :
1&
#1570
b111 =
b111 E
b111 J
b111 O
0&
#1575
0/
b11 9
b1 :
1&
#1580
0&
#1585
1/
b1 9
b11 :
1&
#1590
b1000 =
b1000 E
b1000 J
b1000 O
0&
#1595
0/
b11 9
b1 :
1&
#1600
0&
#1605
1/
b1 9
b11 :
1&
#1610
b1001 =
b1001 E
b1001 J
b1001 O
0&
#1615
0/
b11 9
b1 :
1&
#1620
0&
#1625
1/
b1 9
b11 :
1&
#1630
b1010 =
b1010 E
b1010 J
b1010 O
0&
#1635
0/
b11 9
b1 :
1&
#1640
0&
#1645
1/
b1 9
b11 :
1&
#1650
b1011 =
b1011 E
b1011 J
b1011 O
0&
#1655
0/
b11 9
b1 :
1&
#1660
0&
#1665
1/
b1 9
b11 :
1&
#1670
1-
b1100 =
b1100 E
b1100 J
b1100 O
0&
#1675
0/
b10 9
b1 :
1&
#1680
0&
#1685
12
b11 9
b10 :
1&
#1690
0&
#1695
1/
02
b1 9
b11 :
1&
#1700
b1101 =
b1101 E
b1101 J
b1101 O
0&
#1705
0/
b10 9
b1 :
1&
#1710
0&
#1715
12
b11 9
b10 :
1&
#1720
0&
#1725
1/
02
b1 9
b11 :
1&
#1730
0-
b1110 =
b1110 E
b1110 J
b1110 O
0&
#1735
0/
b11 9
b1 :
1&
#1740
0&
#1745
1/
b1 9
b11 :
1&
#1750
b1111 =
b1111 E
b1111 J
b1111 O
0&
#1755
0/
b11 9
b1 :
1&
#1760
0&
#1765
1/
b1 9
b11 :
1&
#1770
b100 9
1.
b10000 =
b10000 E
b10000 J
b10000 O
0&
#1775
1"
0/
b100 :
1&
#1780
0&
#1785
1&
#1790
0&
#1795
b1 %
b1 ,
b1 <
b1 N
b1 $
b1 +
b1 ;
b1 K
b1 S
b101 *
b1 U
b1 T
1&
#1800
0&
#1805
b0 9
1(
1&
#1810
0&
#1815
11
0"
b1 9
b0 :
1&
