bcd_to_bin/Ultimo/b2bin_comparador.v
module b2bin_comparador #(
    parameter N     = 16,
    parameter WIDTH = 5
)(
    input  wire [WIDTH-1:0] count,
    output wire             Z
);

    assign Z = (count == N[WIDTH-1:0]) ? 1'b1 : 1'b0;

endmodule

bcd_to_bin/Ultimo/b2bin_contador_i.v
module b2bin_contador_i #(
    parameter WIDTH = 5
)(
    input  wire              clk,
    input  wire              rst,
    input  wire              inc,
    output reg [WIDTH-1:0]   count
);

    always @(negedge clk) begin
        if (rst)
            count <= {WIDTH{1'b0}};
        else if (inc)
            count <= count + 1'b1;
    end

endmodule

bcd_to_bin/Ultimo/b2bin_reg_msb.v
module b2bin_reg_msb (
    input  wire       clk,
    input  wire       LD_MSB,
    input  wire [3:0] digito_actual,
    output reg  [3:0] MSB
);

    always @(negedge clk) begin
        if (LD_MSB)
            MSB <= digito_actual;
    end

endmodule

bcd_to_bin/Ultimo/b2bin_reg_a32.v
module b2bin_reg_a32 (
    input  wire         clk,
    input  wire         LD,
    input  wire         SH,
    input  wire         COMMIT,
    input  wire         SUB,
    input  wire [1:0]   digit_sel,   
    input  wire [15:0]  a_in,       
    output reg  [31:0]  A
);

    always @(negedge clk) begin
        if (LD)
            A <= {a_in, 16'b0};
        else if (SH)
            A <= A >> 1;
        else if (COMMIT && SUB) begin
            case (digit_sel)
                2'd0: A[19:16] <= A[19:16] - 4'd3;
                2'd1: A[23:20] <= A[23:20] - 4'd3;
                2'd2: A[27:24] <= A[27:24] - 4'd3;
                2'd3: A[31:28] <= A[31:28] - 4'd3;
            endcase
        end
    end

endmodule

bcd_to_bin/Ultimo/b2bin_datapath.v
module b2bin_datapath (
    input  wire         clk,
    input  wire [15:0]  a,           
    input  wire         LD,
    input  wire         SH,
    input  wire         LD_MSB,
    input  wire         COMMIT,
    input  wire [1:0]   digit_sel,
    output wire         SUB,     
    output wire         Z,       
    output wire [15:0]  bin      
);

    wire [31:0] A;
    wire [3:0]  digito_actual;
    wire [3:0]  MSB;
    wire [4:0]  count;

    assign digito_actual = (digit_sel == 2'd0) ? A[19:16] :
                            (digit_sel == 2'd1) ? A[23:20] :
                            (digit_sel == 2'd2) ? A[27:24] :
                                                   A[31:28];

    b2bin_reg_a32 u_reg_a32 (
        .clk       (clk),
        .LD        (LD),
        .SH        (SH),
        .COMMIT    (COMMIT),
        .SUB       (SUB),
        .digit_sel (digit_sel),
        .a_in      (a),
        .A         (A)
    );

    b2bin_reg_msb u_reg_msb (
        .clk           (clk),
        .LD_MSB        (LD_MSB),
        .digito_actual (digito_actual),
        .MSB           (MSB)
    );

    assign SUB = (MSB >= 4'd8) ? 1'b1 : 1'b0;
    assign bin = A[15:0];

    b2bin_contador_i #(.WIDTH(5)) u_contador_i (
        .clk   (clk),
        .rst   (LD),
        .inc   (SH),
        .count (count)
    );

    b2bin_comparador #(.N(16), .WIDTH(5)) u_comparador (
        .count (count),
        .Z     (Z)
    );

endmodule

bcd_to_bin/Ultimo/b2bin_control.v
module b2bin_control (
    input  wire clk,
    input  wire rst,
    input  wire start,
    input  wire SUB,
    input  wire Z,
    output reg  LD,
    output reg  SH,
    output reg  LD_MSB,
    output reg  COMMIT,
    output reg  [1:0] digit_sel,
    output reg  DONE
);

    localparam [3:0]
        START  = 4'd0,
        SHIFT  = 4'd1,
        CHECK1 = 4'd2, SUB1 = 4'd3,
        CHECK2 = 4'd4, SUB2 = 4'd5,
        CHECK3 = 4'd6, SUB3 = 4'd7,
        CHECK4 = 4'd8, SUB4 = 4'd9,
        DONEST = 4'd10;

    reg [3:0] state, next_state;

    always @(posedge clk or posedge rst) begin
        if (rst)
            state <= START;
        else
            state <= next_state;
    end

    always @(*) begin
        case (state)
            START:  next_state = start ? SHIFT  : START;
            SHIFT:  next_state = Z     ? DONEST : CHECK1;

            CHECK1: next_state = SUB ? SUB1 : CHECK2;
            SUB1:   next_state = CHECK2;

            CHECK2: next_state = SUB ? SUB2 : CHECK3;
            SUB2:   next_state = CHECK3;

            CHECK3: next_state = SUB ? SUB3 : CHECK4;
            SUB3:   next_state = CHECK4;

            CHECK4: next_state = SUB ? SUB4 : SHIFT;
            SUB4:   next_state = SHIFT;

            DONEST: next_state = start ? START : DONEST;
            default: next_state = START;
        endcase
    end

    always @(*) begin
        LD        = 1'b0;
        SH        = 1'b0;
        LD_MSB    = 1'b0;
        COMMIT    = 1'b0;
        digit_sel = 2'd0;
        DONE      = 1'b0;
        case (state)
            START:  LD = 1'b1;
            SHIFT:  SH = 1'b1;

            CHECK1: begin LD_MSB = 1'b1; digit_sel = 2'd0; end
            SUB1:   begin COMMIT = 1'b1; digit_sel = 2'd0; end

            CHECK2: begin LD_MSB = 1'b1; digit_sel = 2'd1; end
            SUB2:   begin COMMIT = 1'b1; digit_sel = 2'd1; end

            CHECK3: begin LD_MSB = 1'b1; digit_sel = 2'd2; end
            SUB3:   begin COMMIT = 1'b1; digit_sel = 2'd2; end

            CHECK4: begin LD_MSB = 1'b1; digit_sel = 2'd3; end
            SUB4:   begin COMMIT = 1'b1; digit_sel = 2'd3; end

            DONEST: DONE = 1'b1;
            default: ;
        endcase
    end

endmodule

bcd_to_bin/Ultimo/b2bin_top.v
module b2bin_top (
    input  wire         clk,
    input  wire         rst,
    input  wire         start,
    input  wire [15:0]  a,      // BCD empacado (4 digitos)
    output wire [15:0]  bin,
    output wire         DONE
);

    wire LD, SH, LD_MSB, COMMIT;
    wire [1:0] digit_sel;
    wire SUB, Z;

    b2bin_control u_control (
        .clk        (clk),
        .rst        (rst),
        .start      (start),
        .SUB        (SUB),
        .Z          (Z),
        .LD         (LD),
        .SH         (SH),
        .LD_MSB     (LD_MSB),
        .COMMIT     (COMMIT),
        .digit_sel  (digit_sel),
        .DONE       (DONE)
    );

    b2bin_datapath u_datapath (
        .clk       (clk),
        .a         (a),
        .LD        (LD),
        .SH        (SH),
        .LD_MSB    (LD_MSB),
        .COMMIT    (COMMIT),
        .digit_sel (digit_sel),
        .SUB       (SUB),
        .Z         (Z),
        .bin       (bin)
    );

endmodule

bcd_to_bin/Ultimo/b2bin_top_TB.v
module tb_b2bin;

    reg              clk;
    reg              rst;
    reg              start;
    reg  [15:0]      a;      
    wire [15:0]      bin;
    wire             DONE;

    integer errors = 0;
    integer tests  = 0;

    b2bin_top uut (
        .clk   (clk),
        .rst   (rst),
        .start (start),
        .a     (a),
        .bin   (bin),
        .DONE  (DONE)
    );

    initial clk = 1'b0;
    always #5 clk = ~clk;

    function [15:0] dec_to_bcd_packed(input integer val);
        integer d0, d1, d2, d3;
        begin
            d0 = val % 10;
            d1 = (val / 10) % 10;
            d2 = (val / 100) % 10;
            d3 = (val / 1000) % 10;
            dec_to_bcd_packed = {d3[3:0], d2[3:0], d1[3:0], d0[3:0]};
        end
    endfunction

    task run_test(input integer decimal_val);
        reg [15:0] bcd_in;
        reg [15:0] expected;
        begin
            tests    = tests + 1;
            bcd_in   = dec_to_bcd_packed(decimal_val);
            expected = decimal_val[15:0];

            a = bcd_in;
            start = 1'b0;
            @(posedge clk);

            start = 1'b1;
            @(posedge clk);
            @(posedge clk);
            start = 1'b0;

            wait (DONE == 1'b1);
            @(posedge clk);

            if (bin !== expected) begin
                $display("FALLO: decimal=%0d (bcd=%h) -> bin=%0d (esperado %0d)",
                          decimal_val, bcd_in, bin, expected);
                errors = errors + 1;
            end else begin
                $display("OK   : decimal=%0d (bcd=%h) -> bin=%0d", decimal_val, bcd_in, bin);
            end

            @(posedge clk);
        end
    endtask

    initial begin
        $dumpfile("b2bin_top_TB.vcd");
        $dumpvars(0, tb_b2bin);

        rst   = 1'b1;
        start = 1'b0;
        a = 0;
        repeat (2) @(posedge clk);
        rst = 1'b0;
        @(posedge clk);

        run_test(0);      // 0000 -> 0
        run_test(9);      // 0009 -> 9
        run_test(10);     // 0010 -> 10
        run_test(67);     // 0067 -> 67
        run_test(150);    // 0150 -> 150
        run_test(1234);   // 1234 -> 1234
        run_test(9999);   // 9999 -> 9999 (maximo con 4 digitos)
        run_test(8);      // 0008 -> 8
        run_test(25);     // 0025 -> 25
        run_test(103);    // 0103 -> 103

        $display("--------------------------------------------------");
        if (errors == 0)
            $display("TODAS LAS PRUEBAS PASARON (%0d/%0d)", tests, tests);
        else
            $display("%0d DE %0d PRUEBAS FALLARON", errors, tests);

        $finish;
    end

endmodule

bcd_to_bin/Ultimo/b2bin_top_TB.vcd
$date
	Thu Jul 16 21:04:23 2026
$end
$version
	Icarus Verilog
$end
$timescale
	1ps
$end
$scope module tb_b2bin $end
$var wire 16 ! bin [15:0] $end
$var wire 1 " DONE $end
$var reg 16 # a [15:0] $end
$var reg 1 $ clk $end
$var reg 1 % rst $end
$var reg 1 & start $end
$var integer 32 ' errors [31:0] $end
$var integer 32 ( tests [31:0] $end
$scope function dec_to_bcd_packed $end
$var integer 32 ) d0 [31:0] $end
$var integer 32 * d1 [31:0] $end
$var integer 32 + d2 [31:0] $end
$var integer 32 , d3 [31:0] $end
$var integer 32 - val [31:0] $end
$upscope $end
$scope module uut $end
$var wire 16 . a [15:0] $end
$var wire 1 $ clk $end
$var wire 1 % rst $end
$var wire 1 & start $end
$var wire 2 / digit_sel [1:0] $end
$var wire 16 0 bin [15:0] $end
$var wire 1 1 Z $end
$var wire 1 2 SUB $end
$var wire 1 3 SH $end
$var wire 1 4 LD_MSB $end
$var wire 1 5 LD $end
$var wire 1 " DONE $end
$var wire 1 6 COMMIT $end
$scope module u_control $end
$var wire 1 $ clk $end
$var wire 1 % rst $end
$var wire 1 & start $end
$var wire 1 1 Z $end
$var wire 1 2 SUB $end
$var parameter 4 7 CHECK1 $end
$var parameter 4 8 CHECK2 $end
$var parameter 4 9 CHECK3 $end
$var parameter 4 : CHECK4 $end
$var parameter 4 ; DONEST $end
$var parameter 4 < SHIFT $end
$var parameter 4 = START $end
$var parameter 4 > SUB1 $end
$var parameter 4 ? SUB2 $end
$var parameter 4 @ SUB3 $end
$var parameter 4 A SUB4 $end
$var reg 1 6 COMMIT $end
$var reg 1 " DONE $end
$var reg 1 5 LD $end
$var reg 1 4 LD_MSB $end
$var reg 1 3 SH $end
$var reg 2 B digit_sel [1:0] $end
$var reg 4 C next_state [3:0] $end
$var reg 4 D state [3:0] $end
$upscope $end
$scope module u_datapath $end
$var wire 1 6 COMMIT $end
$var wire 1 5 LD $end
$var wire 1 4 LD_MSB $end
$var wire 1 3 SH $end
$var wire 16 E a [15:0] $end
$var wire 1 $ clk $end
$var wire 2 F digit_sel [1:0] $end
$var wire 4 G digito_actual [3:0] $end
$var wire 5 H count [4:0] $end
$var wire 16 I bin [15:0] $end
$var wire 1 1 Z $end
$var wire 1 2 SUB $end
$var wire 4 J MSB [3:0] $end
$var wire 32 K A [31:0] $end
$scope module u_comparador $end
$var wire 5 L count [4:0] $end
$var wire 1 1 Z $end
$var parameter 32 M N $end
$var parameter 32 N WIDTH $end
$upscope $end
$scope module u_contador_i $end
$var wire 1 $ clk $end
$var wire 1 3 inc $end
$var wire 1 5 rst $end
$var parameter 32 O WIDTH $end
$var reg 5 P count [4:0] $end
$upscope $end
$scope module u_reg_a32 $end
$var wire 1 6 COMMIT $end
$var wire 1 5 LD $end
$var wire 1 3 SH $end
$var wire 1 2 SUB $end
$var wire 16 Q a_in [15:0] $end
$var wire 1 $ clk $end
$var wire 2 R digit_sel [1:0] $end
$var reg 32 S A [31:0] $end
$upscope $end
$scope module u_reg_msb $end
$var wire 1 4 LD_MSB $end
$var wire 1 $ clk $end
$var wire 4 T digito_actual [3:0] $end
$var reg 4 U MSB [3:0] $end
$upscope $end
$upscope $end
$upscope $end
$scope task run_test $end
$var reg 16 V bcd_in [15:0] $end
$var reg 16 W expected [15:0] $end
$var integer 32 X decimal_val [31:0] $end
$upscope $end
$upscope $end
$enddefinitions $end
$comment Show the parameter values. $end
$dumpall
b101 O
b101 N
b10000 M
b1001 A
b111 @
b101 ?
b11 >
b0 =
b1 <
b1010 ;
b1000 :
b110 9
b100 8
b10 7
$end
#0
$dumpvars
bx X
bx W
bx V
bx U
bx T
bx S
b0 R
b0 Q
bx P
bx L
bx K
bx J
bx I
bx H
bx G
b0 F
b0 E
b0 D
b0 C
b0 B
06
15
04
03
x2
x1
bx 0
b0 /
b0 .
bx -
bx ,
bx +
bx *
bx )
b0 (
b0 '
0&
1%
0$
b0 #
0"
bx !
$end
#5000
1$
#10000
b0 G
b0 T
01
b0 !
b0 0
b0 I
b0 H
b0 L
b0 P
b0 K
b0 S
0$
#15000
0%
1$
#20000
0$
#25000
b0 W
b0 V
b0 ,
b0 +
b0 *
b0 )
b0 -
b1 (
b0 X
1$
#30000
0$
#35000
b1 C
1&
1$
#40000
0$
#45000
13
05
b10 C
b1 D
1$
#50000
b1 H
b1 L
b1 P
0$
#55000
14
03
b0xxx C
b10 D
0&
1$
#60000
b100 C
02
b0 J
b0 U
0$
#65000
b1 /
b1 B
b1 F
b1 R
14
b110 C
b100 D
1$
#70000
0$
#75000
b10 /
b10 B
b10 F
b10 R
14
b1000 C
b110 D
1$
#80000
0$
#85000
b11 /
b11 B
b11 F
b11 R
14
b1 C
b1000 D
1$
#90000
0$
#95000
13
b0 /
b0 B
b0 F
b0 R
04
b10 C
b1 D
1$
#100000
b10 H
b10 L
b10 P
0$
#105000
14
03
b100 C
b10 D
1$
#110000
0$
#115000
b1 /
b1 B
b1 F
b1 R
14
b110 C
b100 D
1$
#120000
0$
#125000
b10 /
b10 B
b10 F
b10 R
14
b1000 C
b110 D
1$
#130000
0$
#135000
b11 /
b11 B
b11 F
b11 R
14
b1 C
b1000 D
1$
#140000
0$
#145000
13
b0 /
b0 B
b0 F
b0 R
04
b10 C
b1 D
1$
#150000
b11 H
b11 L
b11 P
0$
#155000
14
03
b100 C
b10 D
1$
#160000
0$
#165000
b1 /
b1 B
b1 F
b1 R
14
b110 C
b100 D
1$
#170000
0$
#175000
b10 /
b10 B
b10 F
b10 R
14
b1000 C
b110 D
1$
#180000
0$
#185000
b11 /
b11 B
b11 F
b11 R
14
b1 C
b1000 D
1$
#190000
0$
#195000
13
b0 /
b0 B
b0 F
b0 R
04
b10 C
b1 D
1$
#200000
b100 H
b100 L
b100 P
0$
#205000
14
03
b100 C
b10 D
1$
#210000
0$
#215000
b1 /
b1 B
b1 F
b1 R
14
b110 C
b100 D
1$
#220000
0$
#225000
b10 /
b10 B
b10 F
b10 R
14
b1000 C
b110 D
1$
#230000
0$
#235000
b11 /
b11 B
b11 F
b11 R
14
b1 C
b1000 D
1$
#240000
0$
#245000
13
b0 /
b0 B
b0 F
b0 R
04
b10 C
b1 D
1$
#250000
b101 H
b101 L
b101 P
0$
#255000
14
03
b100 C
b10 D
1$
#260000
0$
#265000
b1 /
b1 B
b1 F
b1 R
14
b110 C
b100 D
1$
#270000
0$
#275000
b10 /
b10 B
b10 F
b10 R
14
b1000 C
b110 D
1$
#280000
0$
#285000
b11 /
b11 B
b11 F
b11 R
14
b1 C
b1000 D
1$
#290000
0$
#295000
13
b0 /
b0 B
b0 F
b0 R
04
b10 C
b1 D
1$
#300000
b110 H
b110 L
b110 P
0$
#305000
14
03
b100 C
b10 D
1$
#310000
0$
#315000
b1 /
b1 B
b1 F
b1 R
14
b110 C
b100 D
1$
#320000
0$
#325000
b10 /
b10 B
b10 F
b10 R
14
b1000 C
b110 D
1$
#330000
0$
#335000
b11 /
b11 B
b11 F
b11 R
14
b1 C
b1000 D
1$
#340000
0$
#345000
13
b0 /
b0 B
b0 F
b0 R
04
b10 C
b1 D
1$
#350000
b111 H
b111 L
b111 P
0$
#355000
14
03
b100 C
b10 D
1$
#360000
0$
#365000
b1 /
b1 B
b1 F
b1 R
14
b110 C
b100 D
1$
#370000
0$
#375000
b10 /
b10 B
b10 F
b10 R
14
b1000 C
b110 D
1$
#380000
0$
#385000
b11 /
b11 B
b11 F
b11 R
14
b1 C
b1000 D
1$
#390000
0$
#395000
13
b0 /
b0 B
b0 F
b0 R
04
b10 C
b1 D
1$
#400000
b1000 H
b1000 L
b1000 P
0$
#405000
14
03
b100 C
b10 D
1$
#410000
0$
#415000
b1 /
b1 B
b1 F
b1 R
14
b110 C
b100 D
1$
#420000
0$
#425000
b10 /
b10 B
b10 F
b10 R
14
b1000 C
b110 D
1$
#430000
0$
#435000
b11 /
b11 B
b11 F
b11 R
14
b1 C
b1000 D
1$
#440000
0$
#445000
13
b0 /
b0 B
b0 F
b0 R
04
b10 C
b1 D
1$
#450000
b1001 H
b1001 L
b1001 P
0$
#455000
14
03
b100 C
b10 D
1$
#460000
0$
#465000
b1 /
b1 B
b1 F
b1 R
14
b110 C
b100 D
1$
#470000
0$
#475000
b10 /
b10 B
b10 F
b10 R
14
b1000 C
b110 D
1$
#480000
0$
#485000
b11 /
b11 B
b11 F
b11 R
14
b1 C
b1000 D
1$
#490000
0$
#495000
13
b0 /
b0 B
b0 F
b0 R
04
b10 C
b1 D
1$
#500000
b1010 H
b1010 L
b1010 P
0$
#505000
14
03
b100 C
b10 D
1$
#510000
0$
#515000
b1 /
b1 B
b1 F
b1 R
14
b110 C
b100 D
1$
#520000
0$
#525000
b10 /
b10 B
b10 F
b10 R
14
b1000 C
b110 D
1$
#530000
0$
#535000
b11 /
b11 B
b11 F
b11 R
14
b1 C
b1000 D
1$
#540000
0$
#545000
13
b0 /
b0 B
b0 F
b0 R
04
b10 C
b1 D
1$
#550000
b1011 H
b1011 L
b1011 P
0$
#555000
14
03
b100 C
b10 D
1$
#560000
0$
#565000
b1 /
b1 B
b1 F
b1 R
14
b110 C
b100 D
1$
#570000
0$
#575000
b10 /
b10 B
b10 F
b10 R
14
b1000 C
b110 D
1$
#580000
0$
#585000
b11 /
b11 B
b11 F
b11 R
14
b1 C
b1000 D
1$
#590000
0$
#595000
13
b0 /
b0 B
b0 F
b0 R
04
b10 C
b1 D
1$
#600000
b1100 H
b1100 L
b1100 P
0$
#605000
14
03
b100 C
b10 D
1$
#610000
0$
#615000
b1 /
b1 B
b1 F
b1 R
14
b110 C
b100 D
1$
#620000
0$
#625000
b10 /
b10 B
b10 F
b10 R
14
b1000 C
b110 D
1$
#630000
0$
#635000
b11 /
b11 B
b11 F
b11 R
14
b1 C
b1000 D
1$
#640000
0$
#645000
13
b0 /
b0 B
b0 F
b0 R
04
b10 C
b1 D
1$
#650000
b1101 H
b1101 L
b1101 P
0$
#655000
14
03
b100 C
b10 D
1$
#660000
0$
#665000
b1 /
b1 B
b1 F
b1 R
14
b110 C
b100 D
1$
#670000
0$
#675000
b10 /
b10 B
b10 F
b10 R
14
b1000 C
b110 D
1$
#680000
0$
#685000
b11 /
b11 B
b11 F
b11 R
14
b1 C
b1000 D
1$
#690000
0$
#695000
13
b0 /
b0 B
b0 F
b0 R
04
b10 C
b1 D
1$
#700000
b1110 H
b1110 L
b1110 P
0$
#705000
14
03
b100 C
b10 D
1$
#710000
0$
#715000
b1 /
b1 B
b1 F
b1 R
14
b110 C
b100 D
1$
#720000
0$
#725000
b10 /
b10 B
b10 F
b10 R
14
b1000 C
b110 D
1$
#730000
0$
#735000
b11 /
b11 B
b11 F
b11 R
14
b1 C
b1000 D
1$
#740000
0$
#745000
13
b0 /
b0 B
b0 F
b0 R
04
b10 C
b1 D
1$
#750000
b1111 H
b1111 L
b1111 P
0$
#755000
14
03
b100 C
b10 D
1$
#760000
0$
#765000
b1 /
b1 B
b1 F
b1 R
14
b110 C
b100 D
1$
#770000
0$
#775000
b10 /
b10 B
b10 F
b10 R
14
b1000 C
b110 D
1$
#780000
0$
#785000
b11 /
b11 B
b11 F
b11 R
14
b1 C
b1000 D
1$
#790000
0$
#795000
13
b0 /
b0 B
b0 F
b0 R
04
b10 C
b1 D
1$
#800000
b1010 C
11
b10000 H
b10000 L
b10000 P
0$
#805000
1"
03
b1010 D
1$
#810000
0$
#815000
1$
#820000
0$
#825000
b1001 #
b1001 .
b1001 E
b1001 Q
b1001 W
b1001 V
b1001 )
b1001 -
b10 (
b1001 X
1$
#830000
0$
#835000
b0 C
1&
1$
#840000
0$
#845000
15
0"
b1 C
b0 D
1$
#850000
b1001 G
b1001 T
01
b0 H
b0 L
b0 P
b10010000000000000000 K
b10010000000000000000 S
0$
#855000
13
05
b1 D
b10 C
0&
1$
#860000
b100 G
b100 T
b1000000000000000 !
b1000000000000000 0
b1000000000000000 I
b1001000000000000000 K
b1001000000000000000 S
b1 H
b1 L
b1 P
0$
#865000
14
03
b100 C
b10 D
1$
#870000
b100 J
b100 U
0$
#875000
b0 G
b0 T
b1 /
b1 B
b1 F
b1 R
14
b110 C
b100 D
1$
#880000
b0 J
b0 U
0$
#885000
b10 /
b10 B
b10 F
b10 R
14
b1000 C
b110 D
1$
#890000
0$
#895000
b11 /
b11 B
b11 F
b11 R
14
b1 C
b1000 D
1$
#900000
0$
#905000
b100 G
b100 T
13
b0 /
b0 B
b0 F
b0 R
04
b10 C
b1 D
1$
#910000
b10 G
b10 T
b100000000000000 !
b100000000000000 0
b100000000000000 I
b10 H
b10 L
b10 P
b100100000000000000 K
b100100000000000000 S
0$
#915000
14
03
b100 C
b10 D
1$
#920000
b10 J
b10 U
0$
#925000
b0 G
b0 T
b1 /
b1 B
b1 F
b1 R
14
b110 C
b100 D
1$
#930000
b0 J
b0 U
0$
#935000
b10 /
b10 B
b10 F
b10 R
14
b1000 C
b110 D
1$
#940000
0$
#945000
b11 /
b11 B
b11 F
b11 R
14
b1 C
b1000 D
1$
#950000
0$
#955000
b10 G
b10 T
13
b0 /
b0 B
b0 F
b0 R
04
b10 C
b1 D
1$
#960000
b1 G
b1 T
b10000000000000 !
b10000000000000 0
b10000000000000 I
b10010000000000000 K
b10010000000000000 S
b11 H
b11 L
b11 P
0$
#965000
14
03
b100 C
b10 D
1$
#970000
b1 J
b1 U
0$
#975000
b0 G
b0 T
b1 /
b1 B
b1 F
b1 R
14
b110 C
b100 D
1$
#980000
b0 J
b0 U
0$
#985000
b10 /
b10 B
b10 F
b10 R
14
b1000 C
b110 D
1$
#990000
0$
#995000
b11 /
b11 B
b11 F
b11 R
14
b1 C
b1000 D
1$
#1000000
0$
#1005000
b1 G
b1 T
13
b0 /
b0 B
b0 F
b0 R
04
b10 C
b1 D
1$
#1010000
b0 G
b0 T
b1001000000000000 !
b1001000000000000 0
b1001000000000000 I
b100 H
b100 L
b100 P
b1001000000000000 K
b1001000000000000 S
0$
#1015000
14
03
b100 C
b10 D
1$
#1020000
0$
#1025000
b1 /
b1 B
b1 F
b1 R
14
b110 C
b100 D
1$
#1030000
0$
#1035000
b10 /
b10 B
b10 F
b10 R
14
b1000 C
b110 D
1$
#1040000
0$
#1045000
b11 /
b11 B
b11 F
b11 R
14
b1 C
b1000 D
1$
#1050000
0$
#1055000
13
b0 /
b0 B
b0 F
b0 R
04
b10 C
b1 D
1$
#1060000
b100100000000000 !
b100100000000000 0
b100100000000000 I
b100100000000000 K
b100100000000000 S
b101 H
b101 L
b101 P
0$
#1065000
14
03
b100 C
b10 D
1$
#1070000
0$
#1075000
b1 /
b1 B
b1 F
b1 R
14
b110 C
b100 D
1$
#1080000
0$
#1085000
b10 /
b10 B
b10 F
b10 R
14
b1000 C
b110 D
1$
#1090000
0$
#1095000
b11 /
b11 B
b11 F
b11 R
14
b1 C
b1000 D
1$
#1100000
0$
#1105000
13
b0 /
b0 B
b0 F
b0 R
04
b10 C
b1 D
1$
#1110000
b10010000000000 !
b10010000000000 0
b10010000000000 I
b110 H
b110 L
b110 P
b10010000000000 K
b10010000000000 S
0$
#1115000
14
03
b100 C
b10 D
1$
#1120000
0$
#1125000
b1 /
b1 B
b1 F
b1 R
14
b110 C
b100 D
1$
#1130000
0$
#1135000
b10 /
b10 B
b10 F
b10 R
14
b1000 C
b110 D
1$
#1140000
0$
#1145000
b11 /
b11 B
b11 F
b11 R
14
b1 C
b1000 D
1$
#1150000
0$
#1155000
13
b0 /
b0 B
b0 F
b0 R
04
b10 C
b1 D
1$
#1160000
b1001000000000 !
b1001000000000 0
b1001000000000 I
b1001000000000 K
b1001000000000 S
b111 H
b111 L
b111 P
0$
#1165000
14
03
b100 C
b10 D
1$
#1170000
0$
#1175000
b1 /
b1 B
b1 F
b1 R
14
b110 C
b100 D
1$
#1180000
0$
#1185000
b10 /
b10 B
b10 F
b10 R
14
b1000 C
b110 D
1$
#1190000
0$
#1195000
b11 /
b11 B
b11 F
b11 R
14
b1 C
b1000 D
1$
#1200000
0$
#1205000
13
b0 /
b0 B
b0 F
b0 R
04
b10 C
b1 D
1$
#1210000
b100100000000 !
b100100000000 0
b100100000000 I
b1000 H
b1000 L
b1000 P
b100100000000 K
b100100000000 S
0$
#1215000
14
03
b100 C
b10 D
1$
#1220000
0$
#1225000
b1 /
b1 B
b1 F
b1 R
14
b110 C
b100 D
1$
#1230000
0$
#1235000
b10 /
b10 B
b10 F
b10 R
14
b1000 C
b110 D
1$
#1240000
0$
#1245000
b11 /
b11 B
b11 F
b11 R
14
b1 C
b1000 D
1$
#1250000
0$
#1255000
13
b0 /
b0 B
b0 F
b0 R
04
b10 C
b1 D
1$
#1260000
b10010000000 !
b10010000000 0
b10010000000 I
b10010000000 K
b10010000000 S
b1001 H
b1001 L
b1001 P
0$
#1265000
14
03
b100 C
b10 D
1$
#1270000
0$
#1275000
b1 /
b1 B
b1 F
b1 R
14
b110 C
b100 D
1$
#1280000
0$
#1285000
b10 /
b10 B
b10 F
b10 R
14
b1000 C
b110 D
1$
#1290000
0$
#1295000
b11 /
b11 B
b11 F
b11 R
14
b1 C
b1000 D
1$
#1300000
0$
#1305000
13
b0 /
b0 B
b0 F
b0 R
04
b10 C
b1 D
1$
#1310000
b1001000000 !
b1001000000 0
b1001000000 I
b1010 H
b1010 L
b1010 P
b1001000000 K
b1001000000 S
0$
#1315000
14
03
b100 C
b10 D
1$
#1320000
0$
#1325000
b1 /
b1 B
b1 F
b1 R
14
b110 C
b100 D
1$
#1330000
0$
#1335000
b10 /
b10 B
b10 F
b10 R
14
b1000 C
b110 D
1$
#1340000
0$
#1345000
b11 /
b11 B
b11 F
b11 R
14
b1 C
b1000 D
1$
#1350000
0$
#1355000
13
b0 /
b0 B
b0 F
b0 R
04
b10 C
b1 D
1$
#1360000
b100100000 !
b100100000 0
b100100000 I
b100100000 K
b100100000 S
b1011 H
b1011 L
b1011 P
0$
#1365000
14
03
b100 C
b10 D
1$
#1370000
0$
#1375000
b1 /
b1 B
b1 F
b1 R
14
b110 C
b100 D
1$
#1380000
0$
#1385000
b10 /
b10 B
b10 F
b10 R
14
b1000 C
b110 D
1$
#1390000
0$
#1395000
b11 /
b11 B
b11 F
b11 R
14
b1 C
b1000 D
1$
#1400000
0$
#1405000
13
b0 /
b0 B
b0 F
b0 R
04
b10 C
b1 D
1$
#1410000
b10010000 !
b10010000 0
b10010000 I
b1100 H
b1100 L
b1100 P
b10010000 K
b10010000 S
0$
#1415000
14
03
b100 C
b10 D
1$
#1420000
0$
#1425000
b1 /
b1 B
b1 F
b1 R
14
b110 C
b100 D
1$
#1430000
0$
#1435000
b10 /
b10 B
b10 F
b10 R
14
b1000 C
b110 D
1$
#1440000
0$
#1445000
b11 /
b11 B
b11 F
b11 R
14
b1 C
b1000 D
1$
#1450000
0$
#1455000
13
b0 /
b0 B
b0 F
b0 R
04
b10 C
b1 D
1$
#1460000
b1001000 !
b1001000 0
b1001000 I
b1001000 K
b1001000 S
b1101 H
b1101 L
b1101 P
0$
#1465000
14
03
b100 C
b10 D
1$
#1470000
0$
#1475000
b1 /
b1 B
b1 F
b1 R
14
b110 C
b100 D
1$
#1480000
0$
#1485000
b10 /
b10 B
b10 F
b10 R
14
b1000 C
b110 D
1$
#1490000
0$
#1495000
b11 /
b11 B
b11 F
b11 R
14
b1 C
b1000 D
1$
#1500000
0$
#1505000
13
b0 /
b0 B
b0 F
b0 R
04
b10 C
b1 D
1$
#1510000
b100100 !
b100100 0
b100100 I
b1110 H
b1110 L
b1110 P
b100100 K
b100100 S
0$
#1515000
14
03
b100 C
b10 D
1$
#1520000
0$
#1525000
b1 /
b1 B
b1 F
b1 R
14
b110 C
b100 D
1$
#1530000
0$
#1535000
b10 /
b10 B
b10 F
b10 R
14
b1000 C
b110 D
1$
#1540000
0$
#1545000
b11 /
b11 B
b11 F
b11 R
14
b1 C
b1000 D
1$
#1550000
0$
#1555000
13
b0 /
b0 B
b0 F
b0 R
04
b10 C
b1 D
1$
#1560000
b10010 !
b10010 0
b10010 I
b10010 K
b10010 S
b1111 H
b1111 L
b1111 P
0$
#1565000
14
03
b100 C
b10 D
1$
#1570000
0$
#1575000
b1 /
b1 B
b1 F
b1 R
14
b110 C
b100 D
1$
#1580000
0$
#1585000
b10 /
b10 B
b10 F
b10 R
14
b1000 C
b110 D
1$
#1590000
0$
#1595000
b11 /
b11 B
b11 F
b11 R
14
b1 C
b1000 D
1$
#1600000
0$
#1605000
13
b0 /
b0 B
b0 F
b0 R
04
b10 C
b1 D
1$
#1610000
b1010 C
11
b1001 !
b1001 0
b1001 I
b10000 H
b10000 L
b10000 P
b1001 K
b1001 S
0$
#1615000
1"
03
b1010 D
1$
#1620000
0$
#1625000
1$
#1630000
0$
#1635000
b10000 #
b10000 .
b10000 E
b10000 Q
b1010 W
b10000 V
b1 *
b0 )
b1010 -
b11 (
b1010 X
1$
#1640000
0$
#1645000
b0 C
1&
1$
#1650000
0$
#1655000
15
0"
b1 C
b0 D
1$
#1660000
b0 !
b0 0
b0 I
01
b100000000000000000000 K
b100000000000000000000 S
b0 H
b0 L
b0 P
0$
#1665000
13
05
b1 D
b10 C
0&
1$
#1670000
b1000 G
b1000 T
b1 H
b1 L
b1 P
b10000000000000000000 K
b10000000000000000000 S
0$
#1675000
14
03
b100 C
b10 D
1$
