divisor/comparador.v
// ============================================================
// comparador.v
// Compara el contador i contra N (16 = cantidad de bits de A).
// Z=1 cuando i llega a 16 -> ya se hicieron las 16 iteraciones.
// ============================================================
module comparador #(
    parameter N     = 16,
    parameter WIDTH = 5
)(
    input  wire [WIDTH-1:0] count,
    output wire             Z
);

    assign Z = (count == N[WIDTH-1:0]) ? 1'b1 : 1'b0;

endmodule

divisor/contador_i.v
module contador_i #(
    parameter WIDTH = 5 
)(
    input  wire              clk,
    input  wire              rst,   // = LDA
    input  wire              inc,   // = INC
    output reg [WIDTH-1:0]   count
);

    always @(negedge clk) begin
        if (rst)
            count <= {WIDTH{1'b0}};
        else if (inc)
            count <= count + 1'b1;
    end

endmodule

divisor/reg_ra.v
module reg_ra #(
    parameter N = 16
)(
    input  wire             clk,
    input  wire             LDA,
    input  wire             CO,
    input  wire             AO,
    input  wire             LDR,
    input  wire [N-1:0]     a_in,
    input  wire [N-1:0]     sub_result,
    output reg  [N-1:0]     R,
    output reg  [N-1:0]     A
);

    always @(negedge clk) begin
        if (LDA) begin
            A <= a_in;
            R <= {N{1'b0}};
        end else if (CO) begin
            {R, A} <= {R, A} << 1;
        end else begin
            if (LDR)
                R <= sub_result;
            if (AO)
                A[0] <= 1'b1;
        end
    end

endmodule

divisor/restador.v
module restador #(
    parameter N = 16
)(
    input  wire [N-1:0] R,
    input  wire [N-1:0] B,
    output wire [N-1:0] result,
    output wire         MSB
);

    wire [N:0] diff;

    assign diff   = {1'b0, R} - {1'b0, B};
    assign result = diff[N-1:0];
    assign MSB    = diff[N];   // 1 = negativo (R<B), 0 = R>=B

endmodule

divisor/reg_divisor.v
// ============================================================
// reg_divisor.v
// Registro de B (divisor). Se carga con LDA y se mantiene fijo
// durante todo el proceso. Flanco de BAJADA (negedge clk).
// ============================================================
module reg_divisor #(
    parameter N = 16
)(
    input  wire         clk,
    input  wire         LDA,
    input  wire [N-1:0] b_in,
    output reg  [N-1:0] B
);

    always @(negedge clk) begin
        if (LDA)
            B <= b_in;
    end

endmodule

divisor/datapath.v
module datapath #(
    parameter N          = 16,
    parameter CNT_WIDTH  = 5
)(
    input  wire             clk,
    input  wire [N-1:0]     a,      
    input  wire [N-1:0]     b,      
    input  wire             LDA,
    input  wire             CO,
    input  wire             AO,
    input  wire             INC,
    input  wire             LDR,
    output wire             MSB,    
    output wire             Z,      
    output wire [N-1:0]     Q,      
    output wire [N-1:0]     Rem     
);

    wire [N-1:0]        B_reg;
    wire [N-1:0]         sub_result;
    wire [CNT_WIDTH-1:0] count;

    reg_divisor #(.N(N)) u_reg_divisor (
        .clk  (clk),
        .LDA  (LDA),
        .b_in (b),
        .B    (B_reg)
    );

    restador #(.N(N)) u_restador (
        .R      (Rem),
        .B      (B_reg),
        .result (sub_result),
        .MSB    (MSB)
    );

    reg_ra #(.N(N)) u_reg_ra (
        .clk        (clk),
        .LDA        (LDA),
        .CO         (CO),
        .AO         (AO),
        .LDR        (LDR),
        .a_in       (a),
        .sub_result (sub_result),
        .R          (Rem),
        .A          (Q)
    );

    contador_i #(.WIDTH(CNT_WIDTH)) u_contador_i (
        .clk   (clk),
        .rst   (LDA),
        .inc   (INC),
        .count (count)
    );

    comparador #(.N(N), .WIDTH(CNT_WIDTH)) u_comparador (
        .count (count),
        .Z     (Z)
    );

endmodule

divisor/control.v
module control (
    input  wire clk,
    input  wire rst,   
    input  wire start,
    input  wire MSB,     // signo de R-B: 0=R>=B, 1=R<B
    input  wire Z,       
    output reg  LDA,
    output reg  CO,
    output reg  AO,
    output reg  INC,
    output reg  LDR,
    output reg  DONE
);

    localparam [2:0]
        START = 3'b000,
        SHIFT = 3'b001,
        CHECK = 3'b010,
        ADDST = 3'b011,
        ENDST = 3'b100;

    reg [2:0] state, next_state;

    // Registro de estado: flanco de SUBIDA
    always @(posedge clk or posedge rst) begin
        if (rst)
            state <= START;
        else
            state <= next_state;
    end

    // Logica de siguiente estado
    always @(*) begin
        case (state)
            START: next_state = start ? SHIFT : START;
            SHIFT: next_state = CHECK;
            CHECK: next_state = MSB ? (Z ? ENDST : SHIFT) : ADDST;
            ADDST: next_state = Z ? ENDST : SHIFT;
            ENDST: next_state = START;
            default: next_state = START;
        endcase
    end

    // Salidas (Moore, dependen solo del estado)
    always @(*) begin
        LDA  = 1'b0;
        CO   = 1'b0;
        AO   = 1'b0;
        INC  = 1'b0;
        LDR  = 1'b0;
        DONE = 1'b0;
        case (state)
            START: LDA  = 1'b1;
            SHIFT: begin CO = 1'b1; INC = 1'b1; end
            CHECK: ; // sin senales activas
            ADDST: begin AO = 1'b1; LDR = 1'b1; end
            ENDST: DONE = 1'b1;
            default: ;
        endcase
    end

endmodule

divisor/divisor_top.v
// ============================================================
// divisor_top.v
// Modulo TOP: une Control (FSM) y Datapath (camino de datos)
// del divisor restaurador de numeros binarios.
// ============================================================
module divisor_top #(
    parameter N         = 16,
    parameter CNT_WIDTH = 5
)(
    input  wire             clk,
    input  wire             rst,
    input  wire             start,
    input  wire [N-1:0]     a,      // dividendo
    input  wire [N-1:0]     b,      // divisor
    output wire [N-1:0]     Q,      // cociente
    output wire [N-1:0]     Rem,    // residuo
    output wire             DONE
);

    wire LDA, CO, AO, INC, LDR;
    wire MSB, Z;

    control u_control (
        .clk   (clk),
        .rst   (rst),
        .start (start),
        .MSB   (MSB),
        .Z     (Z),
        .LDA   (LDA),
        .CO    (CO),
        .AO    (AO),
        .INC   (INC),
        .LDR   (LDR),
        .DONE  (DONE)
    );

    datapath #(.N(N), .CNT_WIDTH(CNT_WIDTH)) u_datapath (
        .clk (clk),
        .a   (a),
        .b   (b),
        .LDA (LDA),
        .CO  (CO),
        .AO  (AO),
        .INC (INC),
        .LDR (LDR),
        .MSB (MSB),
        .Z   (Z),
        .Q   (Q),
        .Rem (Rem)
    );

endmodule

divisor/divisor_top_TB.v
module tb_divisor;

    parameter N         = 16;
    parameter CNT_WIDTH = 5;

    reg              clk;
    reg              rst;
    reg              start;
    reg  [N-1:0]     a, b;
    wire [N-1:0]     Q, Rem;
    wire             DONE;

    integer errors = 0;
    integer tests  = 0;

    divisor_top #(.N(N), .CNT_WIDTH(CNT_WIDTH)) uut (
        .clk   (clk),
        .rst   (rst),
        .start (start),
        .a     (a),
        .b     (b),
        .Q     (Q),
        .Rem   (Rem),
        .DONE  (DONE)
    );

    // Generador de reloj: 10 ns de periodo
    initial clk = 1'b0;
    always #5 clk = ~clk;

    task run_test(input [N-1:0] ta, input [N-1:0] tb);
        reg [N-1:0] expected_q, expected_r;
        begin
            tests      = tests + 1;
            expected_q = ta / tb;
            expected_r = ta % tb;

            a = ta;
            b = tb;
            start = 1'b0;
            @(posedge clk);

            start = 1'b1;
            @(posedge clk);
            start = 1'b0;

            // Espera a que la FSM llegue al estado END
            wait (DONE == 1'b1);
            @(posedge clk);

            if (Q !== expected_q || Rem !== expected_r) begin
                $display("a=%0d b=%0d -> Q=%0d Rem=%0d (esperado Q=%0d Rem=%0d)",
                          ta, tb, Q, Rem, expected_q, expected_r);
                errors = errors + 1;
            end else begin
                $display("a=%0d b=%0d -> Q=%0d Rem=%0d", ta, tb, Q, Rem);
            end

            // Deja pasar un ciclo en ENDST y vuelve a START
            @(posedge clk);
        end
    endtask

    initial begin
        $dumpfile("divisor_top_TB.vcd");
        $dumpvars(0, tb_divisor);

        rst   = 1'b1;
        start = 1'b0;
        a = 0; b = 0;
        repeat (2) @(posedge clk);
        rst = 1'b0;
        @(posedge clk);

        run_test(16'd20,    16'd4);
        run_test(16'd100,   16'd7);
        run_test(16'd65535, 16'd1);
        run_test(16'd65535, 16'd65535);
        run_test(16'd1,     16'd1);
        run_test(16'd0,     16'd5);
        run_test(16'd12345, 16'd100);

        $finish;
    end

endmodule

divisor/divisor_top_TB.vcd
$date
	Wed Jul 15 16:00:56 2026
$end
$version
	Icarus Verilog
$end
$timescale
	1ps
$end
$scope module tb_divisor $end
$var wire 16 ! Rem [15:0] $end
$var wire 16 " Q [15:0] $end
$var wire 1 # DONE $end
$var parameter 32 $ CNT_WIDTH $end
$var parameter 32 % N $end
$var reg 16 & a [15:0] $end
$var reg 16 ' b [15:0] $end
$var reg 1 ( clk $end
$var reg 1 ) rst $end
$var reg 1 * start $end
$var integer 32 + errors [31:0] $end
$var integer 32 , tests [31:0] $end
$scope module uut $end
$var wire 16 - a [15:0] $end
$var wire 16 . b [15:0] $end
$var wire 1 ( clk $end
$var wire 1 ) rst $end
$var wire 1 * start $end
$var wire 1 / Z $end
$var wire 16 0 Rem [15:0] $end
$var wire 16 1 Q [15:0] $end
$var wire 1 2 MSB $end
$var wire 1 3 LDR $end
$var wire 1 4 LDA $end
$var wire 1 5 INC $end
$var wire 1 # DONE $end
$var wire 1 6 CO $end
$var wire 1 7 AO $end
$var parameter 32 8 CNT_WIDTH $end
$var parameter 32 9 N $end
$scope module u_control $end
$var wire 1 ( clk $end
$var wire 1 ) rst $end
$var wire 1 * start $end
$var wire 1 / Z $end
$var wire 1 2 MSB $end
$var parameter 3 : ADDST $end
$var parameter 3 ; CHECK $end
$var parameter 3 < ENDST $end
$var parameter 3 = SHIFT $end
$var parameter 3 > START $end
$var reg 1 7 AO $end
$var reg 1 6 CO $end
$var reg 1 # DONE $end
$var reg 1 5 INC $end
$var reg 1 4 LDA $end
$var reg 1 3 LDR $end
$var reg 3 ? next_state [2:0] $end
$var reg 3 @ state [2:0] $end
$upscope $end
$scope module u_datapath $end
$var wire 1 7 AO $end
$var wire 1 6 CO $end
$var wire 1 5 INC $end
$var wire 1 4 LDA $end
$var wire 1 3 LDR $end
$var wire 16 A a [15:0] $end
$var wire 16 B b [15:0] $end
$var wire 1 ( clk $end
$var wire 16 C sub_result [15:0] $end
$var wire 5 D count [4:0] $end
$var wire 1 / Z $end
$var wire 16 E Rem [15:0] $end
$var wire 16 F Q [15:0] $end
$var wire 1 2 MSB $end
$var wire 16 G B_reg [15:0] $end
$var parameter 32 H CNT_WIDTH $end
$var parameter 32 I N $end
$scope module u_comparador $end
$var wire 5 J count [4:0] $end
$var wire 1 / Z $end
$var parameter 32 K N $end
$var parameter 32 L WIDTH $end
$upscope $end
$scope module u_contador_i $end
$var wire 1 ( clk $end
$var wire 1 5 inc $end
$var wire 1 4 rst $end
$var parameter 32 M WIDTH $end
$var reg 5 N count [4:0] $end
$upscope $end
$scope module u_reg_divisor $end
$var wire 1 4 LDA $end
$var wire 16 O b_in [15:0] $end
$var wire 1 ( clk $end
$var parameter 32 P N $end
$var reg 16 Q B [15:0] $end
$upscope $end
$scope module u_reg_ra $end
$var wire 1 7 AO $end
$var wire 1 6 CO $end
$var wire 1 4 LDA $end
$var wire 1 3 LDR $end
$var wire 16 R a_in [15:0] $end
$var wire 1 ( clk $end
$var wire 16 S sub_result [15:0] $end
$var parameter 32 T N $end
$var reg 16 U A [15:0] $end
$var reg 16 V R [15:0] $end
$upscope $end
$scope module u_restador $end
$var wire 16 W B [15:0] $end
$var wire 16 X R [15:0] $end
$var wire 16 Y result [15:0] $end
$var wire 17 Z diff [16:0] $end
$var wire 1 2 MSB $end
$var parameter 32 [ N $end
$upscope $end
$upscope $end
$upscope $end
$scope task run_test $end
$var reg 16 \ expected_q [15:0] $end
$var reg 16 ] expected_r [15:0] $end
$var reg 16 ^ ta [15:0] $end
$var reg 16 _ tb [15:0] $end
$upscope $end
$upscope $end
$enddefinitions $end
$comment Show the parameter values. $end
$dumpall
b10000 [
b10000 T
b10000 P
b101 M
b101 L
b10000 K
b10000 I
b101 H
b0 >
b1 =
b100 <
b10 ;
b11 :
b10000 9
b101 8
b10000 %
b101 $
$end
#0
$dumpvars
bx _
bx ^
bx ]
bx \
bx Z
bx Y
bx X
bx W
bx V
bx U
bx S
b0 R
bx Q
b0 O
bx N
bx J
bx G
bx F
bx E
bx D
bx C
b0 B
b0 A
b0 @
b0 ?
07
06
05
14
03
x2
bx 1
bx 0
x/
b0 .
b0 -
b0 ,
b0 +
0*
1)
0(
b0 '
b0 &
0#
bx "
bx !
$end
#5000
1(
#10000
0/
b0 C
b0 S
b0 Y
02
b0 D
b0 J
b0 N
b0 Z
b0 !
b0 0
b0 E
b0 V
b0 X
b0 "
b0 1
b0 F
b0 U
b0 G
b0 Q
b0 W
0(
#15000
0)
1(
#20000
0(
#25000
b100 '
b100 .
b100 B
b100 O
b10100 &
b10100 -
b10100 A
b10100 R
b0 ]
b101 \
b1 ,
b100 _
b10100 ^
1(
#30000
b1111111111111100 C
b1111111111111100 S
b1111111111111100 Y
12
b10100 "
b10100 1
b10100 F
b10100 U
b11111111111111100 Z
b100 G
b100 Q
b100 W
0(
#35000
b1 ?
1*
1(
#40000
0(
#45000
15
16
04
b1 @
b10 ?
0*
1(
#50000
b1 D
b1 J
b1 N
b101000 "
b101000 1
b101000 F
b101000 U
0(
#55000
05
06
b1 ?
b10 @
1(
#60000
0(
#65000
15
16
b10 ?
b1 @
1(
#70000
b10 D
b10 J
b10 N
b1010000 "
b1010000 1
b1010000 F
b1010000 U
0(
#75000
05
06
b1 ?
b10 @
1(
#80000
0(
#85000
15
16
b10 ?
b1 @
1(
#90000
b11 D
b11 J
b11 N
b10100000 "
b10100000 1
b10100000 F
b10100000 U
0(
#95000
05
06
b1 ?
b10 @
1(
#100000
0(
#105000
15
16
b10 ?
b1 @
1(
#110000
b100 D
b100 J
b100 N
b101000000 "
b101000000 1
b101000000 F
b101000000 U
0(
#115000
05
06
b1 ?
b10 @
1(
#120000
0(
#125000
15
16
b10 ?
b1 @
1(
#130000
b101 D
b101 J
b101 N
b1010000000 "
b1010000000 1
b1010000000 F
b1010000000 U
0(
#135000
05
06
b1 ?
b10 @
1(
#140000
0(
#145000
15
16
b10 ?
b1 @
1(
#150000
b110 D
b110 J
b110 N
b10100000000 "
b10100000000 1
b10100000000 F
b10100000000 U
0(
#155000
05
06
b1 ?
b10 @
1(
#160000
0(
#165000
15
16
b10 ?
b1 @
1(
#170000
b111 D
b111 J
b111 N
b101000000000 "
b101000000000 1
b101000000000 F
b101000000000 U
0(
#175000
05
06
b1 ?
b10 @
1(
#180000
0(
#185000
15
16
b10 ?
b1 @
1(
#190000
b1000 D
b1000 J
b1000 N
b1010000000000 "
b1010000000000 1
b1010000000000 F
b1010000000000 U
0(
#195000
05
06
b1 ?
b10 @
1(
#200000
0(
#205000
15
16
b10 ?
b1 @
1(
#210000
b1001 D
b1001 J
b1001 N
b10100000000000 "
b10100000000000 1
b10100000000000 F
b10100000000000 U
0(
#215000
05
06
b1 ?
b10 @
1(
#220000
0(
#225000
15
16
b10 ?
b1 @
1(
#230000
b1010 D
b1010 J
b1010 N
b101000000000000 "
b101000000000000 1
b101000000000000 F
b101000000000000 U
0(
#235000
05
06
b1 ?
b10 @
1(
#240000
0(
#245000
15
16
b10 ?
b1 @
1(
#250000
b1011 D
b1011 J
b1011 N
b1010000000000000 "
b1010000000000000 1
b1010000000000000 F
b1010000000000000 U
0(
#255000
05
06
b1 ?
b10 @
1(
#260000
0(
#265000
15
16
b10 ?
b1 @
1(
#270000
b1111111111111101 C
b1111111111111101 S
b1111111111111101 Y
b1100 D
b1100 J
b1100 N
b11111111111111101 Z
b1 !
b1 0
b1 E
b1 V
b1 X
b100000000000000 "
b100000000000000 1
b100000000000000 F
b100000000000000 U
0(
#275000
05
06
b1 ?
b10 @
1(
#280000
0(
#285000
15
16
b10 ?
b1 @
1(
#290000
b1111111111111110 C
b1111111111111110 S
b1111111111111110 Y
b1101 D
b1101 J
b1101 N
b11111111111111110 Z
b10 !
b10 0
b10 E
b10 V
b10 X
b1000000000000000 "
b1000000000000000 1
b1000000000000000 F
b1000000000000000 U
0(
#295000
05
06
b1 ?
b10 @
1(
#300000
0(
#305000
15
16
b10 ?
b1 @
1(
#310000
b1 C
b1 S
b1 Y
02
b1110 D
b1110 J
b1110 N
b1 Z
b101 !
b101 0
b101 E
b101 V
b101 X
b0 "
b0 1
b0 F
b0 U
0(
#315000
05
06
b11 ?
b10 @
1(
#320000
0(
#325000
13
17
b1 ?
b11 @
1(
#330000
b1111111111111101 C
b1111111111111101 S
b1111111111111101 Y
12
b1 "
b1 1
b1 F
b1 U
b11111111111111101 Z
b1 !
b1 0
b1 E
b1 V
b1 X
0(
#335000
15
16
03
07
b10 ?
b1 @
1(
#340000
b1111111111111110 C
b1111111111111110 S
b1111111111111110 Y
b11111111111111110 Z
b10 !
b10 0
b10 E
b10 V
b10 X
b10 "
b10 1
b10 F
b10 U
b1111 D
b1111 J
b1111 N
0(
#345000
05
06
b1 ?
b10 @
1(
#350000
0(
#355000
15
16
b10 ?
b1 @
1(
#360000
b0 C
b0 S
b0 Y
02
1/
b0 Z
b100 !
b100 0
b100 E
b100 V
b100 X
b100 "
b100 1
b100 F
b100 U
b10000 D
b10000 J
b10000 N
0(
#365000
05
06
b11 ?
b10 @
1(
#370000
0(
#375000
13
17
b100 ?
b11 @
1(
#380000
b1111111111111100 C
b1111111111111100 S
b1111111111111100 Y
12
b101 "
b101 1
b101 F
b101 U
b11111111111111100 Z
b0 !
b0 0
b0 E
b0 V
b0 X
0(
#385000
1#
03
07
b0 ?
b100 @
1(
#390000
0(
#395000
14
0#
b0 @
1(
#400000
0/
b10100 "
b10100 1
b10100 F
b10100 U
b0 D
b0 J
b0 N
0(
#405000
b111 '
b111 .
b111 B
b111 O
b1100100 &
b1100100 -
b1100100 A
b1100100 R
b10 ]
b1110 \
b10 ,
b111 _
b1100100 ^
1(
#410000
b1111111111111001 C
b1111111111111001 S
b1111111111111001 Y
b1100100 "
b1100100 1
b1100100 F
b1100100 U
b11111111111111001 Z
b111 G
b111 Q
b111 W
0(
#415000
b1 ?
1*
1(
#420000
0(
#425000
15
16
04
b1 @
b10 ?
0*
1(
#430000
b1 D
b1 J
b1 N
b11001000 "
b11001000 1
b11001000 F
b11001000 U
0(
#435000
05
06
b1 ?
b10 @
1(
#440000
0(
#445000
15
16
b10 ?
b1 @
1(
#450000
b10 D
b10 J
b10 N
b110010000 "
b110010000 1
b110010000 F
b110010000 U
0(
#455000
05
06
b1 ?
b10 @
1(
#460000
0(
#465000
15
16
b10 ?
b1 @
1(
#470000
b11 D
b11 J
b11 N
b1100100000 "
b1100100000 1
b1100100000 F
b1100100000 U
0(
#475000
05
06
b1 ?
b10 @
1(
#480000
0(
#485000
15
16
b10 ?
b1 @
1(
#490000
b100 D
b100 J
b100 N
b11001000000 "
b11001000000 1
b11001000000 F
b11001000000 U
0(
#495000
05
06
b1 ?
b10 @
1(
#500000
0(
#505000
15
16
b10 ?
b1 @
1(
#510000
b101 D
b101 J
b101 N
b110010000000 "
b110010000000 1
b110010000000 F
b110010000000 U
0(
#515000
05
06
b1 ?
b10 @
1(
#520000
0(
#525000
15
16
b10 ?
b1 @
1(
#530000
b110 D
b110 J
b110 N
b1100100000000 "
b1100100000000 1
b1100100000000 F
b1100100000000 U
0(
#535000
05
06
b1 ?
b10 @
1(
#540000
0(
#545000
15
16
b10 ?
b1 @
1(
#550000
b111 D
b111 J
b111 N
b11001000000000 "
b11001000000000 1
b11001000000000 F
b11001000000000 U
0(
#555000
05
06
b1 ?
b10 @
1(
#560000
0(
#565000
15
16
b10 ?
b1 @
1(
#570000
b1000 D
b1000 J
b1000 N
b110010000000000 "
b110010000000000 1
b110010000000000 F
b110010000000000 U
0(
#575000
05
06
b1 ?
b10 @
1(
#580000
0(
#585000
15
16
b10 ?
b1 @
1(
#590000
b1001 D
b1001 J
b1001 N
b1100100000000000 "
b1100100000000000 1
b1100100000000000 F
b1100100000000000 U
0(
#595000
05
06
b1 ?
b10 @
1(
#600000
0(
#605000
15
16
b10 ?
b1 @
1(
#610000
b1111111111111010 C
b1111111111111010 S
b1111111111111010 Y
b1010 D
b1010 J
b1010 N
b11111111111111010 Z
b1 !
b1 0
b1 E
b1 V
b1 X
b1001000000000000 "
b1001000000000000 1
b1001000000000000 F
b1001000000000000 U
0(
#615000
05
06
b1 ?
b10 @
1(
#620000
0(
#625000
15
16
b10 ?
b1 @
1(
#630000
b1111111111111100 C
b1111111111111100 S
b1111111111111100 Y
b1011 D
b1011 J
b1011 N
b11111111111111100 Z
b11 !
b11 0
b11 E
b11 V
b11 X
b10000000000000 "
b10000000000000 1
b10000000000000 F
b10000000000000 U
0(
#635000
05
06
b1 ?
b10 @
1(
#640000
0(
#645000
15
16
b10 ?
b1 @
1(
#650000
b1111111111111111 C
b1111111111111111 S
b1111111111111111 Y
b1100 D
b1100 J
b1100 N
b11111111111111111 Z
b110 !
b110 0
b110 E
b110 V
b110 X
b100000000000000 "
b100000000000000 1
b100000000000000 F
b100000000000000 U
0(
#655000
05
06
b1 ?
b10 @
1(
#660000
0(
#665000
15
16
b10 ?
b1 @
1(
#670000
b101 C
b101 S
b101 Y
02
b1101 D
b1101 J
b1101 N
b101 Z
b1100 !
b1100 0
b1100 E
b1100 V
b1100 X
b1000000000000000 "
b1000000000000000 1
b1000000000000000 F
b1000000000000000 U
0(
#675000
05
06
b11 ?
b10 @
1(
#680000
0(
#685000
13
17
b1 ?
b11 @
1(
#690000
b1111111111111110 C
b1111111111111110 S
b1111111111111110 Y
12
b1000000000000001 "
b1000000000000001 1
b1000000000000001 F
b1000000000000001 U
b11111111111111110 Z
b101 !
b101 0
b101 E
b101 V
b101 X
0(
#695000
15
16
03
07
b10 ?
b1 @
1(
#700000
b100 C
b100 S
b100 Y
02
b100 Z
b1011 !
b1011 0
b1011 E
b1011 V
b1011 X
b10 "
b10 1
b10 F
b10 U
b1110 D
b1110 J
b1110 N
0(
#705000
05
06
b11 ?
b10 @
1(
#710000
0(
#715000
13
17
b1 ?
b11 @
1(
#720000
b1111111111111101 C
b1111111111111101 S
b1111111111111101 Y
12
b11 "
b11 1
b11 F
b11 U
b11111111111111101 Z
b100 !
b100 0
b100 E
b100 V
b100 X
0(
#725000
15
16
03
07
b10 ?
b1 @
1(
#730000
b1 C
b1 S
b1 Y
02
b1111 D
b1111 J
b1111 N
b1 Z
b1000 !
b1000 0
b1000 E
b1000 V
b1000 X
b110 "
b110 1
b110 F
b110 U
0(
#735000
05
06
b11 ?
b10 @
1(
#740000
0(
#745000
13
17
b1 ?
b11 @
1(
#750000
b1111111111111010 C
b1111111111111010 S
b1111111111111010 Y
12
b111 "
b111 1
b111 F
b111 U
b11111111111111010 Z
b1 !
b1 0
b1 E
b1 V
b1 X
0(
#755000
15
16
03
07
b10 ?
b1 @
1(
#760000
b1111111111111011 C
b1111111111111011 S
b1111111111111011 Y
1/
b11111111111111011 Z
b10 !
b10 0
b10 E
b10 V
b10 X
b1110 "
b1110 1
b1110 F
b1110 U
b10000 D
b10000 J
b10000 N
0(
#765000
05
06
b100 ?
b10 @
1(
#770000
0(
#775000
1#
b0 ?
b100 @
1(
#780000
0(
#785000
14
0#
b0 @
1(
#790000
0/
b1111111111111001 C
b1111111111111001 S
b1111111111111001 Y
b0 D
b0 J
b0 N
b11111111111111001 Z
b0 !
b0 0
b0 E
b0 V
b0 X
b1100100 "
b1100100 1
b1100100 F
b1100100 U
0(
#795000
b1 '
b1 .
b1 B
b1 O
b1111111111111111 &
b1111111111111111 -
b1111111111111111 A
b1111111111111111 R
b0 ]
b1111111111111111 \
b11 ,
b1 _
b1111111111111111 ^
1(
#800000
b1111111111111111 C
b1111111111111111 S
b1111111111111111 Y
b11111111111111111 Z
b1 G
b1 Q
b1 W
b1111111111111111 "
b1111111111111111 1
b1111111111111111 F
b1111111111111111 U
0(
#805000
b1 ?
1*
1(
#810000
0(
#815000
15
16
04
b1 @
b10 ?
0*
1(
#820000
b0 C
b0 S
b0 Y
02
b0 Z
b1 !
b1 0
b1 E
b1 V
b1 X
b1111111111111110 "
b1111111111111110 1
b1111111111111110 F
b1111111111111110 U
b1 D
b1 J
b1 N
0(
#825000
05
06
b11 ?
b10 @
1(
#830000
0(
#835000
13
17
b1 ?
b11 @
1(
#840000
b1111111111111111 C
b1111111111111111 S
b1111111111111111 Y
12
b1111111111111111 "
b1111111111111111 1
b1111111111111111 F
b1111111111111111 U
b11111111111111111 Z
b0 !
b0 0
b0 E
b0 V
b0 X
0(
#845000
15
16
03
07
b10 ?
b1 @
1(
#850000
b0 C
b0 S
b0 Y
02
b10 D
b10 J
b10 N
b0 Z
b1 !
b1 0
b1 E
b1 V
b1 X
b1111111111111110 "
b1111111111111110 1
b1111111111111110 F
b1111111111111110 U
0(
#855000
05
06
b11 ?
b10 @
1(
#860000
0(
#865000
13
17
b1 ?
b11 @
1(
#870000
b1111111111111111 C
b1111111111111111 S
b1111111111111111 Y
12
b1111111111111111 "
b1111111111111111 1
b1111111111111111 F
b1111111111111111 U
b11111111111111111 Z
b0 !
b0 0
b0 E
b0 V
b0 X
0(
#875000
15
16
03
07
b10 ?
b1 @
1(
#880000
b0 C
b0 S
b0 Y
02
b0 Z
b1 !
b1 0
b1 E
b1 V
b1 X
b1111111111111110 "
b1111111111111110 1
b1111111111111110 F
b1111111111111110 U
b11 D
b11 J
b11 N
0(
#885000
05
06
b11 ?
b10 @
1(
#890000
0(
#895000
13
17
b1 ?
b11 @
1(
#900000
b1111111111111111 C
b1111111111111111 S
b1111111111111111 Y
12
b1111111111111111 "
b1111111111111111 1
b1111111111111111 F
b1111111111111111 U
b11111111111111111 Z
b0 !
b0 0
b0 E
b0 V
b0 X
0(
#905000
15
16
03
07
b10 ?
b1 @
1(
#910000
b0 C
b0 S
b0 Y
02
b100 D
b100 J
b100 N
b0 Z
b1 !
b1 0
b1 E
b1 V
b1 X
b1111111111111110 "
b1111111111111110 1
b1111111111111110 F
b1111111111111110 U
0(
#915000
05
06
b11 ?
b10 @
1(
#920000
0(
#925000
13
17
b1 ?
b11 @
1(
#930000
b1111111111111111 C
b1111111111111111 S
b1111111111111111 Y
12
b1111111111111111 "
b1111111111111111 1
b1111111111111111 F
b1111111111111111 U
b11111111111111111 Z
b0 !
b0 0
b0 E
b0 V
b0 X
0(
#935000
15
16
03
07
b10 ?
b1 @
1(
#940000
b0 C
b0 S
b0 Y
02
b0 Z
b1 !
b1 0
b1 E
b1 V
b1 X
b1111111111111110 "
b1111111111111110 1
b1111111111111110 F
b1111111111111110 U
b101 D
b101 J
b101 N
0(
#945000
05
06
b11 ?
b10 @
1(
#950000
0(
#955000
13
17
b1 ?
b11 @
1(
#960000
b1111111111111111 C
b1111111111111111 S
b1111111111111111 Y
12
b1111111111111111 "
b1111111111111111 1
b1111111111111111 F
b1111111111111111 U
b11111111111111111 Z
b0 !
b0 0
b0 E
b0 V
b0 X
0(
#965000
15
16
03
07
b10 ?
b1 @
1(
#970000
b0 C
b0 S
b0 Y
02
b110 D
b110 J
b110 N
b0 Z
b1 !
b1 0
b1 E
b1 V
b1 X
b1111111111111110 "
b1111111111111110 1
b1111111111111110 F
b1111111111111110 U
0(
#975000
05
06
b11 ?
b10 @
1(
#980000
0(
#985000
13
17
b1 ?
b11 @
1(
#990000
b1111111111111111 C
b1111111111111111 S
b1111111111111111 Y
12
b1111111111111111 "
b1111111111111111 1
b1111111111111111 F
b1111111111111111 U
b11111111111111111 Z
b0 !
b0 0
b0 E
b0 V
b0 X
0(
#995000
15
16
03
07
b10 ?
b1 @
1(
#1000000
b0 C
b0 S
b0 Y
02
b0 Z
b1 !
b1 0
b1 E
b1 V
b1 X
b1111111111111110 "
b1111111111111110 1
b1111111111111110 F
b1111111111111110 U
b111 D
b111 J
b111 N
0(
#1005000
05
06
b11 ?
b10 @
1(
#1010000
0(
#1015000
13
17
b1 ?
b11 @
1(
#1020000
b1111111111111111 C
b1111111111111111 S
b1111111111111111 Y
12
b1111111111111111 "
b1111111111111111 1
b1111111111111111 F
b1111111111111111 U
b11111111111111111 Z
b0 !
b0 0
b0 E
b0 V
b0 X
0(
#1025000
15
16
03
07
b10 ?
b1 @
1(
#1030000
b0 C
b0 S
b0 Y
02
b1000 D
b1000 J
b1000 N
b0 Z
b1 !
b1 0
b1 E
b1 V
b1 X
b1111111111111110 "
b1111111111111110 1
b1111111111111110 F
b1111111111111110 U
0(
#1035000
05
06
b11 ?
b10 @
1(
#1040000
0(
#1045000
13
17
b1 ?
b11 @
1(
#1050000
b1111111111111111 C
b1111111111111111 S
b1111111111111111 Y
12
b1111111111111111 "
b1111111111111111 1
b1111111111111111 F
b1111111111111111 U
b11111111111111111 Z
b0 !
b0 0
b0 E
b0 V
b0 X
0(
#1055000
15
16
03
07
b10 ?
b1 @
1(
#1060000
b0 C
b0 S
b0 Y
02
b0 Z
b1 !
b1 0
b1 E
b1 V
b1 X
b1111111111111110 "
b1111111111111110 1
b1111111111111110 F
b1111111111111110 U
b1001 D
b1001 J
b1001 N
0(
#1065000
05
06
b11 ?
b10 @
1(
#1070000
0(
#1075000
13
17
b1 ?
b11 @
1(
#1080000
b1111111111111111 C
b1111111111111111 S
b1111111111111111 Y
12
b1111111111111111 "
b1111111111111111 1
b1111111111111111 F
b1111111111111111 U
b11111111111111111 Z
b0 !
b0 0
b0 E
b0 V
b0 X
0(
#1085000
15
16
03
07
b10 ?
b1 @
1(
#1090000
b0 C
b0 S
b0 Y
02
b1010 D
b1010 J
b1010 N
b0 Z
b1 !
b1 0
b1 E
b1 V
b1 X
b1111111111111110 "
b1111111111111110 1
b1111111111111110 F
b1111111111111110 U
0(
#1095000
05
06
b11 ?
b10 @
1(
#1100000
0(
#1105000
13
17
b1 ?
b11 @
1(
#1110000
b1111111111111111 C
b1111111111111111 S
b1111111111111111 Y
12
b1111111111111111 "
b1111111111111111 1
b1111111111111111 F
b1111111111111111 U
b11111111111111111 Z
b0 !
b0 0
b0 E
b0 V
b0 X
0(
#1115000
15
16
03
07
b10 ?
b1 @
1(
