paridad/Ultimo/contador_b.v
module contador_b #(
    parameter WIDTH = 4
)(
    input  wire              clk,
    input  wire              rst,   
    input  wire              inc,   
    output reg  [WIDTH-1:0]  b,
    output wire              ok     
);

    always @(negedge clk) begin
        if (rst)
            b <= {WIDTH{1'b0}};
        else if (inc)
            b <= b + 1'b1;
    end

    assign ok = ~b[0];

endmodule

paridad/Ultimo/comparador.v
module comparador #(
    parameter N     = 10,
    parameter WIDTH = 4
)(
    input  wire [WIDTH-1:0] count,
    output wire             Z
);

    assign Z = (count == N[WIDTH-1:0]) ? 1'b1 : 1'b0;

endmodule

paridad/Ultimo/contador_i.v
module contador_i #(
    parameter WIDTH = 4
)(
    input  wire              clk,
    input  wire              rst,  
    input  wire              inc,  
    output reg [WIDTH-1:0]   count
);

    always @(negedge clk) begin
        if (rst)
            count <= {WIDTH{1'b0}};
        else if (inc)
            count <= count + 1'b1;
    end

endmodule

paridad/Ultimo/reg_a.v
module reg_a #(
    parameter N         = 10,
    parameter IDX_WIDTH = 4      
)(
    input  wire                  clk,
    input  wire                  LD,
    input  wire [N-1:0]          a_in,
    input  wire [IDX_WIDTH-1:0]  idx,
    output wire                  a_i
);

    reg [N-1:0] a_reg;

    
    always @(negedge clk) begin
        if (LD)
            a_reg <= a_in;
    end

    assign a_i = (idx < N) ? a_reg[idx] : 1'b0;

endmodule

paridad/Ultimo/datapath.v
module datapath #(
    parameter N         = 10,
    parameter IDX_WIDTH = 4
)(
    input  wire                     clk,
    input  wire [N-1:0]             a,
    input  wire                     LD,
    input  wire                     inci,
    input  wire                     incb,
    output wire                     a_i,      
    output wire                     Z,        
    output wire                     ok,      
    output wire [IDX_WIDTH-1:0]     b_debug   
);

    wire [IDX_WIDTH-1:0] count_i;

    reg_a #(.N(N), .IDX_WIDTH(IDX_WIDTH)) u_reg_a (
        .clk  (clk),
        .LD   (LD),
        .a_in (a),
        .idx  (count_i),
        .a_i  (a_i)
    );

    contador_i #(.WIDTH(IDX_WIDTH)) u_contador_i (
        .clk   (clk),
        .rst   (LD),
        .inc   (inci),
        .count (count_i)
    );

    comparador #(.N(N), .WIDTH(IDX_WIDTH)) u_comparador (
        .count (count_i),
        .Z     (Z)
    );

    contador_b #(.WIDTH(IDX_WIDTH)) u_contador_b (
        .clk (clk),
        .rst (LD),
        .inc (incb),
        .b   (b_debug),
        .ok  (ok)
    );

endmodule

paridad/Ultimo/control.v
module control (
    input  wire clk,
    input  wire rst,    
    input  wire start,
    input  wire a_i,
    input  wire Z,
    output reg  LD,
    output reg  inci,
    output reg  incb,
    output reg  DONE
);

    localparam [2:0]
        START  = 3'b000,
        CHECK  = 3'b001,
        ADDB   = 3'b010,
        ADDI   = 3'b011,
        CHECK2 = 3'b100,
        ENDST  = 3'b101;

    reg [2:0] state, next_state;

    // Registro de estado: flanco de SUBIDA
    always @(posedge clk or posedge rst) begin
        if (rst)
            state <= START;
        else
            state <= next_state;
    end

    // Logica de siguiente estado
    always @(*) begin
        case (state)
            START:   next_state = start ? CHECK  : START;
            CHECK:   next_state = a_i   ? ADDB   : ADDI;
            ADDB:    next_state = ADDI;
            ADDI:    next_state = CHECK2;
            CHECK2:  next_state = Z ? ENDST : CHECK;
            ENDST:   next_state = start ? START : ENDST;
            default: next_state = START;
        endcase
    end

    // Salidas (Moore, dependen solo del estado)
    always @(*) begin
        LD   = 1'b0;
        inci = 1'b0;
        incb = 1'b0;
        DONE = 1'b0;
        case (state)
            START:   LD   = 1'b1;
            CHECK:   ; // sin senales activas
            ADDB:    incb = 1'b1;
            ADDI:    inci = 1'b1;
            CHECK2:  ; // sin senales activas
            ENDST:   DONE = 1'b1;
            default: ;
        endcase
    end

endmodule

paridad/Ultimo/paridad_top.v
module paridad_top #(
    parameter N         = 10,
    parameter IDX_WIDTH = 4
)(
    input  wire             clk,
    input  wire             rst,
    input  wire             start,
    input  wire [N-1:0]     a,
    output wire             ok,
    output wire             DONE
);

    wire LD, inci, incb;
    wire a_i, Z;
    wire [IDX_WIDTH-1:0] b_debug;

    control u_control (
        .clk   (clk),
        .rst   (rst),
        .start (start),
        .a_i   (a_i),
        .Z     (Z),
        .LD    (LD),
        .inci  (inci),
        .incb  (incb),
        .DONE  (DONE)
    );

    datapath #(.N(N), .IDX_WIDTH(IDX_WIDTH)) u_datapath (
        .clk     (clk),
        .a       (a),
        .LD      (LD),
        .inci    (inci),
        .incb    (incb),
        .a_i     (a_i),
        .Z       (Z),
        .ok      (ok),
        .b_debug (b_debug)
    );

endmodule

paridad/Ultimo/paridad_top_TB.v
// ============================================================
// paridad_top_TB.v
// Testbench autoverificable del contador de unos (paridad)
// ============================================================
`timescale 1ns/1ps

module tb_paridad;

    parameter N         = 10;
    parameter IDX_WIDTH = 4;

    reg              clk;
    reg              rst;
    reg              start;
    reg  [N-1:0]     a;
    wire             ok;
    wire             DONE;

    integer errors = 0;
    integer tests  = 0;

    paridad_top #(.N(N), .IDX_WIDTH(IDX_WIDTH)) uut (
        .clk   (clk),
        .rst   (rst),
        .start (start),
        .a     (a),
        .ok    (ok),
        .DONE  (DONE)
    );

    // Generador de reloj: 10 ns de periodo
    initial clk = 1'b0;
    always #5 clk = ~clk;

    task run_test(input [N-1:0] ta);
        reg expected;
        begin
            tests    = tests + 1;
            expected = ~(^ta);   // NOT(XOR reduction) = 1 cuando la cantidad de unos es PAR

            a = ta;
            start = 1'b0;
            @(posedge clk);

            // Pulso de start de 2 ciclos: el primero saca a la FSM de
            // ENDST (si venia atascada ahi esperando) hacia START, y
            // el segundo la lleva de START a CHECK. Si la FSM ya
            // estaba en START (primera prueba), el ciclo extra no
            // afecta nada porque CHECK no consulta la senal start.
            start = 1'b1;
            @(posedge clk);
            @(posedge clk);
            start = 1'b0;

            // Espera a que la FSM llegue al estado END
            wait (DONE == 1'b1);
            @(posedge clk);

            if (ok !== expected) begin
                $display("FALLO: a=%b -> ok=%b (esperado %b)", ta, ok, expected);
                errors = errors + 1;
            end else begin
                $display("OK   : a=%b -> ok=%b", ta, ok);
            end

            // Ciclo extra de margen; la FSM se queda esperando en
            // ENDST (ya no regresa sola a START), y el siguiente
            // run_test se encarga de sacarla de ahi con su pulso
            // de start de 2 ciclos.
            @(posedge clk);
        end
    endtask

    initial begin
        $dumpfile("paridad_top_TB.vcd");
        $dumpvars(0, tb_paridad);

        rst   = 1'b1;
        start = 1'b0;
        a = 0;
        repeat (2) @(posedge clk);
        rst = 1'b0;
        @(posedge clk);

        run_test(10'b0000000000); // 0 unos  -> par   -> ok=1
        run_test(10'b0000000001); // 1 uno   -> impar -> ok=0
        run_test(10'b1111111111); // 10 unos -> par   -> ok=1
        run_test(10'b1010101010); // 5 unos  -> impar -> ok=0
        run_test(10'b1100110011); // 6 unos  -> par   -> ok=1
        run_test(10'b1000000000); // 1 uno   -> impar -> ok=0
        run_test(10'b0101010101); // 5 unos  -> impar -> ok=0

        $display("--------------------------------------------------");
        if (errors == 0)
            $display("TODAS LAS PRUEBAS PASARON (%0d/%0d)", tests, tests);
        else
            $display("%0d DE %0d PRUEBAS FALLARON", errors, tests);

        $finish;
    end

endmodule

paridad/Ultimo/paridad_top_TB.vcd
$date
	Thu Jul 16 14:09:59 2026
$end
$version
	Icarus Verilog
$end
$timescale
	1ps
$end
$scope module tb_paridad $end
$var wire 1 ! ok $end
$var wire 1 " DONE $end
$var parameter 32 # IDX_WIDTH $end
$var parameter 32 $ N $end
$var reg 10 % a [9:0] $end
$var reg 1 & clk $end
$var reg 1 ' rst $end
$var reg 1 ( start $end
$var integer 32 ) errors [31:0] $end
$var integer 32 * tests [31:0] $end
$scope module uut $end
$var wire 10 + a [9:0] $end
$var wire 1 & clk $end
$var wire 1 ' rst $end
$var wire 1 ( start $end
$var wire 1 ! ok $end
$var wire 1 , inci $end
$var wire 1 - incb $end
$var wire 4 . b_debug [3:0] $end
$var wire 1 / a_i $end
$var wire 1 0 Z $end
$var wire 1 1 LD $end
$var wire 1 " DONE $end
$var parameter 32 2 IDX_WIDTH $end
$var parameter 32 3 N $end
$scope module u_control $end
$var wire 1 & clk $end
$var wire 1 ' rst $end
$var wire 1 ( start $end
$var wire 1 / a_i $end
$var wire 1 0 Z $end
$var parameter 3 4 ADDB $end
$var parameter 3 5 ADDI $end
$var parameter 3 6 CHECK $end
$var parameter 3 7 CHECK2 $end
$var parameter 3 8 ENDST $end
$var parameter 3 9 START $end
$var reg 1 " DONE $end
$var reg 1 1 LD $end
$var reg 1 - incb $end
$var reg 1 , inci $end
$var reg 3 : next_state [2:0] $end
$var reg 3 ; state [2:0] $end
$upscope $end
$scope module u_datapath $end
$var wire 1 1 LD $end
$var wire 10 < a [9:0] $end
$var wire 1 & clk $end
$var wire 1 - incb $end
$var wire 1 , inci $end
$var wire 1 ! ok $end
$var wire 4 = count_i [3:0] $end
$var wire 4 > b_debug [3:0] $end
$var wire 1 / a_i $end
$var wire 1 0 Z $end
$var parameter 32 ? IDX_WIDTH $end
$var parameter 32 @ N $end
$scope module u_comparador $end
$var wire 4 A count [3:0] $end
$var wire 1 0 Z $end
$var parameter 32 B N $end
$var parameter 32 C WIDTH $end
$upscope $end
$scope module u_contador_b $end
$var wire 1 & clk $end
$var wire 1 - inc $end
$var wire 1 ! ok $end
$var wire 1 1 rst $end
$var parameter 32 D WIDTH $end
$var reg 4 E b [3:0] $end
$upscope $end
$scope module u_contador_i $end
$var wire 1 & clk $end
$var wire 1 , inc $end
$var wire 1 1 rst $end
$var parameter 32 F WIDTH $end
$var reg 4 G count [3:0] $end
$upscope $end
$scope module u_reg_a $end
$var wire 1 1 LD $end
$var wire 10 H a_in [9:0] $end
$var wire 1 & clk $end
$var wire 4 I idx [3:0] $end
$var wire 1 / a_i $end
$var parameter 32 J IDX_WIDTH $end
$var parameter 32 K N $end
$var reg 10 L a_reg [9:0] $end
$upscope $end
$upscope $end
$upscope $end
$scope task run_test $end
$var reg 1 M expected $end
$var reg 10 N ta [9:0] $end
$upscope $end
$upscope $end
$enddefinitions $end
$comment Show the parameter values. $end
$dumpall
b1010 K
b100 J
b100 F
b100 D
b100 C
b1010 B
b1010 @
b100 ?
b0 9
b101 8
b100 7
b1 6
b11 5
b10 4
b1010 3
b100 2
b1010 $
b100 #
$end
#0
$dumpvars
bx N
xM
bx L
bx I
b0 H
bx G
bx E
bx A
bx >
bx =
b0 <
b0 ;
b0 :
11
x0
x/
bx .
0-
0,
b0 +
b0 *
b0 )
0(
1'
0&
b0 %
0"
x!
$end
#5000
1&
#10000
1!
0/
00
b0 .
b0 >
b0 E
b0 =
b0 A
b0 G
b0 I
b0 L
0&
#15000
0'
1&
#20000
0&
#25000
1M
b1 *
b0 N
1&
#30000
0&
#35000
b1 :
1(
1&
#40000
0&
#45000
01
b11 :
b1 ;
1&
#50000
0&
#55000
1,
b100 :
b11 ;
0(
1&
#60000
b1 =
b1 A
b1 G
b1 I
0&
#65000
0,
b1 :
b100 ;
1&
#70000
0&
#75000
b11 :
b1 ;
1&
#80000
0&
#85000
1,
b100 :
b11 ;
1&
#90000
b10 =
b10 A
b10 G
b10 I
0&
#95000
0,
b1 :
b100 ;
1&
#100000
0&
#105000
b11 :
b1 ;
1&
#110000
0&
#115000
1,
b100 :
b11 ;
1&
#120000
b11 =
b11 A
b11 G
b11 I
0&
#125000
0,
b1 :
b100 ;
1&
#130000
0&
#135000
b11 :
b1 ;
1&
#140000
0&
#145000
1,
b100 :
b11 ;
1&
#150000
b100 =
b100 A
b100 G
b100 I
0&
#155000
0,
b1 :
b100 ;
1&
#160000
0&
#165000
b11 :
b1 ;
1&
#170000
0&
#175000
1,
b100 :
b11 ;
1&
#180000
b101 =
b101 A
b101 G
b101 I
0&
#185000
0,
b1 :
b100 ;
1&
#190000
0&
#195000
b11 :
b1 ;
1&
#200000
0&
#205000
1,
b100 :
b11 ;
1&
#210000
b110 =
b110 A
b110 G
b110 I
0&
#215000
0,
b1 :
b100 ;
1&
#220000
0&
#225000
b11 :
b1 ;
1&
#230000
0&
#235000
1,
b100 :
b11 ;
1&
#240000
b111 =
b111 A
b111 G
b111 I
0&
#245000
0,
b1 :
b100 ;
1&
#250000
0&
#255000
b11 :
b1 ;
1&
#260000
0&
#265000
1,
b100 :
b11 ;
1&
#270000
b1000 =
b1000 A
b1000 G
b1000 I
0&
#275000
0,
b1 :
b100 ;
1&
#280000
0&
#285000
b11 :
b1 ;
1&
#290000
0&
#295000
1,
b100 :
b11 ;
1&
#300000
b1001 =
b1001 A
b1001 G
b1001 I
0&
#305000
0,
b1 :
b100 ;
1&
#310000
0&
#315000
b11 :
b1 ;
1&
#320000
0&
#325000
1,
b100 :
b11 ;
1&
#330000
10
b1010 =
b1010 A
b1010 G
b1010 I
0&
#335000
0,
b101 :
b100 ;
1&
#340000
0&
#345000
1"
b101 ;
1&
#350000
0&
#355000
1&
#360000
0&
#365000
b1 %
b1 +
b1 <
b1 H
0M
b10 *
b1 N
1&
#370000
0&
#375000
b0 :
1(
1&
#380000
0&
#385000
11
0"
b1 :
b0 ;
1&
#390000
1/
00
b0 =
b0 A
b0 G
b0 I
b1 L
0&
#395000
01
b1 ;
b10 :
0(
1&
#400000
0&
#405000
1-
b11 :
b10 ;
1&
#410000
0!
b1 .
b1 >
b1 E
0&
#415000
1,
0-
b100 :
b11 ;
1&
#420000
0/
b1 =
b1 A
b1 G
b1 I
0&
#425000
0,
b1 :
b100 ;
1&
#430000
0&
#435000
b11 :
b1 ;
1&
#440000
0&
#445000
1,
b100 :
b11 ;
1&
#450000
b10 =
b10 A
b10 G
b10 I
0&
#455000
0,
b1 :
b100 ;
1&
#460000
0&
#465000
b11 :
b1 ;
1&
#470000
0&
#475000
1,
b100 :
b11 ;
1&
#480000
b11 =
b11 A
b11 G
b11 I
0&
#485000
0,
b1 :
b100 ;
1&
#490000
0&
#495000
b11 :
b1 ;
1&
#500000
0&
#505000
1,
b100 :
b11 ;
1&
#510000
b100 =
b100 A
b100 G
b100 I
0&
#515000
0,
b1 :
b100 ;
1&
#520000
0&
#525000
b11 :
b1 ;
1&
#530000
0&
#535000
1,
b100 :
b11 ;
1&
#540000
b101 =
b101 A
b101 G
b101 I
0&
#545000
0,
b1 :
b100 ;
1&
#550000
0&
#555000
b11 :
b1 ;
1&
#560000
0&
#565000
1,
b100 :
b11 ;
1&
#570000
b110 =
b110 A
b110 G
b110 I
0&
#575000
0,
b1 :
b100 ;
1&
#580000
0&
#585000
b11 :
b1 ;
1&
#590000
0&
#595000
1,
b100 :
b11 ;
1&
#600000
b111 =
b111 A
b111 G
b111 I
0&
#605000
0,
b1 :
b100 ;
1&
#610000
0&
#615000
b11 :
b1 ;
1&
#620000
0&
#625000
1,
b100 :
b11 ;
1&
#630000
b1000 =
b1000 A
b1000 G
b1000 I
0&
#635000
0,
b1 :
b100 ;
1&
#640000
0&
#645000
b11 :
b1 ;
1&
#650000
0&
#655000
1,
b100 :
b11 ;
1&
#660000
b1001 =
b1001 A
b1001 G
b1001 I
0&
#665000
0,
b1 :
b100 ;
1&
#670000
0&
#675000
b11 :
b1 ;
1&
#680000
0&
#685000
1,
b100 :
b11 ;
1&
#690000
10
b1010 =
b1010 A
b1010 G
b1010 I
0&
#695000
0,
b101 :
b100 ;
1&
#700000
0&
#705000
1"
b101 ;
1&
#710000
0&
#715000
1&
#720000
0&
#725000
b1111111111 %
b1111111111 +
b1111111111 <
b1111111111 H
1M
b11 *
b1111111111 N
1&
#730000
0&
#735000
b0 :
1(
1&
#740000
0&
#745000
11
0"
b1 :
b0 ;
1&
#750000
1!
1/
00
b0 .
b0 >
b0 E
b0 =
b0 A
b0 G
b0 I
b1111111111 L
0&
#755000
01
b1 ;
b10 :
0(
1&
#760000
0&
#765000
1-
b11 :
b10 ;
1&
#770000
0!
b1 .
b1 >
b1 E
0&
#775000
1,
0-
b100 :
b11 ;
1&
#780000
b1 =
b1 A
b1 G
b1 I
0&
#785000
0,
b1 :
b100 ;
1&
#790000
0&
#795000
b10 :
b1 ;
1&
#800000
0&
#805000
1-
b11 :
b10 ;
1&
#810000
1!
b10 .
b10 >
b10 E
0&
#815000
1,
0-
b100 :
b11 ;
1&
#820000
b10 =
b10 A
b10 G
b10 I
0&
#825000
0,
b1 :
b100 ;
1&
#830000
0&
#835000
b10 :
b1 ;
1&
#840000
0&
#845000
1-
b11 :
b10 ;
1&
#850000
0!
b11 .
b11 >
b11 E
0&
#855000
1,
0-
b100 :
b11 ;
1&
#860000
b11 =
b11 A
b11 G
b11 I
0&
#865000
0,
b1 :
b100 ;
1&
#870000
0&
#875000
b10 :
b1 ;
1&
#880000
0&
#885000
1-
b11 :
b10 ;
1&
#890000
1!
b100 .
b100 >
b100 E
0&
#895000
1,
0-
b100 :
b11 ;
1&
#900000
b100 =
b100 A
b100 G
b100 I
0&
#905000
0,
b1 :
b100 ;
1&
#910000
0&
#915000
b10 :
b1 ;
1&
#920000
0&
#925000
1-
b11 :
b10 ;
1&
#930000
0!
b101 .
b101 >
b101 E
0&
#935000
1,
0-
b100 :
b11 ;
1&
#940000
b101 =
b101 A
b101 G
b101 I
0&
#945000
0,
b1 :
b100 ;
1&
#950000
0&
#955000
b10 :
b1 ;
1&
#960000
0&
#965000
1-
b11 :
b10 ;
1&
#970000
1!
b110 .
b110 >
b110 E
0&
#975000
1,
0-
b100 :
b11 ;
1&
#980000
b110 =
b110 A
b110 G
b110 I
0&
#985000
0,
b1 :
b100 ;
1&
#990000
0&
#995000
b10 :
b1 ;
1&
#1000000
0&
#1005000
1-
b11 :
b10 ;
1&
#1010000
0!
b111 .
b111 >
b111 E
0&
#1015000
1,
0-
b100 :
b11 ;
1&
#1020000
b111 =
b111 A
b111 G
b111 I
0&
#1025000
0,
b1 :
b100 ;
1&
#1030000
0&
#1035000
b10 :
b1 ;
1&
#1040000
0&
#1045000
1-
b11 :
b10 ;
1&
#1050000
1!
b1000 .
b1000 >
b1000 E
0&
#1055000
1,
0-
b100 :
b11 ;
1&
#1060000
b1000 =
b1000 A
b1000 G
b1000 I
0&
#1065000
0,
b1 :
b100 ;
1&
#1070000
0&
#1075000
b10 :
b1 ;
1&
#1080000
0&
#1085000
1-
b11 :
b10 ;
1&
#1090000
0!
b1001 .
b1001 >
b1001 E
0&
#1095000
1,
0-
b100 :
b11 ;
1&
#1100000
b1001 =
b1001 A
b1001 G
b1001 I
0&
#1105000
0,
b1 :
b100 ;
1&
#1110000
0&
#1115000
b10 :
b1 ;
1&
#1120000
0&
#1125000
1-
b11 :
b10 ;
1&
#1130000
1!
b1010 .
b1010 >
b1010 E
0&
#1135000
1,
0-
b100 :
b11 ;
1&
#1140000
0/
10
b1010 =
b1010 A
b1010 G
b1010 I
0&
#1145000
0,
b101 :
b100 ;
1&
#1150000
0&
#1155000
1"
b101 ;
1&
#1160000
0&
#1165000
1&
#1170000
0&
#1175000
b1010101010 %
b1010101010 +
b1010101010 <
b1010101010 H
0M
b100 *
b1010101010 N
1&
#1180000
0&
#1185000
b0 :
1(
1&
#1190000
0&
#1195000
11
0"
b1 :
b0 ;
1&
#1200000
00
b1010101010 L
b0 =
b0 A
b0 G
b0 I
b0 .
b0 >
b0 E
0&
#1205000
01
b1 ;
b11 :
0(
1&
#1210000
0&
#1215000
1,
b100 :
b11 ;
1&
#1220000
1/
b1 =
b1 A
b1 G
b1 I
0&
#1225000
0,
b1 :
b100 ;
1&
#1230000
0&
#1235000
b10 :
b1 ;
1&
#1240000
0&
#1245000
1-
b11 :
b10 ;
1&
#1250000
0!
b1 .
b1 >
b1 E
0&
#1255000
1,
0-
b100 :
b11 ;
1&
#1260000
0/
b10 =
b10 A
b10 G
b10 I
0&
#1265000
0,
b1 :
b100 ;
1&
#1270000
0&
#1275000
b11 :
b1 ;
1&
#1280000
0&
#1285000
1,
b100 :
b11 ;
1&
#1290000
1/
b11 =
b11 A
b11 G
b11 I
0&
#1295000
0,
b1 :
b100 ;
1&
#1300000
0&
#1305000
b10 :
b1 ;
1&
#1310000
0&
#1315000
1-
b11 :
b10 ;
1&
#1320000
1!
b10 .
b10 >
b10 E
0&
#1325000
1,
0-
b100 :
b11 ;
1&
#1330000
0/
b100 =
b100 A
b100 G
b100 I
0&
#1335000
0,
b1 :
b100 ;
1&
#1340000
0&
#1345000
b11 :
b1 ;
1&
#1350000
0&
#1355000
1,
b100 :
b11 ;
1&
#1360000
1/
b101 =
b101 A
b101 G
b101 I
0&
#1365000
0,
b1 :
b100 ;
1&
#1370000
0&
#1375000
b10 :
b1 ;
1&
#1380000
0&
#1385000
1-
b11 :
b10 ;
1&
#1390000
0!
b11 .
b11 >
b11 E
0&
#1395000
1,
0-
b100 :
b11 ;
1&
#1400000
0/
b110 =
b110 A
b110 G
b110 I
0&
#1405000
0,
b1 :
b100 ;
1&
#1410000
0&
#1415000
b11 :
b1 ;
1&
#1420000
0&
#1425000
1,
b100 :
b11 ;
1&
#1430000
1/
b111 =
b111 A
b111 G
b111 I
0&
#1435000
0,
b1 :
b100 ;
1&
#1440000
0&
#1445000
b10 :
b1 ;
1&
#1450000
0&
#1455000
1-
b11 :
b10 ;
1&
#1460000
1!
b100 .
b100 >
b100 E
0&
#1465000
1,
0-
b100 :
b11 ;
1&
#1470000
0/
b1000 =
b1000 A
b1000 G
b1000 I
0&
#1475000
0,
b1 :
b100 ;
1&
#1480000
0&
#1485000
b11 :
b1 ;
1&
#1490000
0&
#1495000
1,
b100 :
b11 ;
1&
#1500000
1/
b1001 =
b1001 A
b1001 G
b1001 I
0&
#1505000
0,
b1 :
b100 ;
1&
#1510000
0&
#1515000
b10 :
b1 ;
1&
#1520000
0&
#1525000
1-
b11 :
b10 ;
1&
#1530000
0!
b101 .
b101 >
b101 E
0&
#1535000
1,
0-
b100 :
b11 ;
1&
#1540000
0/
10
b1010 =
b1010 A
b1010 G
b1010 I
0&
#1545000
0,
b101 :
b100 ;
1&
#1550000
0&
#1555000
1"
b101 ;
1&
#1560000
0&
#1565000
1&
#1570000
0&
#1575000
b1100110011 %
b1100110011 +
b1100110011 <
b1100110011 H
1M
b101 *
b1100110011 N
1&
#1580000
0&
#1585000
b0 :
1(
1&
#1590000
0&
#1595000
11
0"
b1 :
b0 ;
1&
#1600000
1!
1/
00
b1100110011 L
b0 =
b0 A
b0 G
b0 I
b0 .
b0 >
b0 E
0&
#1605000
01
b1 ;
b10 :
0(
1&
#1610000
0&
#1615000
1-
b11 :
b10 ;
1&
#1620000
0!
b1 .
b1 >
b1 E
0&
#1625000
1,
0-
b100 :
b11 ;
1&
#1630000
b1 =
b1 A
b1 G
b1 I
0&
#1635000
0,
b1 :
b100 ;
1&
#1640000
0&
#1645000
b10 :
b1 ;
1&
#1650000
0&
#1655000
1-
b11 :
b10 ;
1&
#1660000
1!
b10 .
b10 >
b10 E
0&
#1665000
1,
0-
b100 :
b11 ;
1&
#1670000
0/
b10 =
b10 A
b10 G
b10 I
0&
#1675000
0,
b1 :
b100 ;
1&
#1680000
0&
#1685000
b11 :
b1 ;
1&
#1690000
0&
#1695000
1,
b100 :
b11 ;
1&
#1700000
b11 =
b11 A
b11 G
b11 I
0&
#1705000
0,
b1 :
b100 ;
1&
#1710000
0&
#1715000
b11 :
b1 ;
1&
#1720000
0&
#1725000
1,
b100 :
b11 ;
1&
#1730000
1/
b100 =
b100 A
b100 G
b100 I
0&
#1735000
0,
b1 :
b100 ;
1&
#1740000
0&
#1745000
b10 :
b1 ;
1&
#1750000
0&
#1755000
1-
b11 :
b10 ;
1&
#1760000
0!
b11 .
b11 >
b11 E
0&
#1765000
1,
0-
b100 :
b11 ;
1&
#1770000
b101 =
b101 A
b101 G
b101 I
0&
#1775000
0,
b1 :
b100 ;
1&
#1780000
0&
#1785000
b10 :
b1 ;
1&
#1790000
0&
#1795000
1-
b11 :
b10 ;
1&
#1800000
1!
b100 .
b100 >
b100 E
0&
#1805000
1,
0-
b100 :
b11 ;
1&
#1810000
0/
b110 =
b110 A
b110 G
b110 I
0&
#1815000
0,
b1 :
b100 ;
1&
#1820000
0&
#1825000
b11 :
b1 ;
1&
#1830000
0&
#1835000
1,
b100 :
b11 ;
1&
#1840000
b111 =
b111 A
b111 G
b111 I
0&
#1845000
0,
b1 :
b100 ;
1&
#1850000
0&
#1855000
b11 :
b1 ;
1&
#1860000
0&
#1865000
1,
b100 :
b11 ;
1&
#1870000
1/
b1000 =
b1000 A
b1000 G
b1000 I
0&
#1875000
0,
b1 :
b100 ;
1&
#1880000
0&
#1885000
b10 :
b1 ;
1&
#1890000
0&
#1895000
1-
b11 :
b10 ;
1&
#1900000
0!
b101 .
b101 >
b101 E
0&
#1905000
1,
0-
b100 :
b11 ;
1&
#1910000
b1001 =
b1001 A
b1001 G
b1001 I
0&
#1915000
0,
b1 :
b100 ;
1&
#1920000
0&
#1925000
b10 :
b1 ;
1&
#1930000
0&
#1935000
1-
b11 :
b10 ;
1&
#1940000
1!
b110 .
b110 >
b110 E
0&
#1945000
1,
0-
b100 :
b11 ;
1&
#1950000
0/
10
b1010 =
b1010 A
b1010 G
b1010 I
0&
#1955000
0,
b101 :
b100 ;
1&
#1960000
0&
#1965000
1"
b101 ;
1&
#1970000
0&
#1975000
1&
#1980000
0&
#1985000
b1000000000 %
b1000000000 +
b1000000000 <
b1000000000 H
0M
b110 *
b1000000000 N
1&
#1990000
0&
#1995000
b0 :
1(
1&
#2000000
0&
#2005000
11
0"
b1 :
b0 ;
1&
#2010000
00
b0 .
b0 >
b0 E
b0 =
b0 A
b0 G
b0 I
b1000000000 L
0&
#2015000
01
b1 ;
b11 :
0(
1&
#2020000
0&
#2025000
1,
b100 :
b11 ;
1&
#2030000
b1 =
b1 A
b1 G
b1 I
0&
#2035000
0,
b1 :
b100 ;
1&
#2040000
0&
#2045000
b11 :
b1 ;
1&
#2050000
0&
#2055000
1,
b100 :
b11 ;
1&
#2060000
b10 =
b10 A
b10 G
b10 I
0&
#2065000
0,
b1 :
b100 ;
1&
#2070000
0&
#2075000
b11 :
b1 ;
1&
#2080000
0&
#2085000
1,
b100 :
b11 ;
1&
#2090000
b11 =
b11 A
b11 G
b11 I
0&
#2095000
0,
b1 :
b100 ;
1&
#2100000
0&
#2105000
b11 :
b1 ;
1&
#2110000
0&
#2115000
1,
b100 :
b11 ;
1&
#2120000
b100 =
b100 A
b100 G
b100 I
0&
#2125000
0,
b1 :
b100 ;
1&
#2130000
0&
#2135000
b11 :
b1 ;
1&
#2140000
0&
#2145000
1,
b100 :
b11 ;
1&
#2150000
b101 =
b101 A
b101 G
b101 I
0&
#2155000
0,
b1 :
b100 ;
1&
#2160000
0&
#2165000
b11 :
b1 ;
1&
#2170000
0&
#2175000
1,
b100 :
b11 ;
1&
#2180000
b110 =
b110 A
b110 G
b110 I
0&
#2185000
0,
b1 :
b100 ;
1&
#2190000
0&
#2195000
b11 :
b1 ;
1&
#2200000
0&
#2205000
1,
b100 :
b11 ;
1&
#2210000
b111 =
b111 A
b111 G
b111 I
0&
#2215000
0,
b1 :
b100 ;
1&
#2220000
0&
#2225000
b11 :
b1 ;
1&
#2230000
0&
#2235000
1,
b100 :
b11 ;
1&
#2240000
b1000 =
b1000 A
b1000 G
b1000 I
0&
#2245000
0,
b1 :
b100 ;
1&
#2250000
0&
#2255000
b11 :
b1 ;
1&
#2260000
0&
#2265000
1,
b100 :
b11 ;
1&
#2270000
1/
b1001 =
b1001 A
b1001 G
b1001 I
0&
#2275000
0,
b1 :
b100 ;
1&
#2280000
0&
#2285000
b10 :
b1 ;
1&
#2290000
0&
#2295000
1-
b11 :
b10 ;
1&
#2300000
0!
b1 .
b1 >
b1 E
0&
#2305000
1,
0-
b100 :
b11 ;
1&
#2310000
0/
10
b1010 =
b1010 A
b1010 G
b1010 I
0&
#2315000
0,
b101 :
b100 ;
1&
#2320000
0&
#2325000
1"
b101 ;
1&
#2330000
0&
#2335000
1&
#2340000
0&
#2345000
b101010101 %
b101010101 +
b101010101 <
b101010101 H
b111 *
b101010101 N
1&
#2350000
0&
#2355000
b0 :
1(
1&
#2360000
0&
#2365000
11
0"
b1 :
b0 ;
1&
#2370000
1!
1/
00
b0 .
b0 >
b0 E
b0 =
b0 A
b0 G
b0 I
b101010101 L
0&
#2375000
01
b1 ;
b10 :
0(
1&
#2380000
0&
#2385000
1-
b11 :
b10 ;
1&
#2390000
0!
b1 .
b1 >
b1 E
0&
#2395000
1,
0-
b100 :
b11 ;
1&
#2400000
0/
b1 =
b1 A
b1 G
b1 I
0&
#2405000
0,
b1 :
b100 ;
1&
#2410000
0&
#2415000
b11 :
b1 ;
1&
#2420000
0&
#2425000
1,
b100 :
b11 ;
1&
#2430000
1/
b10 =
b10 A
b10 G
b10 I
0&
#2435000
0,
b1 :
b100 ;
1&
#2440000
0&
#2445000
b10 :
b1 ;
1&
#2450000
0&
#2455000
1-
b11 :
b10 ;
1&
#2460000
1!
b10 .
b10 >
b10 E
0&
#2465000
1,
0-
b100 :
b11 ;
1&
#2470000
0/
b11 =
b11 A
b11 G
b11 I
0&
#2475000
0,
b1 :
b100 ;
1&
#2480000
0&
#2485000
b11 :
b1 ;
1&
#2490000
0&
#2495000
1,
b100 :
b11 ;
1&
#2500000
1/
b100 =
b100 A
b100 G
b100 I
0&
#2505000
0,
b1 :
b100 ;
1&
#2510000
0&
#2515000
b10 :
b1 ;
1&
#2520000
0&
#2525000
1-
b11 :
b10 ;
1&
#2530000
0!
b11 .
b11 >
b11 E
0&
#2535000
1,
0-
b100 :
b11 ;
1&
#2540000
0/
b101 =
b101 A
b101 G
b101 I
0&
#2545000
0,
b1 :
b100 ;
1&
#2550000
0&
#2555000
b11 :
b1 ;
1&
#2560000
0&
#2565000
1,
b100 :
b11 ;
1&
#2570000
1/
b110 =
b110 A
b110 G
b110 I
0&
