bintobcd/Ultimo/comparador.v
module comparador #(
    parameter N     = 16,
    parameter WIDTH = 5
)(
    input  wire [WIDTH-1:0] count,
    output wire             Z
);

    assign Z = (count == N[WIDTH-1:0]) ? 1'b1 : 1'b0;

endmodule

bintobcd/Ultimo/contador_i.v
module contador_i #(
    parameter WIDTH = 5   
)(
    input  wire              clk,
    input  wire              rst,
    input  wire              inc,
    output reg [WIDTH-1:0]   count
);

    always @(negedge clk) begin
        if (rst)
            count <= {WIDTH{1'b0}};
        else if (inc)
            count <= count + 1'b1;
    end

endmodule

bintobcd/Ultimo/reg_msb_propio.v
module reg_msb_propio (
    input  wire       clk,
    input  wire       LD_MSB,
    input  wire [3:0] digito_actual,
    output reg  [3:0] MSB
);

    always @(negedge clk) begin
        if (LD_MSB)
            MSB <= digito_actual;
    end

endmodule

bintobcd/Ultimo/reg_a36.v
module reg_a36 #(
    parameter N = 16
)(
    input  wire         clk,
    input  wire         LD,
    input  wire         SH,
    input  wire         COMMIT,
    input  wire         ADD,
    input  wire [2:0]   digit_sel,   
    input  wire [N-1:0] a_in,
    output reg  [35:0]  A
);

    always @(negedge clk) begin
        if (LD)
            A <= {20'b0, a_in};
        else if (SH)
            A <= A << 1;
        else if (COMMIT && ADD) begin
            case (digit_sel)
                3'd0: A[19:16] <= A[19:16] + 4'd3;
                3'd1: A[23:20] <= A[23:20] + 4'd3;
                3'd2: A[27:24] <= A[27:24] + 4'd3;
                3'd3: A[31:28] <= A[31:28] + 4'd3;
                3'd4: A[35:32] <= A[35:32] + 4'd3;
                default: ;
            endcase
        end
    end

endmodule

bintobcd/Ultimo/datapath.v
module datapath #(
    parameter N = 16
)(
    input  wire         clk,
    input  wire [N-1:0] a,
    input  wire         LD,
    input  wire         SH,
    input  wire         LD_MSB,
    input  wire         COMMIT,
    input  wire [2:0]   digit_sel,
    output wire         ADD,     
    output wire         Z,      
    output wire [19:0]  bcd      // resultado final 
);

    wire [35:0] A;
    wire [3:0]  digito_actual;
    wire [3:0]  MSB;
    wire [4:0]  count;

    // Multiplexor: extrae el digito seleccionado del registro grande
    assign digito_actual = (digit_sel == 3'd0) ? A[19:16] :
                            (digit_sel == 3'd1) ? A[23:20] :
                            (digit_sel == 3'd2) ? A[27:24] :
                            (digit_sel == 3'd3) ? A[31:28] :
                                                   A[35:32];

    reg_a36 #(.N(N)) u_reg_a36 (
        .clk       (clk),
        .LD        (LD),
        .SH        (SH),
        .COMMIT    (COMMIT),
        .ADD       (ADD),
        .digit_sel (digit_sel),
        .a_in      (a),
        .A         (A)
    );

    reg_msb_propio u_reg_msb (
        .clk           (clk),
        .LD_MSB        (LD_MSB),
        .digito_actual (digito_actual),
        .MSB           (MSB)
    );

    assign ADD = (MSB > 4'd4) ? 1'b1 : 1'b0;
    assign bcd = A[35:16];

    contador_i #(.WIDTH(5)) u_contador_i (
        .clk   (clk),
        .rst   (LD),
        .inc   (SH),
        .count (count)
    );

    comparador #(.N(N), .WIDTH(5)) u_comparador (
        .count (count),
        .Z     (Z)
    );

endmodule

bintobcd/Ultimo/control.v
module control (
    input  wire clk,
    input  wire rst,
    input  wire start,
    input  wire ADD,
    input  wire Z,
    output reg  LD,
    output reg  SH,
    output reg  LD_MSB,
    output reg  COMMIT,
    output reg  [2:0] digit_sel,
    output reg  DONE
);

    localparam [3:0]
        START  = 4'd0,
        SHIFT  = 4'd1,
        CHECK1 = 4'd2,  ADD1 = 4'd3,
        CHECK2 = 4'd4,  ADD2 = 4'd5,
        CHECK3 = 4'd6,  ADD3 = 4'd7,
        CHECK4 = 4'd8,  ADD4 = 4'd9,
        CHECK5 = 4'd10, ADD5 = 4'd11,
        DONEST = 4'd12;

    reg [3:0] state, next_state;

    always @(posedge clk or posedge rst) begin
        if (rst)
            state <= START;
        else
            state <= next_state;
    end

    always @(*) begin
        case (state)
            START:  next_state = start ? SHIFT  : START;
            SHIFT:  next_state = Z     ? DONEST : CHECK1;

            CHECK1: next_state = ADD ? ADD1 : CHECK2;
            ADD1:   next_state = CHECK2;

            CHECK2: next_state = ADD ? ADD2 : CHECK3;
            ADD2:   next_state = CHECK3;

            CHECK3: next_state = ADD ? ADD3 : CHECK4;
            ADD3:   next_state = CHECK4;

            CHECK4: next_state = ADD ? ADD4 : CHECK5;
            ADD4:   next_state = CHECK5;

            CHECK5: next_state = ADD ? ADD5 : SHIFT;
            ADD5:   next_state = SHIFT;

            DONEST: next_state = start ? START : DONEST;
            default: next_state = START;
        endcase
    end

    always @(*) begin
        LD        = 1'b0;
        SH        = 1'b0;
        LD_MSB    = 1'b0;
        COMMIT    = 1'b0;
        digit_sel = 3'd0;
        DONE      = 1'b0;
        case (state)
            START:  LD = 1'b1;
            SHIFT:  SH = 1'b1;

            CHECK1: begin LD_MSB = 1'b1; digit_sel = 3'd0; end
            ADD1:   begin COMMIT = 1'b1; digit_sel = 3'd0; end

            CHECK2: begin LD_MSB = 1'b1; digit_sel = 3'd1; end
            ADD2:   begin COMMIT = 1'b1; digit_sel = 3'd1; end

            CHECK3: begin LD_MSB = 1'b1; digit_sel = 3'd2; end
            ADD3:   begin COMMIT = 1'b1; digit_sel = 3'd2; end

            CHECK4: begin LD_MSB = 1'b1; digit_sel = 3'd3; end
            ADD4:   begin COMMIT = 1'b1; digit_sel = 3'd3; end

            CHECK5: begin LD_MSB = 1'b1; digit_sel = 3'd4; end
            ADD5:   begin COMMIT = 1'b1; digit_sel = 3'd4; end

            DONEST: DONE = 1'b1;
            default: ;
        endcase
    end

endmodule

bintobcd/Ultimo/bin2bcd_top.v
module bin2bcd_top #(
    parameter N = 16
)(
    input  wire         clk,
    input  wire         rst,
    input  wire         start,
    input  wire [N-1:0] a,
    output wire [19:0]  bcd,
    output wire         DONE
);

    wire LD, SH, LD_MSB, COMMIT;
    wire [2:0] digit_sel;
    wire ADD, Z;

    control u_control (
        .clk        (clk),
        .rst        (rst),
        .start      (start),
        .ADD        (ADD),
        .Z          (Z),
        .LD         (LD),
        .SH         (SH),
        .LD_MSB     (LD_MSB),
        .COMMIT     (COMMIT),
        .digit_sel  (digit_sel),
        .DONE       (DONE)
    );

    datapath #(.N(N)) u_datapath (
        .clk       (clk),
        .a         (a),
        .LD        (LD),
        .SH        (SH),
        .LD_MSB    (LD_MSB),
        .COMMIT    (COMMIT),
        .digit_sel (digit_sel),
        .ADD       (ADD),
        .Z         (Z),
        .bcd       (bcd)
    );

endmodule

bintobcd/Ultimo/bin2bcd_top_TB.v
module tb_bin2bcd;

    parameter N = 16;

    reg              clk;
    reg              rst;
    reg              start;
    reg  [N-1:0]     a;
    wire [19:0]      bcd;
    wire             DONE;

    integer errors = 0;
    integer tests  = 0;

    bin2bcd_top #(.N(N)) uut (
        .clk   (clk),
        .rst   (rst),
        .start (start),
        .a     (a),
        .bcd   (bcd),
        .DONE  (DONE)
    );

    initial clk = 1'b0;
    always #5 clk = ~clk;

    function [19:0] bin_to_bcd_ref(input integer val);
        integer d0, d1, d2, d3, d4;
        begin
            d0 = val % 10;
            d1 = (val / 10) % 10;
            d2 = (val / 100) % 10;
            d3 = (val / 1000) % 10;
            d4 = (val / 10000) % 10;
            bin_to_bcd_ref = {d4[3:0], d3[3:0], d2[3:0], d1[3:0], d0[3:0]};
        end
    endfunction

    task run_test(input [N-1:0] ta);
        reg [19:0] expected;
        begin
            tests    = tests + 1;
            expected = bin_to_bcd_ref(ta);

            a = ta;
            start = 1'b0;
            @(posedge clk);

            start = 1'b1;
            @(posedge clk);
            @(posedge clk);
            start = 1'b0;

            wait (DONE == 1'b1);
            @(posedge clk);

            if (bcd !== expected) begin
                $display("FALLO: a=%0d -> bcd=%h (esperado %h = %0d%0d%0d%0d%0d decimal)",
                          ta, bcd, expected,
                          expected[19:16], expected[15:12], expected[11:8], expected[7:4], expected[3:0]);
                errors = errors + 1;
            end else begin
                $display("OK   : a=%0d -> bcd=%h (%0d%0d%0d%0d%0d)",
                          ta, bcd,
                          bcd[19:16], bcd[15:12], bcd[11:8], bcd[7:4], bcd[3:0]);
            end

            @(posedge clk);
        end
    endtask

    initial begin
        $dumpfile("bin2bcd_top_TB.vcd");
        $dumpvars(0, tb_bin2bcd);

        rst   = 1'b1;
        start = 1'b0;
        a = 0;
        repeat (2) @(posedge clk);
        rst = 1'b0;
        @(posedge clk);

        run_test(16'd0);       // 0     -> 00000
        run_test(16'd9);       // 9     -> 00009
        run_test(16'd10);      // 10    -> 00010
        run_test(16'd150);     // 150   -> 00150
        run_test(16'd1234);    // 1234  -> 01234
        run_test(16'd9999);    // 9999  -> 09999
        run_test(16'd10000);   // 10000 -> 10000
        run_test(16'd65535);   // 65535 -> 65535 (maximo de 16 bits)
        run_test(16'd8);       // 8     -> 00008 (no necesita correccion)
        run_test(16'd25);      // 25    -> 00025

        $display("--------------------------------------------------");
        if (errors == 0)
            $display("TODAS LAS PRUEBAS PASARON (%0d/%0d)", tests, tests);
        else
            $display("%0d DE %0d PRUEBAS FALLARON", errors, tests);

        $finish;
    end

endmodule

bintobcd/Ultimo/bin2bcd_top_TB.vcd
$date
	Thu Jul 16 19:30:09 2026
$end
$version
	Icarus Verilog
$end
$timescale
	1ps
$end
$scope module tb_bin2bcd $end
$var wire 20 ! bcd [19:0] $end
$var wire 1 " DONE $end
$var parameter 32 # N $end
$var reg 16 $ a [15:0] $end
$var reg 1 % clk $end
$var reg 1 & rst $end
$var reg 1 ' start $end
$var integer 32 ( errors [31:0] $end
$var integer 32 ) tests [31:0] $end
$scope function bin_to_bcd_ref $end
$var integer 32 * d0 [31:0] $end
$var integer 32 + d1 [31:0] $end
$var integer 32 , d2 [31:0] $end
$var integer 32 - d3 [31:0] $end
$var integer 32 . d4 [31:0] $end
$var integer 32 / val [31:0] $end
$upscope $end
$scope module uut $end
$var wire 16 0 a [15:0] $end
$var wire 1 % clk $end
$var wire 1 & rst $end
$var wire 1 ' start $end
$var wire 3 1 digit_sel [2:0] $end
$var wire 20 2 bcd [19:0] $end
$var wire 1 3 Z $end
$var wire 1 4 SH $end
$var wire 1 5 LD_MSB $end
$var wire 1 6 LD $end
$var wire 1 " DONE $end
$var wire 1 7 COMMIT $end
$var wire 1 8 ADD $end
$var parameter 32 9 N $end
$scope module u_control $end
$var wire 1 % clk $end
$var wire 1 & rst $end
$var wire 1 ' start $end
$var wire 1 3 Z $end
$var wire 1 8 ADD $end
$var parameter 4 : ADD1 $end
$var parameter 4 ; ADD2 $end
$var parameter 4 < ADD3 $end
$var parameter 4 = ADD4 $end
$var parameter 4 > ADD5 $end
$var parameter 4 ? CHECK1 $end
$var parameter 4 @ CHECK2 $end
$var parameter 4 A CHECK3 $end
$var parameter 4 B CHECK4 $end
$var parameter 4 C CHECK5 $end
$var parameter 4 D DONEST $end
$var parameter 4 E SHIFT $end
$var parameter 4 F START $end
$var reg 1 7 COMMIT $end
$var reg 1 " DONE $end
$var reg 1 6 LD $end
$var reg 1 5 LD_MSB $end
$var reg 1 4 SH $end
$var reg 3 G digit_sel [2:0] $end
$var reg 4 H next_state [3:0] $end
$var reg 4 I state [3:0] $end
$upscope $end
$scope module u_datapath $end
$var wire 1 7 COMMIT $end
$var wire 1 6 LD $end
$var wire 1 5 LD_MSB $end
$var wire 1 4 SH $end
$var wire 16 J a [15:0] $end
$var wire 1 % clk $end
$var wire 3 K digit_sel [2:0] $end
$var wire 4 L digito_actual [3:0] $end
$var wire 5 M count [4:0] $end
$var wire 20 N bcd [19:0] $end
$var wire 1 3 Z $end
$var wire 4 O MSB [3:0] $end
$var wire 1 8 ADD $end
$var wire 36 P A [35:0] $end
$var parameter 32 Q N $end
$scope module u_comparador $end
$var wire 5 R count [4:0] $end
$var wire 1 3 Z $end
$var parameter 32 S N $end
$var parameter 32 T WIDTH $end
$upscope $end
$scope module u_contador_i $end
$var wire 1 % clk $end
$var wire 1 4 inc $end
$var wire 1 6 rst $end
$var parameter 32 U WIDTH $end
$var reg 5 V count [4:0] $end
$upscope $end
$scope module u_reg_a36 $end
$var wire 1 8 ADD $end
$var wire 1 7 COMMIT $end
$var wire 1 6 LD $end
$var wire 1 4 SH $end
$var wire 16 W a_in [15:0] $end
$var wire 1 % clk $end
$var wire 3 X digit_sel [2:0] $end
$var parameter 32 Y N $end
$var reg 36 Z A [35:0] $end
$upscope $end
$scope module u_reg_msb $end
$var wire 1 5 LD_MSB $end
$var wire 1 % clk $end
$var wire 4 [ digito_actual [3:0] $end
$var reg 4 \ MSB [3:0] $end
$upscope $end
$upscope $end
$upscope $end
$scope task run_test $end
$var reg 20 ] expected [19:0] $end
$var reg 16 ^ ta [15:0] $end
$upscope $end
$upscope $end
$enddefinitions $end
$comment Show the parameter values. $end
$dumpall
b10000 Y
b101 U
b101 T
b10000 S
b10000 Q
b0 F
b1 E
b1100 D
b1010 C
b1000 B
b110 A
b100 @
b10 ?
b1011 >
b1001 =
b111 <
b101 ;
b11 :
b10000 9
b10000 #
$end
#0
$dumpvars
bx ^
bx ]
bx \
bx [
bx Z
b0 X
b0 W
bx V
bx R
bx P
bx O
bx N
bx M
bx L
b0 K
b0 J
b0 I
b0 H
b0 G
x8
07
16
05
04
x3
bx 2
b0 1
b0 0
bx /
bx .
bx -
bx ,
bx +
bx *
b0 )
b0 (
0'
1&
0%
b0 $
0"
bx !
$end
#5000
1%
#10000
b0 L
b0 [
03
b0 !
b0 2
b0 N
b0 M
b0 R
b0 V
b0 P
b0 Z
0%
#15000
0&
1%
#20000
0%
#25000
b0 ]
b0 .
b0 -
b0 ,
b0 +
b0 *
b0 /
b1 )
b0 ^
1%
#30000
0%
#35000
b1 H
1'
1%
#40000
0%
#45000
14
06
b10 H
b1 I
1%
#50000
b1 M
b1 R
b1 V
0%
#55000
15
04
b0xxx H
b10 I
0'
1%
#60000
b100 H
08
b0 O
b0 \
0%
#65000
b1 1
b1 G
b1 K
b1 X
15
b110 H
b100 I
1%
#70000
0%
#75000
b10 1
b10 G
b10 K
b10 X
15
b1000 H
b110 I
1%
#80000
0%
#85000
b11 1
b11 G
b11 K
b11 X
15
b1010 H
b1000 I
1%
#90000
0%
#95000
b100 1
b100 G
b100 K
b100 X
15
b1 H
b1010 I
1%
#100000
0%
#105000
14
b0 1
b0 G
b0 K
b0 X
05
b10 H
b1 I
1%
#110000
b10 M
b10 R
b10 V
0%
#115000
15
04
b100 H
b10 I
1%
#120000
0%
#125000
b1 1
b1 G
b1 K
b1 X
15
b110 H
b100 I
1%
#130000
0%
#135000
b10 1
b10 G
b10 K
b10 X
15
b1000 H
b110 I
1%
#140000
0%
#145000
b11 1
b11 G
b11 K
b11 X
15
b1010 H
b1000 I
1%
#150000
0%
#155000
b100 1
b100 G
b100 K
b100 X
15
b1 H
b1010 I
1%
#160000
0%
#165000
14
b0 1
b0 G
b0 K
b0 X
05
b10 H
b1 I
1%
#170000
b11 M
b11 R
b11 V
0%
#175000
15
04
b100 H
b10 I
1%
#180000
0%
#185000
b1 1
b1 G
b1 K
b1 X
15
b110 H
b100 I
1%
#190000
0%
#195000
b10 1
b10 G
b10 K
b10 X
15
b1000 H
b110 I
1%
#200000
0%
#205000
b11 1
b11 G
b11 K
b11 X
15
b1010 H
b1000 I
1%
#210000
0%
#215000
b100 1
b100 G
b100 K
b100 X
15
b1 H
b1010 I
1%
#220000
0%
#225000
14
b0 1
b0 G
b0 K
b0 X
05
b10 H
b1 I
1%
#230000
b100 M
b100 R
b100 V
0%
#235000
15
04
b100 H
b10 I
1%
#240000
0%
#245000
b1 1
b1 G
b1 K
b1 X
15
b110 H
b100 I
1%
#250000
0%
#255000
b10 1
b10 G
b10 K
b10 X
15
b1000 H
b110 I
1%
#260000
0%
#265000
b11 1
b11 G
b11 K
b11 X
15
b1010 H
b1000 I
1%
#270000
0%
#275000
b100 1
b100 G
b100 K
b100 X
15
b1 H
b1010 I
1%
#280000
0%
#285000
14
b0 1
b0 G
b0 K
b0 X
05
b10 H
b1 I
1%
#290000
b101 M
b101 R
b101 V
0%
#295000
15
04
b100 H
b10 I
1%
#300000
0%
#305000
b1 1
b1 G
b1 K
b1 X
15
b110 H
b100 I
1%
#310000
0%
#315000
b10 1
b10 G
b10 K
b10 X
15
b1000 H
b110 I
1%
#320000
0%
#325000
b11 1
b11 G
b11 K
b11 X
15
b1010 H
b1000 I
1%
#330000
0%
#335000
b100 1
b100 G
b100 K
b100 X
15
b1 H
b1010 I
1%
#340000
0%
#345000
14
b0 1
b0 G
b0 K
b0 X
05
b10 H
b1 I
1%
#350000
b110 M
b110 R
b110 V
0%
#355000
15
04
b100 H
b10 I
1%
#360000
0%
#365000
b1 1
b1 G
b1 K
b1 X
15
b110 H
b100 I
1%
#370000
0%
#375000
b10 1
b10 G
b10 K
b10 X
15
b1000 H
b110 I
1%
#380000
0%
#385000
b11 1
b11 G
b11 K
b11 X
15
b1010 H
b1000 I
1%
#390000
0%
#395000
b100 1
b100 G
b100 K
b100 X
15
b1 H
b1010 I
1%
#400000
0%
#405000
14
b0 1
b0 G
b0 K
b0 X
05
b10 H
b1 I
1%
#410000
b111 M
b111 R
b111 V
0%
#415000
15
04
b100 H
b10 I
1%
#420000
0%
#425000
b1 1
b1 G
b1 K
b1 X
15
b110 H
b100 I
1%
#430000
0%
#435000
b10 1
b10 G
b10 K
b10 X
15
b1000 H
b110 I
1%
#440000
0%
#445000
b11 1
b11 G
b11 K
b11 X
15
b1010 H
b1000 I
1%
#450000
0%
#455000
b100 1
b100 G
b100 K
b100 X
15
b1 H
b1010 I
1%
#460000
0%
#465000
14
b0 1
b0 G
b0 K
b0 X
05
b10 H
b1 I
1%
#470000
b1000 M
b1000 R
b1000 V
0%
#475000
15
04
b100 H
b10 I
1%
#480000
0%
#485000
b1 1
b1 G
b1 K
b1 X
15
b110 H
b100 I
1%
#490000
0%
#495000
b10 1
b10 G
b10 K
b10 X
15
b1000 H
b110 I
1%
#500000
0%
#505000
b11 1
b11 G
b11 K
b11 X
15
b1010 H
b1000 I
1%
#510000
0%
#515000
b100 1
b100 G
b100 K
b100 X
15
b1 H
b1010 I
1%
#520000
0%
#525000
14
b0 1
b0 G
b0 K
b0 X
05
b10 H
b1 I
1%
#530000
b1001 M
b1001 R
b1001 V
0%
#535000
15
04
b100 H
b10 I
1%
#540000
0%
#545000
b1 1
b1 G
b1 K
b1 X
15
b110 H
b100 I
1%
#550000
0%
#555000
b10 1
b10 G
b10 K
b10 X
15
b1000 H
b110 I
1%
#560000
0%
#565000
b11 1
b11 G
b11 K
b11 X
15
b1010 H
b1000 I
1%
#570000
0%
#575000
b100 1
b100 G
b100 K
b100 X
15
b1 H
b1010 I
1%
#580000
0%
#585000
14
b0 1
b0 G
b0 K
b0 X
05
b10 H
b1 I
1%
#590000
b1010 M
b1010 R
b1010 V
0%
#595000
15
04
b100 H
b10 I
1%
#600000
0%
#605000
b1 1
b1 G
b1 K
b1 X
15
b110 H
b100 I
1%
#610000
0%
#615000
b10 1
b10 G
b10 K
b10 X
15
b1000 H
b110 I
1%
#620000
0%
#625000
b11 1
b11 G
b11 K
b11 X
15
b1010 H
b1000 I
1%
#630000
0%
#635000
b100 1
b100 G
b100 K
b100 X
15
b1 H
b1010 I
1%
#640000
0%
#645000
14
b0 1
b0 G
b0 K
b0 X
05
b10 H
b1 I
1%
#650000
b1011 M
b1011 R
b1011 V
0%
#655000
15
04
b100 H
b10 I
1%
#660000
0%
#665000
b1 1
b1 G
b1 K
b1 X
15
b110 H
b100 I
1%
#670000
0%
#675000
b10 1
b10 G
b10 K
b10 X
15
b1000 H
b110 I
1%
#680000
0%
#685000
b11 1
b11 G
b11 K
b11 X
15
b1010 H
b1000 I
1%
#690000
0%
#695000
b100 1
b100 G
b100 K
b100 X
15
b1 H
b1010 I
1%
#700000
0%
#705000
14
b0 1
b0 G
b0 K
b0 X
05
b10 H
b1 I
1%
#710000
b1100 M
b1100 R
b1100 V
0%
#715000
15
04
b100 H
b10 I
1%
#720000
0%
#725000
b1 1
b1 G
b1 K
b1 X
15
b110 H
b100 I
1%
#730000
0%
#735000
b10 1
b10 G
b10 K
b10 X
15
b1000 H
b110 I
1%
#740000
0%
#745000
b11 1
b11 G
b11 K
b11 X
15
b1010 H
b1000 I
1%
#750000
0%
#755000
b100 1
b100 G
b100 K
b100 X
15
b1 H
b1010 I
1%
#760000
0%
#765000
14
b0 1
b0 G
b0 K
b0 X
05
b10 H
b1 I
1%
#770000
b1101 M
b1101 R
b1101 V
0%
#775000
15
04
b100 H
b10 I
1%
#780000
0%
#785000
b1 1
b1 G
b1 K
b1 X
15
b110 H
b100 I
1%
#790000
0%
#795000
b10 1
b10 G
b10 K
b10 X
15
b1000 H
b110 I
1%
#800000
0%
#805000
b11 1
b11 G
b11 K
b11 X
15
b1010 H
b1000 I
1%
#810000
0%
#815000
b100 1
b100 G
b100 K
b100 X
15
b1 H
b1010 I
1%
#820000
0%
#825000
14
b0 1
b0 G
b0 K
b0 X
05
b10 H
b1 I
1%
#830000
b1110 M
b1110 R
b1110 V
0%
#835000
15
04
b100 H
b10 I
1%
#840000
0%
#845000
b1 1
b1 G
b1 K
b1 X
15
b110 H
b100 I
1%
#850000
0%
#855000
b10 1
b10 G
b10 K
b10 X
15
b1000 H
b110 I
1%
#860000
0%
#865000
b11 1
b11 G
b11 K
b11 X
15
b1010 H
b1000 I
1%
#870000
0%
#875000
b100 1
b100 G
b100 K
b100 X
15
b1 H
b1010 I
1%
#880000
0%
#885000
14
b0 1
b0 G
b0 K
b0 X
05
b10 H
b1 I
1%
#890000
b1111 M
b1111 R
b1111 V
0%
#895000
15
04
b100 H
b10 I
1%
#900000
0%
#905000
b1 1
b1 G
b1 K
b1 X
15
b110 H
b100 I
1%
#910000
0%
#915000
b10 1
b10 G
b10 K
b10 X
15
b1000 H
b110 I
1%
#920000
0%
#925000
b11 1
b11 G
b11 K
b11 X
15
b1010 H
b1000 I
1%
#930000
0%
#935000
b100 1
b100 G
b100 K
b100 X
15
b1 H
b1010 I
1%
#940000
0%
#945000
14
b0 1
b0 G
b0 K
b0 X
05
b10 H
b1 I
1%
#950000
b1100 H
13
b10000 M
b10000 R
b10000 V
0%
#955000
1"
04
b1100 I
1%
#960000
0%
#965000
1%
#970000
0%
#975000
b1001 $
b1001 0
b1001 J
b1001 W
b1001 ]
b1001 *
b1001 /
b10 )
b1001 ^
1%
#980000
0%
#985000
b0 H
1'
1%
#990000
0%
#995000
16
0"
b1 H
b0 I
1%
#1000000
03
b1001 P
b1001 Z
b0 M
b0 R
b0 V
0%
#1005000
14
06
b1 I
b10 H
0'
1%
#1010000
b1 M
b1 R
b1 V
b10010 P
b10010 Z
0%
#1015000
15
04
b100 H
b10 I
1%
#1020000
0%
#1025000
b1 1
b1 G
b1 K
b1 X
15
b110 H
b100 I
1%
#1030000
0%
#1035000
b10 1
b10 G
b10 K
b10 X
15
b1000 H
b110 I
1%
#1040000
0%
#1045000
b11 1
b11 G
b11 K
b11 X
15
b1010 H
b1000 I
1%
#1050000
0%
#1055000
b100 1
b100 G
b100 K
b100 X
15
b1 H
b1010 I
1%
#1060000
0%
#1065000
14
b0 1
b0 G
b0 K
b0 X
05
b10 H
b1 I
1%
#1070000
b10 M
b10 R
b10 V
b100100 P
b100100 Z
0%
#1075000
15
04
b100 H
b10 I
1%
#1080000
0%
#1085000
b1 1
b1 G
b1 K
b1 X
15
b110 H
b100 I
1%
#1090000
0%
#1095000
b10 1
b10 G
b10 K
b10 X
15
b1000 H
b110 I
1%
#1100000
0%
#1105000
b11 1
b11 G
b11 K
b11 X
15
b1010 H
b1000 I
1%
#1110000
0%
#1115000
b100 1
b100 G
b100 K
b100 X
15
b1 H
b1010 I
1%
#1120000
0%
#1125000
14
b0 1
b0 G
b0 K
b0 X
05
b10 H
b1 I
1%
#1130000
b11 M
b11 R
b11 V
b1001000 P
b1001000 Z
0%
#1135000
15
04
b100 H
b10 I
1%
#1140000
0%
#1145000
b1 1
b1 G
b1 K
b1 X
15
b110 H
b100 I
1%
#1150000
0%
#1155000
b10 1
b10 G
b10 K
b10 X
15
b1000 H
b110 I
1%
#1160000
0%
#1165000
b11 1
b11 G
b11 K
b11 X
15
b1010 H
b1000 I
1%
#1170000
0%
#1175000
b100 1
b100 G
b100 K
b100 X
15
b1 H
b1010 I
1%
#1180000
0%
#1185000
14
b0 1
b0 G
b0 K
b0 X
05
b10 H
b1 I
1%
#1190000
b100 M
b100 R
b100 V
b10010000 P
b10010000 Z
0%
#1195000
15
04
b100 H
b10 I
1%
#1200000
0%
#1205000
b1 1
b1 G
b1 K
b1 X
15
b110 H
b100 I
1%
#1210000
0%
#1215000
b10 1
b10 G
b10 K
b10 X
15
b1000 H
b110 I
1%
#1220000
0%
#1225000
b11 1
b11 G
b11 K
b11 X
15
b1010 H
b1000 I
1%
#1230000
0%
#1235000
b100 1
b100 G
b100 K
b100 X
15
b1 H
b1010 I
1%
#1240000
0%
#1245000
14
b0 1
b0 G
b0 K
b0 X
05
b10 H
b1 I
1%
#1250000
b101 M
b101 R
b101 V
b100100000 P
b100100000 Z
0%
#1255000
15
04
b100 H
b10 I
1%
#1260000
0%
#1265000
b1 1
b1 G
b1 K
b1 X
15
b110 H
b100 I
1%
#1270000
0%
#1275000
b10 1
b10 G
b10 K
b10 X
15
b1000 H
b110 I
1%
#1280000
0%
#1285000
b11 1
b11 G
b11 K
b11 X
15
b1010 H
b1000 I
1%
#1290000
0%
#1295000
b100 1
b100 G
b100 K
b100 X
15
b1 H
b1010 I
1%
#1300000
0%
#1305000
14
b0 1
b0 G
b0 K
b0 X
05
b10 H
b1 I
1%
#1310000
b110 M
b110 R
b110 V
b1001000000 P
b1001000000 Z
0%
#1315000
15
04
b100 H
b10 I
1%
#1320000
0%
#1325000
b1 1
b1 G
b1 K
b1 X
15
b110 H
b100 I
1%
#1330000
0%
#1335000
b10 1
b10 G
b10 K
b10 X
15
b1000 H
b110 I
1%
#1340000
0%
#1345000
b11 1
b11 G
b11 K
b11 X
15
b1010 H
b1000 I
1%
#1350000
0%
#1355000
b100 1
b100 G
b100 K
b100 X
15
b1 H
b1010 I
1%
#1360000
0%
#1365000
14
b0 1
b0 G
b0 K
b0 X
05
b10 H
b1 I
1%
#1370000
b111 M
b111 R
b111 V
b10010000000 P
b10010000000 Z
0%
#1375000
15
04
b100 H
b10 I
1%
#1380000
0%
#1385000
b1 1
b1 G
b1 K
b1 X
15
b110 H
b100 I
1%
#1390000
0%
#1395000
b10 1
b10 G
b10 K
b10 X
15
b1000 H
b110 I
1%
#1400000
0%
#1405000
b11 1
b11 G
b11 K
b11 X
15
b1010 H
b1000 I
1%
#1410000
0%
#1415000
b100 1
b100 G
b100 K
b100 X
15
b1 H
b1010 I
1%
#1420000
0%
#1425000
14
b0 1
b0 G
b0 K
b0 X
05
b10 H
b1 I
1%
#1430000
b1000 M
b1000 R
b1000 V
b100100000000 P
b100100000000 Z
0%
#1435000
15
04
b100 H
b10 I
1%
#1440000
0%
#1445000
b1 1
b1 G
b1 K
b1 X
15
b110 H
b100 I
1%
#1450000
0%
#1455000
b10 1
b10 G
b10 K
b10 X
15
b1000 H
b110 I
1%
#1460000
0%
#1465000
b11 1
b11 G
b11 K
b11 X
15
b1010 H
b1000 I
1%
#1470000
0%
#1475000
b100 1
b100 G
b100 K
b100 X
15
b1 H
b1010 I
1%
#1480000
0%
#1485000
14
b0 1
b0 G
b0 K
b0 X
05
b10 H
b1 I
1%
#1490000
b1001 M
b1001 R
b1001 V
b1001000000000 P
b1001000000000 Z
0%
#1495000
15
04
b100 H
b10 I
1%
#1500000
0%
#1505000
b1 1
b1 G
b1 K
b1 X
15
b110 H
b100 I
1%
#1510000
0%
#1515000
b10 1
b10 G
b10 K
b10 X
15
b1000 H
b110 I
1%
#1520000
0%
#1525000
b11 1
b11 G
b11 K
b11 X
15
b1010 H
b1000 I
1%
#1530000
0%
#1535000
b100 1
b100 G
b100 K
b100 X
15
b1 H
b1010 I
1%
#1540000
0%
#1545000
14
b0 1
b0 G
b0 K
b0 X
05
b10 H
b1 I
1%
#1550000
b1010 M
b1010 R
b1010 V
b10010000000000 P
b10010000000000 Z
0%
#1555000
15
04
b100 H
b10 I
1%
#1560000
0%
#1565000
b1 1
b1 G
b1 K
b1 X
15
b110 H
b100 I
1%
#1570000
0%
#1575000
b10 1
b10 G
b10 K
b10 X
15
b1000 H
b110 I
1%
#1580000
0%
#1585000
b11 1
b11 G
b11 K
b11 X
15
b1010 H
b1000 I
1%
#1590000
0%
#1595000
b100 1
b100 G
b100 K
b100 X
15
b1 H
b1010 I
1%
#1600000
0%
#1605000
14
b0 1
b0 G
b0 K
b0 X
05
b10 H
b1 I
1%
#1610000
b1011 M
b1011 R
b1011 V
b100100000000000 P
b100100000000000 Z
0%
#1615000
15
04
b100 H
b10 I
1%
#1620000
0%
#1625000
b1 1
b1 G
b1 K
b1 X
15
b110 H
b100 I
1%
#1630000
0%
#1635000
b10 1
b10 G
b10 K
b10 X
15
b1000 H
b110 I
1%
#1640000
0%
#1645000
b11 1
b11 G
b11 K
b11 X
15
b1010 H
b1000 I
1%
#1650000
0%
#1655000
b100 1
b100 G
b100 K
b100 X
15
b1 H
b1010 I
1%
#1660000
0%
#1665000
14
b0 1
b0 G
b0 K
b0 X
05
b10 H
b1 I
1%
#1670000
b1100 M
b1100 R
b1100 V
b1001000000000000 P
b1001000000000000 Z
0%
#1675000
15
04
b100 H
b10 I
1%
#1680000
0%
#1685000
b1 1
b1 G
b1 K
b1 X
15
b110 H
b100 I
1%
#1690000
0%
#1695000
b10 1
b10 G
b10 K
b10 X
15
b1000 H
b110 I
1%
#1700000
0%
#1705000
b11 1
b11 G
b11 K
b11 X
15
b1010 H
b1000 I
1%
#1710000
0%
